Workbook

Sheet Coffee Audit
A1: Date | B1: City | C1: Cafe_Name | D1: Coffee_Name | E1: Producer_Farm | F1: Origin | G1: Varietal | H1: Process | I1: Roast_Level | J1: Brew_Method | K1: Dose_g | L1: Yield_g | M1: Ratio | N1: Water_Temp_C | O1: Bloom | P1: Grinder | Q1: Price_SGD | R1: Official_Notes | S1: Your_Verdict | T1: Technical_Enrichment | U1: Visit_Context | V1: Source | W1: Gesha_Alert
A2: 46025 | B2: Ubud, Bali | C2: Seniman Coffee Studio | D2: Bali Karana Kintamanis | E2: Unknown | F2: Kintamani, Bali | G2: Unknown | H2: Natural | I2: Light | J2: Filter | K2: Unknown | L2: Unknown | M2: Unknown | N2: Unknown | O2: Unknown | P2: Unknown | Q2: Unknown | R2: Clean citrus; floral | S2: Excellent clarity for a natural process; clean citrus and floral notes. | T2: Natural processing contributed mild fruit-forward esters with relatively clean finish; foundational exposure to local Indonesian origins. | U2: Bali family trip | V2: Merged (Gemini + ChatGPT) | W2: =IF(OR(ISNUMBER(SEARCH("gesha",G2)),ISNUMBER(SEARCH("geisha",G2))),"⭐ GESHA","")
A3: 46026 | B3: Ubud, Bali | C3: Seniman Coffee Studio | D3: Sulawesi Toraja | E3: Unknown | F3: Sulawesi, Indonesia | G3: Unknown | H3: Wet-Hulled | I3: Medium | J3: Pour-over | K3: Unknown | L3: Unknown | M3: Unknown | N3: Unknown | O3: Unknown | P3: Unknown | Q3: Unknown | R3: Cocoa; earthy structures | S3: Heavy body with rich cocoa and earthy notes; low acidity; dense mouthfeel. | T3: Classic Giling Basah wet-hulled process emphasized earthy compounds and syrupy mouthfeel; structural density confirmed. | U3: Bali family trip | V3: Merged (Gemini + ChatGPT) | W3: =IF(OR(ISNUMBER(SEARCH("gesha",G3)),ISNUMBER(SEARCH("geisha",G3))),"⭐ GESHA","")
A4: 46026 | B4: Ubud, Bali | C4: Seniman Coffee Studio | D4: House Blend | E4: Unknown | F4: Unknown | G4: Unknown | H4: Unknown | I4: Espresso Roast | J4: Piccolo | K4: Unknown | L4: Unknown | M4: Unknown | N4: Unknown | O4: Unknown | P4: Unknown | Q4: Unknown | R4: Balanced | S4: Great milk integration; standard espresso + milk calibration. | T4: Baseline milk pairing; milk fats softened acidity and amplified sweetness and body. | U4: Bali family trip | V4: Merged (Gemini + ChatGPT) | W4: =IF(OR(ISNUMBER(SEARCH("gesha",G4)),ISNUMBER(SEARCH("geisha",G4))),"⭐ GESHA","")
A5: 46063 | B5: Singapore | C5: Kyuukei Coffee | D5: Kenya Kiamugumo AA | E5: New Ngariama Farmer's Cooperative Society | F5: Kiamugumo, Murang'a County, Kenya | G5: SL28 / SL34 | H5: Washed | I5: Unknown | J5: Pour-over (Flat-Bottom) | K5: 15 | L5: 240 | M5: 1:16 | N5: 93 | O5: Unknown | P5: 120mm Hybrid Burr | Q5: 8 | R5: Blackcurrant, Lemon, Citrus Zest, Mineral Finish | S5: Extremely clean and structured — classic Kenyan profile. Bright blackcurrant acidity layered with lemon and light white grape sweetness. Clarity was the standout: no fermentation noise, no muddiness — precise, well-executed extraction. Compelling demonstration of how a well-processed washed coffee performs when roasted and brewed correctly. Phosphoric acid signature fully confirmed across all phases. | T5: 120mm hybrid burr grinder delivered uniform particle distribution; flat-bottom pour-over geometry ensured even extraction across the full puck. 93°C water temp and 1:16 lean ratio preserved SL28/SL34 phosphoric acid clarity without over-extracting into bitterness. Brew time 2:45 consistent with controlled drawdown on flat-bottom geometry. Kenyan phosphoric acid and anthocyanin-driven blackcurrant notes are varietal signatures of Scott Laboratories SL28/SL34 genetics. | U5: Solo visit — early archive period, first Kyūkei filter audit | V5: Direct observation + infographic + Google review (10 Feb 2026) | W5: =IF(OR(ISNUMBER(SEARCH("gesha",G5)),ISNUMBER(SEARCH("geisha",G5))),"⭐ GESHA","")
A6: 46082 | B6: Mumbai | C6: Subko Coffee Roasters | D6: Project Pearl Ratnagiri | E6: Ratnagiri Estate | F6: India | G6: Unknown | H6: Anaerobic Natural | I6: Light (Agtron 89) | J6: Filter | K6: Unknown | L6: Unknown | M6: Unknown | N6: Unknown | O6: Unknown | P6: Unknown | Q6: Unknown | R6: Unknown | S6: Clean and balanced; interesting but restrained anaerobic expression. | T6: Very light roast (Agtron 89) suppressed ester development despite anaerobic process; muted expected fermented intensity. | U6: Mumbai café exploration | V6: Merged (Gemini + ChatGPT) | W6: =IF(OR(ISNUMBER(SEARCH("gesha",G6)),ISNUMBER(SEARCH("geisha",G6))),"⭐ GESHA","")
A7: 46089 | B7: Mumbai | C7: Grey Soul Coffee Roasters | D7: Raspberry in Loop - Zoya Estate | E7: Zoya Estate | F7: India | G7: Unknown | H7: Multi-stage Anaerobic | I7: Medium | J7: Filter | K7: Unknown | L7: Unknown | M7: Unknown | N7: Unknown | O7: Unknown | P7: Unknown | Q7: Unknown | R7: Chocolate | S7: Heavy body; over-smoothed expression muted brightness and terroir. | T7: Higher development in medium roast reduced aggressive fruit acidity; heavy multi-stage fermentation suppressed terroir expression. | U7: Mumbai café exploration | V7: Merged (Gemini + ChatGPT) | W7: =IF(OR(ISNUMBER(SEARCH("gesha",G7)),ISNUMBER(SEARCH("geisha",G7))),"⭐ GESHA","")
A8: 46099 | B8: Singapore | C8: Narrative Coffee Stand | D8: Finca La Siberia | E8: Unknown | F8: El Salvador | G8: Pacamara | H8: Natural | I8: Light | J8: Pour-over | K8: Unknown | L8: Unknown | M8: Unknown | N8: Unknown | O8: Unknown | P8: Unknown | Q8: Unknown | R8: Unknown | S8: Stewed apples; Apricot; Pu'er tea — Aanya's first specialty filter experience. | T8: Natural Pacamara generated beginner-friendly fruit esters and approachable sweetness; large Pacamara bean size aided even extraction. | U8: Father-daughter coffee exploration | V8: ChatGPT only | W8: =IF(OR(ISNUMBER(SEARCH("gesha",G8)),ISNUMBER(SEARCH("geisha",G8))),"⭐ GESHA","")
A9: 46099 | B9: Singapore | C9: Narrative Coffee Stand | D9: El Puente | E9: Unknown | F9: Honduras | G9: Catuai | H9: Washed | I9: Medium-Light | J9: Espresso | K9: Unknown | L9: Unknown | M9: Unknown | N9: Unknown | O9: Unknown | P9: Unknown | Q9: Unknown | R9: Unknown | S9: Black cherry; Apricot; Pecan — ordered for espresso contrast. | T9: Washed Central American espresso balanced nutty sweetness and fruit acidity; Catuai's consistent cell structure aided uniform extraction. | U9: Father-daughter coffee exploration | V9: ChatGPT only | W9: =IF(OR(ISNUMBER(SEARCH("gesha",G9)),ISNUMBER(SEARCH("geisha",G9))),"⭐ GESHA","")
A10: 46099 | B10: Singapore | C10: ASK Coffee Roastery | D10: Honduras Masaguara (S13) | E10: Unknown | F10: Honduras | G10: Catuai / Caturra | H10: Washed Co-Ferment | I10: Light | J10: Pour-over | K10: Unknown | L10: Unknown | M10: Unknown | N10: Unknown | O10: Unknown | P10: Unknown | Q10: 15 | R10: Lychee; Brandy; Honeydew; Milk Chocolate | S10: Premium but memorable; highly complex tropical profile. | T10: Co-fermentation amplified tropical ester complexity; co-ferment substrates introduced lychee lactones and brandy-like ethyl esters. | U10: Father-daughter coffee exploration | V10: ChatGPT only | W10: =IF(OR(ISNUMBER(SEARCH("gesha",G10)),ISNUMBER(SEARCH("geisha",G10))),"⭐ GESHA","")
A11: 46099 | B11: Singapore | C11: ASK Coffee Roastery | D11: House Blend | E11: Unknown | F11: Unknown | G11: Unknown | H11: Unknown | I11: Unknown | J11: Magic (Ristretto Milk) | K11: Unknown | L11: Unknown | M11: Unknown | N11: Unknown | O11: Unknown | P11: Unknown | Q11: Unknown | R11: Unknown | S11: Contrast milk calibration; excellent concentrated cocoa expression. | T11: Ristretto milk extraction increased sweetness density and concentrated cocoa compounds through reduced water content. | U11: Father-daughter coffee exploration | V11: ChatGPT only | W11: =IF(OR(ISNUMBER(SEARCH("gesha",G11)),ISNUMBER(SEARCH("geisha",G11))),"⭐ GESHA","")
A12: 46103 | B12: Singapore | C12: Apartment (Selegie Rd) | D12: Colombia Don Gallego - Wush Wush | E12: Don Gallego | F12: Colombia | G12: Wush Wush | H12: Washed | I12: Light | J12: Pour-over (Flat-Bottom) | K12: Unknown | L12: Unknown | M12: 1:17 | N12: Unknown | O12: Unknown | P12: Unknown | Q12: Unknown | R12: Tea-like | S12: Incredible tea-like clarity; transparent floral expression. | T12: Lean 1:17 ratio maximized aromatic separation; Wush Wush's Ethiopian-lineage genetics produced delicate phenolic and floral complexity. | U12: Solo specialty calibration | V12: Merged (Gemini + ChatGPT) | W12: =IF(OR(ISNUMBER(SEARCH("gesha",G12)),ISNUMBER(SEARCH("geisha",G12))),"⭐ GESHA","")
A13: 46105 | B13: Singapore | C13: Kyuukei Coffee | D13: Kenya Ndiaini AA | E13: Unknown | F13: Kenya | G13: SL28 / SL34 / Ruiru 11 | H13: Washed | I13: Unknown | J13: Pour-over | K13: Unknown | L13: Unknown | M13: Unknown | N13: Unknown | O13: Unknown | P13: Unknown | Q13: 9 | R13: Redcurrant; Elderflower; Lemon; Apricot | S13: Acidic and interesting; well balanced; high clarity. | T13: Ruiru 11 introduced structural body alongside classic SL28/SL34 brightness; further Kenyan terroir depth confirmed. | U13: Solo specialty calibration | V13: Merged (Gemini + ChatGPT) | W13: =IF(OR(ISNUMBER(SEARCH("gesha",G13)),ISNUMBER(SEARCH("geisha",G13))),"⭐ GESHA","")
A14: 46106 | B14: Singapore | C14: Agora Coffee | D14: Nicaragua Matagalpa - Finca La Virgen | E14: Finca La Virgen | F14: Nicaragua | G14: Unknown | H14: Fully Washed | I14: Espresso Roast | J14: Flat White | K14: Unknown | L14: Unknown | M14: Unknown | N14: Unknown | O14: Unknown | P14: Unknown | Q14: Unknown | R14: Caramel; Chocolate; Red Apple | S14: Solid milk beverage; clean apple acidity preserved in milk integration. | T14: Fully washed Central American profile preserved clean malic acidity in milk; espresso roast development amplified caramel Maillard notes. | U14: Solo specialty calibration | V14: Merged (Gemini + ChatGPT) | W14: =IF(OR(ISNUMBER(SEARCH("gesha",G14)),ISNUMBER(SEARCH("geisha",G14))),"⭐ GESHA","")
A15: 46108 | B15: Singapore | C15: Agora Coffee | D15: Ethiopia Yirgacheffe Beloya | E15: Beloya | F15: Yirgacheffe, Ethiopia | G15: Heirloom | H15: Natural | I15: Filter Roast | J15: V60 | K15: 15 | L15: 220 | M15: 1:14.6 | N15: Unknown | O15: Unknown | P15: Mahlkönig EK43 | Q15: Unknown | R15: Blackcurrant; Strawberry; White Floral | S15: Bright, floral, and distinct strawberry; classic natural Ethiopian profile. | T15: EK43 98mm flat burrs reduced fines and preserved clarity despite natural processing; 1:14.6 ratio retained fruity body. | U15: Solo specialty calibration | V15: Merged (Gemini + ChatGPT) | W15: =IF(OR(ISNUMBER(SEARCH("gesha",G15)),ISNUMBER(SEARCH("geisha",G15))),"⭐ GESHA","")
A16: 46109 | B16: Singapore | C16: Tiong Hoe Specialty Coffee | D16: Brazil Mogiana | E16: Unknown | F16: Mogiana, Brazil | G16: Unknown | H16: Natural | I16: Medium | J16: Pour-over | K16: 15 | L16: 225 | M16: 1:15 | N16: Unknown | O16: Unknown | P16: Unknown | Q16: 8 | R16: Red Dates; Chocolates; Honey | S16: Chocolate-heavy and satisfying; classic dense Brazilian profile. | T16: Tighter 1:15 ratio increased body and amplified Maillard-derived caramel sweetness; medium roast caramelized sugars without losing origin character. | U16: Solo specialty calibration | V16: Merged (Gemini + ChatGPT) | W16: =IF(OR(ISNUMBER(SEARCH("gesha",G16)),ISNUMBER(SEARCH("geisha",G16))),"⭐ GESHA","")
A17: 46109 | B17: Singapore | C17: Tiong Hoe Specialty Coffee | D17: Smoky Quartz Blend | E17: Unknown | F17: Brazil + India | G17: Unknown | H17: Unknown | I17: Unknown | J17: Piccolo Latte | K17: Unknown | L17: Unknown | M17: Unknown | N17: Unknown | O17: Unknown | P17: Unknown | Q17: 5.1 | R17: Dark Chocolates; Hazelnut; Smoky | S17: Strong milk side calibration; excellent concentrated cocoa expression. | T17: Low milk volume in piccolo format concentrated cocoa and hazelnut compounds; cross-origin blend leveraged Indian robusta structural density. | U17: Solo specialty calibration | V17: ChatGPT only | W17: =IF(OR(ISNUMBER(SEARCH("gesha",G17)),ISNUMBER(SEARCH("geisha",G17))),"⭐ GESHA","")
A18: 46110 | B18: Singapore | C18: Asylum Coffeehouse | D18: Peru Cajamarca Gesha (Iced) | E18: Wilder Garcia | F18: Cajamarca, Peru | G18: Gesha | H18: Washed | I18: Medium | J18: Iced Pour-over | K18: 15 | L18: 240 | M18: 1:16 | N18: 92.5 | O18: Unknown | P18: Option-O Lagom P64 | Q18: 11 | R18: Jasmine; Caramel; Lime; Cacao Nibs | S18: Super floral and elegant; flash-chilled expression of Gesha purity. | T18: Flash-chilled extraction via Option-O Lagom P64 preserved volatile floral monoterpenes (linalool); cold dilution stabilized aromatic compounds. | U18: Solo specialty calibration | V18: ChatGPT only | W18: =IF(OR(ISNUMBER(SEARCH("gesha",G18)),ISNUMBER(SEARCH("geisha",G18))),"⭐ GESHA","")
A19: 46113 | B19: Singapore | C19: Maxi Coffee Bar | D19: La Laja | E19: James Fernandez | F19: Cauca, Colombia | G19: Sudan Rume | H19: Washed | I19: Light | J19: Pour-over (Flat-Bottom) | K19: 15 | L19: 230 | M19: 1:15.3 | N19: 90-92 | O19: Unknown | P19: FM Grinder 120mm Flat Burr / Timemore Sculptor 078 | Q19: 9 | R19: Raspberry; Nectarine; Floral | S19: Nectarine and raspberry extremely clear; barista sophistication superb; technical milestone. | T19: 120mm flat burr geometry maximized uniform particle distribution; flat-bottom brewer enhanced sweetness while preserving Sudan Rume's rare genetic clarity. | U19: CBD lunch calibration | V19: Merged (Gemini + ChatGPT) | W19: =IF(OR(ISNUMBER(SEARCH("gesha",G19)),ISNUMBER(SEARCH("geisha",G19))),"⭐ GESHA","")
A20: 46113 | B20: Singapore | C20: Lume Café | D20: Corpachi Panama Geisha | E20: Corpachi | F20: Boquerón, Chiriquí, Panama | G20: Geisha | H20: Red Honey | I20: Filter Roast | J20: V60 | K20: Unknown | L20: Unknown | M20: 1:15 | N20: 90 + 70 | O20: Unknown | P20: Mahlkönig EK43 | Q20: 12 | R20: Mandarin Candy; Jasmine; Apricot | S20: Clearly perceived apricot and structured sweetness. | T20: Dual-temperature extraction balanced aromatics and body in honey-process Geisha; red honey partial mucilage retention amplified structured sweetness. | U20: Rainy CBD lunch calibration | V20: ChatGPT only | W20: =IF(OR(ISNUMBER(SEARCH("gesha",G20)),ISNUMBER(SEARCH("geisha",G20))),"⭐ GESHA","")
A21: 46117 | B21: Singapore | C21: Asylum Coffeehouse | D21: Castillo Watermelon (Jairo Arcila) | E21: Jairo Arcila | F21: Armenia, Quindío, Colombia | G21: Castillo | H21: Washed Co-Ferment (Watermelon Anaerobic) | I21: Unknown | J21: Pour-over (V60) | K21: 15 | L21: 225 | M21: 1:15 | N21: 90 + 70 | O21: Unknown | P21: Mahlkönig EK43 | Q21: 12.5 | R21: Watermelon; Mint; Lime; Chocolate | S21: Distinct fruit-forward expression; sweetness layered rather than sharp; experimental but controlled. | T21: Watermelon co-fermentation enhanced volatile ester complexity; dual-temperature extraction preserved layered aromatic architecture. | U21: Father-daughter coffee session | V21: Merged (Gemini + ChatGPT) | W21: =IF(OR(ISNUMBER(SEARCH("gesha",G21)),ISNUMBER(SEARCH("geisha",G21))),"⭐ GESHA","")
A22: 46117 | B22: Singapore | C22: Asylum Coffeehouse | D22: Peru Gesha (Wilder Garcia) | E22: Wilder Garcia | F22: Jaén, Peru | G22: Gesha | H22: Washed | I22: Filter Roast | J22: Pour-over (V60) | K22: 15 | L22: 225 | M22: 1:15 | N22: 90 + 70 | O22: Unknown | P22: Mahlkönig EK43 | Q22: 12.5 | R22: Jasmine; Caramel; Lime; Cacao Nibs | S22: Clean, structured, high-clarity cup; apricot-like sweetness and excellent structure. | T22: Dual-temperature extraction engineered aromatic separation and body control; Gesha genetics delivered intrinsic phenolic complexity with minimal processing interference. | U22: Father-daughter coffee session | V22: Merged (Gemini + ChatGPT) | W22: =IF(OR(ISNUMBER(SEARCH("gesha",G22)),ISNUMBER(SEARCH("geisha",G22))),"⭐ GESHA","")
A23: 46120 | B23: Singapore | C23: Maxi Coffee Bar | D23: La Villa #1 | E23: Eduard Gaviria | F23: Huila, Colombia | G23: Papayo | H23: Natural | I23: Unknown | J23: Pour-over (Flat-Bottom) | K23: 15 | L23: 225 | M23: 1:15 | N23: Unknown | O23: Unknown | P23: Timemore Sculptor 078 | Q23: 9 | R23: Stewed Forest Berries; Grape; Black Forest Cake | S23: Dense fruit profile with rounded sweetness. | T23: Flat-bottom geometry and tight 1:15 ratio emphasized body; Papayo varietal's high sugar content amplified by natural processing into rich fruit-cake profile. | U23: Lunch catch-up with Yichen | V23: ChatGPT only | W23: =IF(OR(ISNUMBER(SEARCH("gesha",G23)),ISNUMBER(SEARCH("geisha",G23))),"⭐ GESHA","")
A24: 46130 | B24: Johor Bahru | C24: Clod Coffee Bar & Roasters | D24: Hacienda La Florida | E24: Unknown | F24: Unknown | G24: Typica Mejorado | H24: Anaerobic Washed | I24: Unknown | J24: Origami (Conical) | K24: 18 | L24: 277 | M24: 1:15.4 | N24: Unknown | O24: 42g / 30s (1:2.3) | P24: Mahlkönig EK Omnia | Q24: 11.08 | R24: Lemon verbena; Red plum; Citronella; Hibiscus | S24: Excellent. Lime when hot, distinct plum as it cooled. | T24: EK Omnia precision grind and Origami conical drove extreme clarity; thermal phase shift perfectly isolated citric-to-malic acid transition (lime → plum). | U24: Unknown | V24: Gemini only | W24: =IF(OR(ISNUMBER(SEARCH("gesha",G24)),ISNUMBER(SEARCH("geisha",G24))),"⭐ GESHA","")
A25: 46136 | B25: Singapore | C25: Agora Coffee | D25: Brazil Santuário Sul | E25: Unknown | F25: Carmo de Minas, Brazil | G25: Unknown | H25: Natural Fermentation | I25: Light-Medium | J25: V60 | K25: 16 | L25: 224 | M25: 1:14 | N25: 95 | O25: Unknown | P25: Mahlkönig EK43 | Q25: Unknown | R25: Blackcurrant; Black Cherry; Dark Chocolate | S25: Full body; prominent blackcurrant; clear chocolaty finish. | T25: Tight 1:14 ratio engineered maximum body; EK43 98mm burrs maintained clarity to keep fermented natural fruit clean and non-bitter. | U25: Midday specialty calibration | V25: Merged (Gemini + ChatGPT) | W25: =IF(OR(ISNUMBER(SEARCH("gesha",G25)),ISNUMBER(SEARCH("geisha",G25))),"⭐ GESHA","")
A26: 46148 | B26: Singapore | C26: Nylon Coffee Roasters | D26: Brazil FAF Organic | E26: Unknown | F26: Brazil | G26: Arara | H26: Natural | I26: Filter Roast | J26: xBloom (Flat-Bottom) | K26: Unknown | L26: Unknown | M26: 1:17 | N26: Unknown | O26: Unknown | P26: Mahlkönig EK Omnia | Q26: 7.5 | R26: Red Apple; Cherry; Raisin; Milk Chocolate | S26: Solid body with crisp green apple (malic) front, resolving into smooth milk chocolate finish. | T26: High-quality Arara natural processing yielded excellent structural body while maintaining crisp malic acidity; xBloom flat-bottom avoided heavy fermentation mud. | U26: Unknown | V26: Gemini only | W26: =IF(OR(ISNUMBER(SEARCH("gesha",G26)),ISNUMBER(SEARCH("geisha",G26))),"⭐ GESHA","")
A27: 46148 | B27: Singapore | C27: Nylon Coffee Roasters | D27: Brazil Serra dos Ciganos | E27: Unknown | F27: Brazil | G27: Catucai 24/137 | H27: Natural | I27: Espresso Roast | J27: Flat White | K27: Unknown | L27: Unknown | M27: Unknown | N27: Unknown | O27: Unknown | P27: Unknown | Q27: Unknown | R27: Sultana; Dried Apricot; Praline; Roasted Hazelnut | S27: Good cup with pleasant lingering sweet aftertaste. | T27: Milk fats bound perfectly with natural processed espresso; Catucai 24/137 high-density bean structure created long, comforting finish. | U27: Unknown | V27: Gemini only | W27: =IF(OR(ISNUMBER(SEARCH("gesha",G27)),ISNUMBER(SEARCH("geisha",G27))),"⭐ GESHA","")
A28: 46149 | B28: Singapore | C28: Nylon Coffee Roasters | D28: Ethiopia Banko Gotiti | E28: Unknown | F28: Ethiopia | G28: Heirloom | H28: Washed | I28: Filter Roast | J28: xBloom (Flat-Bottom) | K28: Unknown | L28: Unknown | M28: 1:17 | N28: Unknown | O28: Unknown | P28: Mahlkönig EK Omnia | Q28: 8.5 | R28: Lemonade; Raspberry; Peach; Bergamot | S28: Lemon front, heavy melon mid-cup, fading into clean white tea finish. | T28: 1:17 lean ratio isolated volatile citric acids; xBloom flat-bottom geometry stabilized mid-cup sugars before clean tannin-forward white tea finish. | U28: Unknown | V28: Gemini only | W28: =IF(OR(ISNUMBER(SEARCH("gesha",G28)),ISNUMBER(SEARCH("geisha",G28))),"⭐ GESHA","")
A29: 46149 | B29: Singapore | C29: Nylon Coffee Roasters | D29: Nicaragua Buena Vista | E29: Unknown | F29: Nicaragua | G29: Parainema | H29: Natural Anaerobic | I29: Espresso Roast | J29: Single Espresso | K29: Unknown | L29: Unknown | M29: ~1:2 | N29: Unknown | O29: Unknown | P29: Unknown | Q29: Unknown | R29: Chiku; Stewed Cherry; Dried Apricot; Brazil Nut | S29: Thick, syrupy body. Highly fermented, savory/not sweet, very long lingering finish. | T29: Anaerobic fermentation metabolized sugars into complex savory esters; 9-bar pressure emulsification drove heavy oil-based viscosity and extended aftertaste. | U29: Unknown | V29: Gemini only | W29: =IF(OR(ISNUMBER(SEARCH("gesha",G29)),ISNUMBER(SEARCH("geisha",G29))),"⭐ GESHA","")
A30: 46150 | B30: Singapore | C30: Alchemist (Raffles Place) | D30: El Morito | E30: Unknown | F30: Colombia | G30: Marshell | H30: Washed | I30: Filter Roast | J30: V60 Pour-over (Conical) | K30: 15 | L30: 240 | M30: 1:16 | N30: Unknown | O30: Unknown | P30: Mahlkönig EK43S (98mm Flat Burr) | Q30: Unknown | R30: Yellow Plum; Orange; Cane Sugar | S30: Simultaneous citric-malic acid overlap with integrated cane sugar — smooth and refreshing with excellent mid-palate juiciness. Confirmed: I love this bean. | T30: EK43S 98mm flat burrs + V60 conical at 1:16 delivered perfect dual-acid integration (citric orange + malic plum) without single-note dominance. Sucrose extraction at 1:16 bridged acid structure into clean cane sugar finish. Marshell is an extremely rare Colombian varietal — natural mutation prized for simultaneous citric-malic acid duality. | U30: Solo visit — Alchemist Raffles Place | V30: Master CSV (hari_coffee_audit_master_2026) | W30: =IF(OR(ISNUMBER(SEARCH("gesha",G30)),ISNUMBER(SEARCH("geisha",G30))),"⭐ GESHA","")
A31: 46154 | B31: Singapore | C31: Kurasu | D31: Indonesia Frinsa Estate | E31: Frinsa Estate | F31: West Java, Indonesia | G31: Local Varietals | H31: Extended Fermentation Honey | I31: Light | J31: Pour-over (Hario Alpha — Flat-Bottom) | K31: 15 | L31: 225 | M31: 1:16 | N31: 80 → 95 → 80 | O31: Unknown | P31: Mahlkönig EK43S (98mm Flat Burr) | Q31: 9.5 | R31: Floral aroma; Stewed Strawberries; Grapefruit; Brown Sugar; Black Tea | S31: Floral taste with a sweet coating on the tongue that gradually sticks and fades off cleanly — sugar and tea aftertaste. Well-executed Indonesian honey with unusual clarity for the origin. | T31: Multi-temperature pour (80→95→80°C) with Hario Alpha flat-bottom perfectly managed heavy honey-process mucilage sugars — clear floral extraction at lower temps, dissolving jammy mucilage at peak heat, finishing cleanly. Extended fermentation honey adds structured sweetness without heavy ferment-funk. First Indonesian-mainland entry in archive (distinct from Bali entries). | U31: Solo visit — Kurasu Singapore | V31: Master CSV (hari_coffee_audit_master_2026) | W31: =IF(OR(ISNUMBER(SEARCH("gesha",G31)),ISNUMBER(SEARCH("geisha",G31))),"⭐ GESHA","")
A32: 46155 | B32: Singapore | C32: The Community Coffee (Hamilton) | D32: Jose Mancia Honduras | E32: Jose Mancia | F32: Honduras | G32: Typica | H32: Natural | I32: Filter Roast | J32: Pour-over (Hario Switch — Immersion/Percolation) | K32: 15 | L32: 255 | M32: 1:17 | N32: Unknown | O32: Unknown | P32: Mahlkönig EK43 (98mm Flat Burr) | Q32: 9 | R32: Kiwi; Oolong Tea; Chocolate Truffle | S32: Pretty good. Kiwi and oolong tea style — full bodied. Short finish with slight hints of chocolate. Clean and approachable natural without heavy fermentation noise. | T32: Typica inherent lipid clarity + raised-bed drying produced clean tea-structure body. EK43 98mm flat burrs + Hario Switch immersion phase stabilised full mouthfeel at lean 1:17. Short finish consistent with 15-days-off-roast volatile taper — kiwi and oolong top notes fade rapidly. Honduras Typica at altitude expresses tea-like clarity atypical of natural-process expectations. | U32: Solo visit — The Community Coffee Hamilton | V32: Master CSV (hari_coffee_audit_master_2026) | W32: =IF(OR(ISNUMBER(SEARCH("gesha",G32)),ISNUMBER(SEARCH("geisha",G32))),"⭐ GESHA","")
A33: 46157 | B33: Singapore | C33: Alchemist (Ocean Financial Centre) | D33: Ijen Laurina | E33: Ijen Plateau | F33: East Java, Indonesia | G33: Hybrid Laurina | H33: Anaerobic Natural | I33: Light | J33: V60 Pour-over (Conical) | K33: 15 | L33: 240 | M33: 1:16 | N33: 90 | O33: Unknown | P33: Mahlkönig EK43S (98mm Flat Burr) | Q33: 8.5 | R33: Hibiscus; Red Apple; Hawthorn | S33: Felt hibiscus hot. Mid temp showed apple paste. Cooled to a honeyed character. Full bodied. Textbook style flavours — definitely a good one. Clean progressive thermal arc. | T33: 90°C brew temp suppressed lactic ester over-extraction while preserving volatile anthocyanin hibiscus esters. Laurina low-caffeine mutation allows intrinsic sucrose to express as clean honeyed finish without alkaloid bitterness. Anaerobic Natural transformed malic acid into jammy apple paste mid-phase. First Hybrid Laurina varietal in archive — new genetic category unlocked. Hibiscus = anthocyanin; Apple paste = malic lactone; Honey = sucrose at sub-50°C. | U33: Solo visit — Alchemist Ocean Financial Centre | V33: Master CSV (hari_coffee_audit_master_2026) | W33: =IF(OR(ISNUMBER(SEARCH("gesha",G33)),ISNUMBER(SEARCH("geisha",G33))),"⭐ GESHA","")
A34: 46158 | B34: Singapore | C34: Fluid Collective | D34: El Obraje | E34: El Obraje | F34: Huila, Colombia | G34: Gesha | H34: Washed | I34: Light | J34: Flatbed Dripper (Flat-Bottom) | K34: 15 | L34: 230 | M34: 1:15.3 | N34: 92 | O34: Unknown | P34: Option-O Lagom P64 (64mm Flat Burr) | Q34: 14 | R34: Mango; Orange Blossom; Nectarine; Honey | S34: Damn the taste so nice — the orange nectarine finishing with that honey is terrific. Love this one. So far my favourite. Honey sweetness lingers and taste changes as temperature cools. Best Gesha washed in archive at time of logging. | T34: Lagom P64 64mm flat burrs deliver near-unimodal particle distribution — same hardware platform as Asylum Coffeehouse entries, enabling pure terroir delta comparison between Colombia Gesha (El Obraje, Huila) and Peru Gesha (Wilder Garcia, Jaén). 92°C at 1:15.3 maximised linalool floral ester retention while stabilising malic acid mango-nectarine backbone. Flat-bottom eliminated bypass and ensured even bed saturation — critical for preserving fragile Gesha aromatics. Honey finish = sucrose preserved at washed-process mucilage removal stage. | U34: Solo visit — FLUID Singapore | V34: Master CSV (hari_coffee_audit_master_2026) | W34: =IF(OR(ISNUMBER(SEARCH("gesha",G34)),ISNUMBER(SEARCH("geisha",G34))),"⭐ GESHA","")
A35: 46161 | B35: Singapore | C35: Pocket by Flip (Flip Coffee Roasters) | D35: Ecuador La Papaya | E35: La Papaya Farm | F35: Loja, Ecuador | G35: Geisha | H35: Washed | I35: Light | J35: Filter Hot — Flat-Bottom (Hario Alpha) | K35: 15 | L35: 225 | M35: 1:15 | N35: 92 → 75 → 92 | O35: Unknown | P35: Mahlkönig CORE (54mm Flat Burr) | Q35: 18 | R35: Fresh Apricot; Rooibos; Lemon Thyme; Toffee Apple | S35: Opening: tartaric apricot + rooibos aspalathin. Mid: thymol terpene coat — lipid-binding, persistent to midway. Cooling: malic apple shift + caramelised sucrose. Clean transparent fade. No linalool/jasmine — terpene-forward character distinct from Peru Geisha entries. Highest-altitude Geisha in archive at 2,100 MASL. | T35: Triple-temp cascade (92→75→92°C) on CORE 54mm flat burr + Hario Alpha flat-bottom preserved heat-sensitive thymol terpenes from 2,100 MASL Loja terroir. 75°C mid-pour is the critical terpene-stabilisation variable — thymol is lipid-binding and volatile above 80°C, so mid-temp pour is the architecture delivering the persistent midpalate coat. Ecuador Geisha = terpene-forward (Thymol/Aspalathin) clearly differentiated from linalool-forward Peru Geisha (Jasmine/Citric). First Ecuador-origin entry in archive. | U35: Solo visit — Pocket by Flip, 30 Stevens Road | V35: Master CSV (hari_coffee_audit_master_2026) | W35: =IF(OR(ISNUMBER(SEARCH("gesha",G35)),ISNUMBER(SEARCH("geisha",G35))),"⭐ GESHA","")
A36: 46168 | B36: Singapore | C36: Zerah Roasters | D36: El Diviso — Caturra Chiroso (Ester Bomb) | E36: El Diviso Farm | F36: Huila, Colombia | G36: Caturra Chiroso | H36: Yeast Anaerobic Natural | I36: Filter Roast | J36: Flat-Bottom Dripper | K36: 15 | L36: 240 | M36: 1:16 | N36: 92 | O36: 38g / Unknown seconds | P36: DF64 Gen 2 (64mm Flat Burr — aftermarket upgrade) | Q36: 12 | R36: Passionfruit; Plum Wine; Mango | S36: Goddamn the smell is intense. Flavor burst — acid or strong flavor, super punchy. Passionfruit with enhanced fruit, funky. Plums. After cooling — sugars came out. Interesting. Strong flavor gone. Overall: funky, fermentation-driven. Processing-dominant cup. Three completely different cups in one — ester detonation hot, funk phase mid, mango sweetness cool. | T36: Yeast strains WLPU07 + LALVIN 71B at 96hr fermentation, pH 3.72, 100% anaerobic sealed tank (1.2 bar, 23.4°C) produced extreme ester complexity: γ-decalactone (passionfruit lactone) dominant hot, tartaric esters + acetic acid (plum wine/funk) mid, fructose ester chains (mango sweetness) cold. 1:16 lean ratio was critical safety valve — prevented cloying ester overload and enabled three-phase thermal tracking. Flat-bottom geometry amplified body and even bed saturation. DF64 Gen 2 with aftermarket 64mm flat burrs: first DF64 platform entry in archive. Caturra Chiroso = elongated cell structure, Geisha-adjacent clarity potential overridden by fermentation intensity. Yeast Anaerobic Natural distinct process category from Wild Anaerobic. | U36: Solo visit — Zerah Roasters, Singapore, 26 May 2026. Barista explained fermentation process, flat-bottom geometry rationale, 1:16 ratio decision in detail. Warm educational session on 2nd floor cosy space. Barista recommended Glyph Supply Co (Jurong). | V36: Infographic (Entry #025 Ester Bomb) + Google Maps review + Google review authored by Hari | W36: =IF(OR(ISNUMBER(SEARCH("gesha",G36)),ISNUMBER(SEARCH("geisha",G36))),"⭐ GESHA","")
A37: 46183 | B37: Singapore | C37: Nylon Coffee Roasters | D37: Colombia Juan Martin | E37: Banexport | F37: Colombia | G37: Red Striped Bourbon | H37: Washed | I37: Filter Roast | J37: xBloom (Flat-Bottom) | K37: Unknown | L37: Unknown | M37: 1:17 | N37: Unknown | O37: Unknown | P37: Mahlkönig EK Omnia (98mm Flat Burr) | Q37: 7.5 | R37: Berry, Red Plum, Nectarine, Orange Tea | S37: Orange-type aromatic afterfeel when hot — bright and encapsulating. Clearly fruity character throughout. Mellows cleanly as it cools; sugars emerge distinctly at mid-cool phase. Nice and light overall — 1:17 lean ratio working well on this varietal. | T37: EK Omnia 98mm flat burrs + xBloom flat-bottom geometry maintained body integrity at 1:17 lean ratio. Retail bag on shelf dated 10 Jun 2026 but filter batch roast date unconfirmed — cup behaviour (clean sugar emergence, well-integrated stone fruit at cool phase) is consistent with a properly rested lot of 10–21 days post-roast. Red Striped Bourbon sucrose density confirmed by clean sweetness at cool phase. | U37: Solo visit — office lunch break, 13:15 | V37: Direct observation + bag photo (retail stock) | W37: =IF(OR(ISNUMBER(SEARCH("gesha",G37)),ISNUMBER(SEARCH("geisha",G37))),"⭐ GESHA","")
A38: 46186 | B38: Singapore | C38: Kurasu | D38: Rwanda Nkara Soil Project Lot 1204 | E38: Nkara Soil Project | F38: Rwanda | G38: Red Bourbon | H38: Fully Washed | I38: Filter Roast | J38: V60 Pour-over (Conical) | K38: Unknown | L38: Unknown | M38: Unknown | N38: Unknown | O38: Unknown | P38: Mahlkönig EK43 (98mm Flat Burr) | Q38: 9.27 | R38: Floral aroma, taste of mandarin orange, baked apple and grapefruit, brown sugar-like sweetness and accompanying aftertaste | S38: Strong aftertaste with slight bitterness noted. Baked apple taste dominates and persists across all phases. Sugars emerge clearly on cooling — brown sugar sweetness confirmed at cool phase. Rated average. Rwanda Nkara terroir pushes more citrus-floral (mandarin/grapefruit) vs prior Rwanda entry at Twenty Grams (Entry #024) which was peach/stone fruit dominant. | T38: EK43 98mm flat burrs paired with conical V60 geometry — key hardware distinction vs prior Kurasu Frinsa entry. V60 conical creates faster flow rate and higher bypass risk vs flat-bottom; the slight bitterness is consistent with conical geometry allowing fine particles to over-extract at the drain. Washed Red Bourbon at altitude delivers classic Rwandan citric-malic duality (mandarin + baked apple). Baked apple dominance = malic acid thermally stabilised — persists across full thermal arc unlike volatile citric top notes which fade. Brown sugar aftertaste is sucrose retention signature of Red Bourbon genetics. | U38: Solo visit — 13 Jun 2026 | V38: Direct observation + bean card photo | W38: =IF(OR(ISNUMBER(SEARCH("gesha",G38)),ISNUMBER(SEARCH("geisha",G38))),"⭐ GESHA","")
A39: 46187 | B39: Singapore | C39: Keryi Coffee | D39: Colombia Finca La Esmaralda | E39: Finca La Esmaralda | F39: Colombia | G39: Gesha | H39: Honey | I39: Light Roast | J39: Hario Switch (Immersion/Percolation Hybrid) | K39: 15 | L39: 210 | M39: 1:14 | N39: 91 → 78 | O39: 60g (~4:1) | P39: Ditting 98mm flat burr | Q39: 15 | R39: Citrus, white florals, lychee, sugar-cane sweetness | S39: Smooth body throughout. Lychee & white florals lead in the hot phase — fragile linalool terpenes survived the tight 1:14 concentration. Citrus surfaces mid-cool as perceived sweetness rises; honey-derived sweetness rounds the cool-phase finish into progressive smoothness. Rated highly — a fine, relaxing Gesha. Clarity held; upper Gesha tier (cf. El Obraje washed favourite, Hiu Los Lajones honey Panama). | T39: Ditting 98mm flat burrs deliver lab-grade narrow particle distribution with minimal fines — the key variable licensing an aggressive 1:14 ratio without astringency. Descending pour (91°C bloom/first pour → 78°C final) uses temperature as a brake on the extraction tail: high heat early extracts volatile terpenes, acids & sugars; the cool final pour reaches target volume while suppressing late-stage chlorogenic-acid bitterness. Hario Switch valve-closed immersion develops honey-process mucilage sweetness & body evenly before percolative drain adds finish definition — conical geometry runs against the flat-bottom affinity but suits this process. | U39: Solo relaxation visit — Sunday 14 Jun 2026, 11 AM; barista-led brew interview (grinder/ratio/temp confirmed) | V39: Direct observation + menu photo + barista interview | W39: =IF(OR(ISNUMBER(SEARCH("gesha",G39)),ISNUMBER(SEARCH("geisha",G39))),"⭐ GESHA","")
A40: 46192 | B40: Singapore | C40: Corner Corner | D40: Malaysia My Liberica | E40: My Liberica (Jason Liew), Kulai, Johor | F40: Malaysia, Kulai, Johor | G40: Liberica (Coffea liberica) | H40: JH Natural (Jekyll & Hyde controlled fermentation - proprietary My Liberica process) | I40: Light | J40: Pour Over (filter) | K40: 13 | L40: 190 | M40: 1:14.6 | N40: 90-92 (steady throughout) | O40: Unknown | P40: Timemore (conical Gold burr, coarse) | Q40: 13 | R40: Root beer / Tropical fruit punch / Raspberry candy / Rambutan / Longan / Sarsi (roaster: One Half) | S40: Interesting and approachable - 'not so funky but different for sure'; picked out longan-type fruit. First non-arabica capture in the archive; landed as a positive novelty rather than rejected. | T40: First Liberica (Coffea liberica) and first Malaysia/Johor origin in archive; near-sea-level farm (26-30 MASL). Low 13g dose at ~1:14.6 ratio with steady 90-92C and a conical Timemore Gold burr deliberately tames Liberica's smoky-woody funk into a cleaner, longan-forward cup; the small dose + generous water dilutes intensity for legibility. NOTE: barista verbally cited ~1:16, but stated 13g:190g computes to 1:14.6. | U40: Roaster: One Half (light-roast filter program). Corner Corner is a vinyl-record listening bar/cafe; walls of LPs, warm low lighting, Japanese-style carafe-and-cup serve. Friday 19 June 2026, ~15:15. Rated awesome by Hari. | V40: Field audit (Claude) | W40: =IF(OR(ISNUMBER(SEARCH("gesha",G40)),ISNUMBER(SEARCH("geisha",G40))),"⭐ GESHA","")
A41: 46192 | B41: Singapore | C41: Equate | D41: Colombia Huila La Pradera | E41: La Pradera | F41: Colombia, Huila | G41: Gesha | H41: Washed | I41: Unknown | J41: Pour Over (Orea V4) | K41: 15 | L41: 210 | M41: 1:14 | N41: 90-92 (pours 1-2), 68-70 (pours 3-4) | O41: Unknown | P41: EK43 | Q41: 13 | R41: Peach Jam / Orange / Honey Sweetness | S41: Average - strong isolated peach note but jam/honey sweetness underdeveloped; suspects 1:15 ratio would have balanced acid/sweetness better | T41: Flat-burr EK43 (98mm) paired with flat-bottom Orea V4 geometry and a descending 90-92C to 68-70C thermal pulse profile; the 1:14 ratio (tighter than Hari's 1:15-1:17 default) front-loaded malic acid extraction (strong peach) while leaving honey/sweetness underdeveloped due to reduced dilution and low back-half temperature. | U41: 2nd-floor minimalist cafe; pastel interiors, spacious, dog-friendly; cakes-only food menu (banana cake); benchmark ambience per Hari. | V41: Field audit (Claude) | W41: =IF(OR(ISNUMBER(SEARCH("gesha",G41)),ISNUMBER(SEARCH("geisha",G41))),"⭐ GESHA","")
A42: 46194 | B42: Singapore | C42: Apartment (Jalan Riang) | D42: Colombia Javier Quintero | E42: Javier Quintero, Buena Vista Farm | F42: Inza, Cauca, Colombia | G42: Bourbon Aruzi | H42: Washed | I42: Light (Filter Roast) | J42: Pour-over (Hand Brew) | K42: 13 | L42: 220 | M42: 1:16.9 | N42: 95 | O42: Unknown | P42: Mahlkönig EK43 | Q42: 9.5 | R42: White peach; blackberry; jasmine | S42: White peach dominant, well-balanced; clean washed expression, very enjoyable | T42: High-temp (95C) and 1:16.9 ratio on EK43 flat burr favored extraction of volatile floral/peach esters (linalool, lactones) over heavier blackberry polyphenolics, producing a peach-forward, high-clarity cup. 200g bag roasted 15 June 2026 (6 days post-roast at time of visit). | U42: Sister branch of Apartment (Selegie Rd), located Jalan Riang, Serangoon Gardens. First visit to this branch. | V42: Field audit (Claude) | W42: =IF(OR(ISNUMBER(SEARCH("gesha",G42)),ISNUMBER(SEARCH("geisha",G42))),"⭐ GESHA","")
A43: 46198 | B43: Singapore | C43: PPP Coffee (Funan) | D43: Ethiopia Suke Quto | E43: Suke Quto Farm (Tesfaye Bekele) | F43: Ethiopia | G43: Welicho & Kurume (blend) | H43: Fully-Washed | I43: Light Filter Roast | J43: V60 Pour-over (Conical) | K43: 15 | L43: 225 | M43: 1:15 | N43: Unknown | O43: Unknown | P43: Mazzer MM (83mm Flat Burr) | Q43: 9 | R43: Nectarine, White Florals, Citrus | S43: Sharp unripe orange dominated all thermal phases — no floral lift, no mid-cool malic sweetness, no phase shift detected. Citric over-extraction signature suppressed linalool volatiles and sucrose emergence. Hardware execution miss — Guji terroir likely unrealised. Rated below average. | T43: Mazzer MM 83mm flat burrs produce wider fines distribution than 98mm reference tier; fine particle accumulation at V60 conical drain drove chlorogenic-acid over-extraction, presenting as persistent sharp citrus and blunting the Welicho & Kurume floral/nectarine terroir expression across the full thermal arc. Second V60 conical over-extraction pattern in archive (cf. Entry #31, Kurasu Rwanda). | U43: Solo visit — 25 Jun 2026; Funan mall location; bean card photographed; no barista consultation | V43: Direct observation + bean card photo + menu photo | W43: =IF(OR(ISNUMBER(SEARCH("gesha",G43)),ISNUMBER(SEARCH("geisha",G43))),"⭐ GESHA","")
A44: 46200 | B44: Singapore | C44: Apartment (Jalan Riang) | D44: China Yunnan Meng Hai | E44: Blang and Dai Family Farms | F44: Menghai, Xishuangbanna, Yunnan, China | G44: Purple Leaf Caturra | H44: Double Washed | I44: Light (Filter Roast) | J44: Pour-over (Hand Brew) | K44: 13 | L44: 215 | M44: 1:16.5 | N44: 95 | O44: 4-pour progressive ~30s intervals; Bloom 30g; to 120g (+90g); to 180g (+60g); to 215g (+35g). Descending pour volumes confirmed by barista. | P44: Mahlkönig EK43 | Q44: 9.5 | R44: Dried tangerine peel; red apple; pandan (origin card) / Dried orange peel; red apple; pandan (menu — discrepancy flagged) | S44: Bright vibrant opening (hot); crisp malic clarity; mellowed gracefully at cool with no dominant note; pandan as background aromatic binder; well-balanced; no bitterness; genuinely pleasant surprise for non-core-palate origin | T44: Double Washed process + EK43 flat burr uniformity produced exceptional acid clarity across all thermal phases; constant 95C 4-pour progressive with descending pour volumes (30g bloom → +90g → +60g → +35g) front-loaded solubles extraction then completed gently without bed agitation; Purple Leaf Caturra anthocyanin complexity confirmed at cool phase. | U44: Second visit to Apartment (Jalan Riang); Saturday 27 Jun 2026, 10:45am. Menu note: dried orange peel (menu) vs dried tangerine peel (origin card) — origin card used as authoritative. First Chinese-origin entry in archive (entry #36). | V44: Field audit (Claude) | W44: =IF(OR(ISNUMBER(SEARCH("gesha",G44)),ISNUMBER(SEARCH("geisha",G44))),"⭐ GESHA","")
A45: 46201 | B45: Singapore | C45: Keryi Coffee | D45: Ethiopia Urabeast G1 | E45: Unknown | F45: Uraga, Guji, Ethiopia | G45: 74110 / 74112 | H45: Mosto Fermentation | I45: Filter Roast | J45: Hario Switch (Immersion/Percolation Hybrid) | K45: 15 | L45: 210 | M45: 1:14 | N45: 88 → 70 | O45: Unknown | P45: Ditting 98mm flat burr | Q45: 13 | R45: Winey; Raspberry; Purple grapes | S45: First mosto fermentation entry in archive — process milestone. Bright raspberry and florals dominate hot phase; fruit esters volatile and immediate confirming correct low-entry-temp calibration at 88°C. Thermal transition mid-cool reveals progressive winey character as acetic compounds emerge post-ester dissipation. Purple grape ambiguous — raspberry clearly dominant throughout. Light-to-medium body with clean short finish consistent with 74110/74112 JARC varietal genetics. Fruity, controlled, process-honest expression. Rated excellent. | T45: 88°C descending to 70°C entry temp is deliberate suppression of acetic acid volatilisation — allows fruit esters to express cleanly before winey compounds dominate. Ditting 98mm flat burr uniformity protected raspberry ester clarity; 1:14 tight ratio on Hario Switch immersion built even body without over-extracting fermentation-derived acetic acids. 2-minute brew time limited lipid extraction keeping finish clean rather than syrupy. Mosto fermentation uses cherry pulp juice as fermentation medium — produces restrained winey complexity vs full natural while retaining dark fruit ester complexity. | U45: Solo visit — 28 Jun 2026, 10:30AM. Keryi return visit (Entry #31 ref: Colombia Finca La Esmaralda). First mosto fermentation process in archive. | V45: Field audit (Claude) — direct barista confirmation | W45: =IF(OR(ISNUMBER(SEARCH("gesha",G45)),ISNUMBER(SEARCH("geisha",G45))),"⭐ GESHA","")
A46: 46201 | B46: Singapore | C46: Asylum Coffeehouse | D46: Yellow Sudan Rume | E46: Felipe Arcila - Jardines Del Eden | F46: Pijiao, Quindío, Colombia | G46: Sudan Rume (Yellow) | H46: Extended Fermentation Natural (EF2) | I46: Filter Roast | J46: April Brewer (Flat-Bottom) | K46: 15 | L46: 240 | M46: 1:16 | N46: 90 | O46: 110g (first pour) → 240g (second pour) | P46: Option-O Lagom P64 | Q46: 14 | R46: Lemongrass, Vanilla, Red Fruits, Brown Sugar | S46: Hot phase: red fruits dominant, bright and acidic, light-to-medium body. Mid-cool: lemongrass clarifies as geraniol emerges; vanilla appears as background aromatic. Cool: brown sugar sweetness confirmed, mellowed, clean lingering finish with pleasant mouthfeel. Overall excellent — bright, fruity, balanced, varietal-honest. First Yellow Sudan Rume natural-process entry in archive. | T46: EF2 24-hour Grainpro aerobic fermentation at sub-22°C produced controlled ester development without acetic acid overproduction — cup reads bright and clean vs winey (contrast Entry #37 mosto). Red fruit dominance hot phase = ethyl butyrate/hexanoate fermentation esters. Lemongrass/geraniol mid-cool = Sudan Rume varietal-native genetic signature, not process-derived. Vanillin + brown sugar sucrose emerges sub-55°C at cool phase. April flat-bottom two-pour (110g + 130g) at 90°C maintained even bed saturation preserving delicate geraniol top notes. Three milestones: first Yellow Sudan Rume mutation in archive; first EF2 Extended Fermentation Natural process category; new producer Felipe Arcila / Jardines Del Eden. | U46: Solo visit — 28 Jun 2026, 11:06AM. Second stop of dual-session day (Entry #37 Keryi Coffee mosto fermentation same morning). Receipt SGD 14.00 confirmed. | V46: Field audit (Claude) — bean card + receipt + hardware photos | W46: =IF(OR(ISNUMBER(SEARCH("gesha",G46)),ISNUMBER(SEARCH("geisha",G46))),"⭐ GESHA","")
A47: 46203 | B47: Singapore | C47: 2050 Coffee | D47: Myanmar Arakan Mountain | E47: Asho Chin Coffee Association | F47: Magway, Myanmar | G47: Catimor | H47: Fully Washed & Honey | I47: Light Roast | J47: Automated Tap Dispenser (Filter) | K47: N/A — batch-dispensed, no per-cup brew event | L47: N/A — batch-dispensed, no per-cup brew event | M47: N/A — batch-dispensed, no per-cup brew event | N47: N/A — batch-dispensed, no per-cup brew event | O47: Unknown | P47: N/A — batch-dispensed, no per-cup brew event | Q47: 6 | R47: Yellow Pear, Dried Fruits, Brown Sugar, Almond | S47: Fruity and acidic with pear dominant and a light nutty edge — closely matches official notes (Yellow Pear, Almond). But flat across the cup: none of the hot/mid-cool/cool thermal progression of a manual pourover, reading as machine-consistent rather than barista-crafted. Hari's verdict: not worth a repeat visit — and on principle, he considers it a bad idea to automate the pourover format specifically. Pourover's whole identity rests on a human reading the bed and adjusting pour/temperature in real time; a tap dispenser removes that variable entirely, so even a technically clean cup like this one reads as inert rather than expressive. | T47: Tap-dispensed batch brewing removes the two levers that define pourover's identity — pulse-pour agitation and a controlled, declining temperature curve — collapsing what should be a three-phase thermal arc into one static, averaged extraction state. Consistent, but expressively inert; this backs up Hari's stated view that automation and pourover are a poor philosophical fit. Catimor's rust-resistant hybrid lineage plus the sub-1,050m altitude also compress the acid/aromatic ceiling well below the 1,700m+ Bourbon/Gesha lots this benchmarks against. Automation suits high-throughput formats (espresso, batch drip, cold brew) where uniformity is the point; it works against the reason pourover exists in the first place. Machine-brewed psychological discount applies per scoring convention. | U47: First visit — automated tap filter bar (2050 Coffee), novelty try. First Myanmar origin and first Catimor varietal in archive. Hari has ruled out a return visit and holds a firm general view that automating pourover-format filter brewing is conceptually flawed, regardless of cup quality. | V47: Direct observation + bean card photo | W47: =IF(OR(ISNUMBER(SEARCH("gesha",G47)),ISNUMBER(SEARCH("geisha",G47))),"⭐ GESHA","")
A48: 46204 | B48: Singapore | C48: Kyuukei Coffee | D48: Ethiopia Worka Chelchele | E48: Kyūkei Coffee (In-house roast) — confirmed via Instagram DM | F48: Gedeb, Gedeo Zone, Ethiopia | G48: Dega, Wolisho, Kurume (Landrace Triad) | H48: Washed | I48: Light | J48: Pour-over (Deep27, Flat-Bottom, Immersion-Assist) — confirmed by Kyūkei Coffee via Instagram DM | K48: 16 | L48: 240 | M48: 1:15 | N48: 85 → 95 (ramped) | O48: 30 seconds | P48: Unknown — Kyūkei DM did not address grinder; tall cylindrical flat-burr unit visible in bar photo, model unconfirmed | Q48: 9 | R48: Lemon, Peach, Bergamot, Apricot | S48: Floral hit and citrus brightness dominated the hot phase — lime/lemon citric clarity with linalool florals leading. Mid-cool: brightness tapered into balanced malic structure; slight chlorogenic bitter tinge after slurp — contained, not a flaw. Cool phase: nectarine and stone fruit sugars emerged cleanly; jasmine/berry aftertaste lingered beyond the cup. Excellent 4/4 palate alignment with roaster notes. Barista confirmed "bright" — accurate. Berry-jasmine aftertaste tail identified as likely Wolisho landrace signature beyond stated roaster notes. | T48: Deep27 flat-bottom immersion-assist brewer (confirmed by Kyūkei via DM) — the "D something" brewer identified in-session. Immersion-assist geometry ensures full and even bed saturation before drawdown, explaining the exceptional extraction clarity and balanced thermal arc observed. Grinder model unconfirmed — tall cylindrical flat-burr unit visible on bar but not identified by Kyūkei in DM. House ratio confirmed as 16g/240g (1:15) — within the 1:15–1:17 Palate DNA comfort band. Bloom confirmed 30 seconds. In-house roast confirmed. | U48: Solo visit — Kyūkei Coffee Maxwell lunch audit, 01 Jul 2026, 13:04 | V48: Direct observation + receipt + barista confirmation | W48: =IF(OR(ISNUMBER(SEARCH("gesha",G48)),ISNUMBER(SEARCH("geisha",G48))),"⭐ GESHA","")
A49: 46206 | B49: Singapore | C49: Zerah Roasters | D49: Finca Villarazo — Pink Bourbon | E49: Finca Villarazo | F49: Colombia | G49: Pink Bourbon | H49: Washed | I49: Filter Roast | J49: Pour-over (Orea V4 — Flat-Bottom) | K49: 15 | L49: 240 | M49: 1:16 | N49: 92 (constant) | O49: 50g / 40s (1:3.3 bloom ratio) | P49: DF83V (83mm Flat Burr) | Q49: 9 | R49: Lively and juicy; Pomegranate; Mandarin; Lingering Florals | S49: Hot phase: simultaneous pomegranate + mandarin orange hit — bright, punchy, fruity. Low-to-medium body throughout. Mid-cool: sugar emergence as brightness decreases — sucrose surfacing as citric volatiles dissipate. Cool phase: sugar dominant with pomegranate aftertaste lingering cleanly. Floral presence subtle — linalool under the citric punch. Official notes confirmed across all three thermal phases. First Pink Bourbon in archive. | T49: DF83V 83mm flat burrs (Chinese-market variant) — first DF83 platform entry in archive, largest consumer flat burr diameter logged (83mm vs prior max 98mm commercial). Larger burr surface area + higher RPM produces near-zero fines, explaining exceptional acid clarity at hot phase. Orea V4 flat-bottom geometry: zero bypass, full bed saturation via wave filter — isolated Pink Bourbon citric-malic duality without channeling interference. 22 days off roast (roasted 11 Jun 2026) — one day past optimal 10-21 day degas window; citric top notes (mandarin) still present but beginning to fade, explaining why mid-cool sugar emergence was earlier and stronger than expected. Bloom 50g/40s (1:3.3 ratio) — generous bloom on 15g dose ensured full CO₂ purge before extraction. Constant 92°C with no temperature step-down: single-temp protocol on washed Pink Bourbon works because the bean has no heavy mucilage sugars requiring lower-temp management. Pink Bourbon genetic signature confirmed: ellagic acid esters (pomegranate, thermally stable) + citric acid (mandarin, volatile) co-present hot phase; sucrose density characteristic of Bourbon mutation reveals at cool. In-house micro-roastery adjacent to café — Zerah roasts own beans on-site. | U49: Solo visit — Zerah Roasters, Singapore. Friday lunch break, 12:30 PM, 3 Jul 2026. Second Zerah visit (Entry #035 ref: El Diviso Ester Bomb, 26 May 2026). Bean card photo confirmed. In-house roast, micro-roastery on-site next to café. Barista: Aqil — most friendly and enthusiastic barista across all 48 archive visits to date. Explained brew parameters, roast date, and flat-bottom geometry rationale unprompted. Standout human element — educational and warm throughout. | V49: Field audit (Claude) — bean card + barista confirmation | W49: =IF(OR(ISNUMBER(SEARCH("gesha",G49)),ISNUMBER(SEARCH("geisha",G49))),"⭐ GESHA","")
A50: 46207 | B50: Singapore | C50: Oaks Coffee Co. | D50: Floripondio 90 Hours | E50: Los Rodriguez | F50: Bolivia | G50: Pacamara | H50: Lactic Honey | I50: Filter Roast | J50: Origami Dripper (Flat-Bottom) | K50: 15 | L50: 240 | M50: 1:16 | N50: 88 (constant) | O50: 80-90g first pour (3-pour protocol) | P50: Option-O Lagom P80 (80mm Flat Burr) | Q50: 9 | R50: Mango; Passionfruit | S50: Hot phase: mango and passionfruit dominant — bright punchy LAB ester burst. Mid-cool: tropicals recede, sugar clarity emerges, lactic-glycerol creaminess surfaces. Cool phase: clean nectarine emergence — Pacamara varietal-native genetic signature. Clean honey sweetness, thermally stable finish. Bright, fruity, well-structured throughout. Highly enjoyable. | T50: P80 80mm flat burrs delivered near-unimodal distribution on Pacamara's oversized bean mass; 88°C constant temperature preserved LAB-derived fruit esters and lactic-glycerol creaminess from 90-hour fermentation without volatilising into sharpness; Origami flat-bottom zero-bypass architecture protected aromatic integrity across all three thermal phases. | U50: Solo visit — Oaks Coffee Co., Bukit Timah Road, 4 Jul 2026, 16:00. Café Day 4 of operations. Milestones: First Bolivia, First Pacamara, First Lactic Honey, First P80 platform. Barista warm and knowledgeable. | V50: Direct observation + bean card photo + barista confirmation | W50: =IF(OR(ISNUMBER(SEARCH("gesha",G50)),ISNUMBER(SEARCH("geisha",G50))),"⭐ GESHA","")
A51: 46208 | B51: Singapore | C51: Homeground Coffee Roasters | D51: Colombia Inmaculada Gesha Natural | E51: Inmaculada Estate | F51: Valle del Cauca, Colombia | G51: Gesha | H51: Natural | I51: Light | J51: Origami Dripper (Ceramic — Flat-Bottom Stand) | K51: 15 | L51: 247 | M51: 1:16.5 | N51: 86-90 | O51: Unknown | P51: Mahlkönig EK43 (98mm Flat Burr) | Q51: 19 | R51: Hibiscus, Pomegranate, Stewed Peach, Darjeeling Tea | S51: HOT: Hibiscus and pomegranate bright and balanced — clean anthocyanin-driven floral punch, excellent opening. | MID-COOL: Flavour tapered gracefully; Darjeeling tea polyphenol structure emerged, smooth and soothing. | COOL: Tea backbone confirmed with slight sugar aftercoat — cherry-dried sucrose persisting cleanly at sub-50°C. Overall: excellent and deeply relaxing; Gesha varietal identity held under natural process layer. Top-tier entry — starred. | T51: EK43 98mm flat burrs at 24–26 click equivalent; 86–90°C natural protocol deliberately suppresses acetic acid volatilisation while preserving anthocyanin-driven hibiscus esters and Gesha linalool-floral DNA. Lean 1:16.5 ratio dilutes fermentation-derived sugar density to reveal Gesha varietal structure underneath. Origami flat-bottom stand confirmed by direct observation — same pink ceramic unit used for both cups. 21 days off roast (roasted 14 Jun 2026, tasted 5 Jul 2026) — optimal degas window per bean card guidance; volatile aromatics intact, zero stale oxidation. Darjeeling tea polyphenol structure held clean across all thermal phases confirming precision aerobic fermentation at Inmaculada. First Colombia Gesha Natural in archive; completes washed/honey/natural Colombia Gesha process trilogy. First Homeground entry; first Origami brewer logged. | U51: Father-daughter visit — Homeground Coffee Roasters Bukit Timah Experience Room; 5 Jul 2026 10:30 AM | V51: Field audit (Claude) — bean card + barista confirmed + direct observation | W51: =IF(OR(ISNUMBER(SEARCH("gesha",G51)),ISNUMBER(SEARCH("geisha",G51))),"⭐ GESHA","")
A52: 46208 | B52: Singapore | C52: Homeground Coffee Roasters | D52: Bolivia Los Rodriguez Caturra Washed | E52: Los Rodriguez | F52: Samaipata, Bolivia | G52: Caturra | H52: Washed | I52: Light | J52: Origami Dripper (Ceramic — Flat-Bottom Stand) | K52: 15 | L52: 244 | M52: 1:16.2 | N52: 90-93 | O52: Unknown | P52: Mahlkönig EK43 (98mm Flat Burr) | Q52: 10 | R52: Apricot, Apple, Honey | S52: Aanya's cup (companion entry). Fruity and clean throughout — apricot and stone fruit character apparent from opening; honey sweetness emerged clearly at cool phase. Both Hari and Aanya enjoyed; approachable, well-structured, and clean finish with no bitterness. Excellent introduction-level specialty filter. | T52: EK43 98mm flat burrs at 26–28 click equivalent (coarser than Gesha Natural — consistent with washed protocol building structured body); 90–93°C higher temp than natural protocol to fully dissolve Caturra's denser post-pulping cellulose structure. Origami flat-bottom stand confirmed by direct observation — same pink ceramic unit as Gesha. Flat-bottom geometry builds even puck saturation preserving malic apricot-apple clarity. Samaipata Bolivia high-altitude Caturra: compact varietal frame produces clean malic acid structure with honey-sucrose finish. Bean card specifies 14-day minimum rest. Roast date unknown. | U52: Father-daughter visit — Homeground Coffee Roasters Bukit Timah Experience Room; 5 Jul 2026 10:30 AM; Aanya's cup | V52: Field audit (Claude) — bean card confirmed + direct observation | W52: =IF(OR(ISNUMBER(SEARCH("gesha",G52)),ISNUMBER(SEARCH("geisha",G52))),"⭐ GESHA","")
A53: 46208 | B53: Singapore | C53: Cowpresso Coffee Roasters | D53: Geisha Colombia Las Nubes | E53: Unknown | F53: Valle de Cauca, Colombia | G53: Geisha | H53: Natural | I53: Medium | J53: Pour-over (Cowpresso Custom 3-Hole Ceramic Dripper — Conical) | K53: 15 | L53: 225 | M53: 1:15 | N53: 92 | O53: Unknown | P53: DF83 (83mm Flat Burr) — barista confirmed | Q53: 9.9 | R53: Lychee, Strawberry, Blueberry, Floral, Lemons | S53: HOT: Explosive berry and lemon citric punch; fruity-forward ester detonation with isoamyl lychee dominant and acetic back-note trailing from Natural process. | MID-COOL: Acid persistence — lychee ester adheres to palate; malic backbone emerges as citric fades; still assertive rather than settling. | COOL: Lychee and body hold clean to final temperature; no notable sugar emergence — melanoidin body from medium roast persists. Verdict: An aggressive Geisha expression — Natural process × medium roast drives a fruit-heavy, body-forward profile divergent from the archive's Washed Geisha baseline. Enjoyable on its own terms; confirms Palate DNA preference for calmer washed clarity. First Natural Geisha in archive. Father-daughter visit with Aanya; barista Aung (Myanmar) gifted a complimentary sea salt latte — standout warmth and hospitality. Excellent café ambience and visual aesthetics noted. | T53: Natural process ester chemistry (isoamyl acetate/lychee, berry esters) amplified by the custom Cowpresso 3-hole conical ceramic dripper's extended bed contact geometry, explaining the assertive acid punch and lychee persistence across all three thermal phases; medium roast Maillard contribution added unusual body mass for a Geisha, compressing linalool florals but sustaining melanoidin mouthfeel to cool — third conical-geometry entry in archive, consistent with the documented over-extraction pattern. DF83 83mm flat burrs provided low-fines grind consistency, moderating fermentation-derived acetic acid amplification. 10 days off roast (roasted 25 Jun 2026) — opening edge of optimal rest window; residual CO₂ may have contributed to slightly compressed clarity. | U53: Father-daughter visit with Aanya — Cowpresso Coffee Roasters Singapore, 5 Jul 2026, 17:00. Second café of the day after Homeground Coffee Roasters morning session (2 Geishas in one day). Post-hike afternoon visit. Barista: Aung (from Myanmar) — warm and hospitable; gifted a complimentary sea salt latte for tasting. Excellent café ambience and visual aesthetics. Roast date: 25 Jun 2026 (10 days off roast at time of visit). Coffee name 'Las Nubes' from menu/receipt; bean bag reads 'Valle de Cauca' — Las Nubes likely estate name, unconfirmed. | V53: Direct observation + bean bag photo + receipt + barista confirmation (Aung) | W53: =IF(OR(ISNUMBER(SEARCH("gesha",G53)),ISNUMBER(SEARCH("geisha",G53))),"⭐ GESHA","")
A54: 46209 | B54: Singapore | C54: Fluid Collective | D54: Alo Coffee — Natural Anaerobic Ethiopia 74158 | E54: Tamiru Tadesse | F54: Ethiopia | G54: 74158 | H54: Natural Anaerobic | I54: Light | J54: Hario Switch (Flat-Bottom Immersion Hybrid) | K54: 15 | L54: 225 | M54: 1:15 | N54: 70 → 90 → 70°C (Thermal Oscillation Protocol) | O54: Unknown | P54: Lagom P64 | Q54: 11 | R54: Lychee | Purple Grape | White Peach | S54: HOT: Perfect balance — lychee and white peach hit immediately. Clean tropical entry, no fermented funk. Light to medium body. WARM: Medium body settles; winey grape character emerges — controlled anaerobic expression, no acetic sharpness. COOL: Brightness recedes, grape clarifies and becomes dominant signal. Less vivid but more structured. Clarity increases as heat dissipates. Overall: well done. Fluid tamed the anaerobic variable cleanly. | T54: 74158 (JARC Ethiopian selection) under anaerobic natural protocol: sealed-tank fermentation produces geraniol and rose oxide compounds — lychee and white peach dominant in hot phase. Ethyl acetate and anthocyanins unlock in warm phase as winey grape. Cool phase: volatile esters dissipate, structural anthocyanin compounds clarify into clean grape signal — classic anaerobic thermal behaviour. Fluid's 70→90→70°C protocol preserved fermentation character without amplifying acetic sharpness. Third Fluid visit confirms thermal oscillation protocol consistent across all menu rotations. Served in white handled mug — different serveware vs previous Fluid visits. | U54: Third visit to Fluid Collective, 6 July 2026, 13:10, lunch. Menu fully rotated — all three filter offerings new. First cup of two ordered today. Experimental mood — chose anaerobic. Barista confirmed: ratio 1:15, temp 70→90→70°C, standard Fluid protocol. | V54: Live Field Audit — Third Visit | W54: =IF(OR(ISNUMBER(SEARCH("gesha",G54)),ISNUMBER(SEARCH("geisha",G54))),"⭐ GESHA","")
A55: 46209 | B55: Singapore | C55: Fluid Collective | D55: Gara Agena | E55: Gara Agena Washing Station | F55: Ethiopia | G55: Heirloom Ethiopian Varieties | H55: Washed Special Prep | I55: Light | J55: Hario Switch (Flat-Bottom Immersion Hybrid) | K55: 15 | L55: 225 | M55: 1:15 | N55: 70 → 90 → 70°C (Thermal Oscillation Protocol) | O55: Unknown | P55: Lagom P64 | Q55: 9 | R55: Nectarine | Mandarin Orange | Floral Honey | S55: HOT: Bright nectarine hit immediate and clean. Floral light orange present from the first sip. Honey detectable even at high temperature — extremely clean washed expression, orange character very clear. WARM: Honey gains ground and becomes the dominant note. Coffee calms and cleans further. Orange recedes to background — gentle, not forward. COOL: Very nice to drink. Washed clarity fully expresses. Nectarine returns cleaner and more defined at lower temperature. Top of my list for what I like. Exceptional. | T55: Gara Agena Washing Station — Gedeo Zone, Ethiopia. Washed Special Prep designation = Ethiopian Coffee Exchange highest sorting standard, defect-free, hand-selected. Heirloom Ethiopian varieties carry exceptional linalool ester diversity expressing as mandarin orange and floral honey. Nectarine = malic acid dominant — Hari's core palate signal. Clean three-phase thermal arc: nectarine/orange hot → honey grounds warm → washed clarity + nectarine cool. Same Fluid hardware and protocol as all prior visits. Perfect post-anaerobic palate reset — washed clarity after fermentation complexity creates maximum contrast in same session. | U55: Second cup of two at Fluid Collective third visit, 6 July 2026. Followed Alo Coffee Natural Anaerobic — deliberate contrast pairing. Gara Agena placed top of personal preference list by Hari. SGD 9 — outstanding value for Special Prep Ethiopian heirloom. | V55: Live Field Audit — Third Visit | W55: =IF(OR(ISNUMBER(SEARCH("gesha",G55)),ISNUMBER(SEARCH("geisha",G55))),"⭐ GESHA","")
A56: 46210 | B56: Singapore | C56: Pinhole Coffee Bar | D56: Santa Barbara #1 — Gesha Honey Colombia | E56: Jhon Samboni — Santa Barbara #1 | F56: Colombia — Huila | G56: Gesha | H56: Honey | I56: Light | J56: Hario V60 Ceramic (Conical — Single Aperture) | K56: 13.5 | L56: 200 | M56: 1:14.8 | N56: 92°C (Constant) | O56: 52g (3.85× dose) | P56: Mahlkönig EK43 Mini (64mm Flat Burr) | Q56: 15 | R56: White Florals, Berry Candy, Tangerines | S56: HOT: Tea-like and light — less acidic than expected. Bergamot and white florals present from the first sip, characteristic Gesha linalool signature. Not loud; elegant and restrained. WARM: Subtle tangerine and stone fruit emerge as malic acid takes over from citric. Lychee hit — geraniol expression surfacing at lower temperature. Honey sweetness begins layering in. Brightness tapers cleanly with no harsh edge. COOL: Cup fully opens. Mandarin orange clarifies as the dominant acid signal — malic at low temp, softer and rounder than tangerine. Honey sweetness crystallises and lingers as a clean aftertaste. Best phase of the cup — this is a cold-cup Gesha. Patience rewarded. | T56: Jhon Samboni's Santa Barbara #1 roasted by Slurp Coffee Project (Roast Gate 15 June — 22 days off-roast, peak filter window). EK43 Mini (64mm flat burrs) — compact single-dose grinder with 64mm flat burrs, tighter particle distribution than full-size EK43 98mm; superior grind uniformity for single-dose filter; V60 conical geometry concentrates fines at apex creating flow restriction risk — mitigated here by fast 2-minute draw-down. 1:14.8 ratio (below Palate DNA band 1:15–1:17) amplified sweetness but compressed hot-phase aromatic lift. Honey process ketone-derived berry/stone fruit compounds require temperature below 65°C to fully volatilise — explains cold-phase revelation. Flat-bottom geometry would have delivered wider aromatic headspace in hot phase. | U56: Solo audit — Café debut, Watchlist visit fulfilled. 7 July 2026, 12:30 PM. Two offerings on menu: this Gesha at SGD 15 (Santa Barbara #1, Slurp Coffee Project) and Peru Natural Sidra+Caturra at SGD 12 (Elvis Tineo, Cajamarca). Chose Gesha. Pinhole Barista's Stash SGD 10 blind option also available. First Slurp Coffee Project roast in the archive. Barista noted V60 usage is legacy from previous management; current team considering switch to flat-bottom or siphon in future. | V56: Live Field Audit — Café Debut + Bean Card (Slurp Coffee Project) + Barista Confirmation (dose/temp/pour protocol) | W56: =IF(OR(ISNUMBER(SEARCH("gesha",G56)),ISNUMBER(SEARCH("geisha",G56))),"⭐ GESHA","")
A57: 46211 | B57: Singapore | C57: Double Shot Coffee | D57: Kotowa Carolina Gesha | E57: Kotowa Estate — Carolina Lot | F57: Boquete, Chiriquí, Panama | G57: Gesha | H57: Natural | I57: Unknown | J57: OREA V4 (Flat-Bottom) | K57: 13.5 | L57: 180 | M57: 1:13.3 | N57: 92°C | O57: 50g bloom (4-pour: 50/50/50/30g) | P57: Ditting 63.5mm Flat Burr | Q57: 16 | R57: White Floral · Peach · White Grape | S57: HOT: Bright and immediate peach hit — ethyl ester fraction opening cleanly with malic brightness. Promising, high-energy opening. MID-COOL: White florals and peach clarity emerging together — linalool terpenes surfacing as expected for Gesha genetics. Both official notes (white floral, peach) tracking accurately. COOL: Cup mellows significantly. Peach recedes to background. Sucrose sweetness underperforms expectation — sugars suppressed by concentrated house ratio. Lingering bitterness detected — procyanidin and tannin expression from Natural cherry skin polyphenols amplified by 1:13.3 TDS. White grape polyphenol reads as astringent rather than sweet at cool. Overall rated average. Bean quality likely higher than this ratio reveals. Would revisit at 1:15–1:17 to properly isolate Kotowa terroir ceiling. | T57: Ditting 63.5mm flat burr delivered tight PSD with minimal fines migration and low heat transfer — correct hardware for a delicate Natural Gesha. OREA V4 flat-bottom geometry ensured uniform bed extraction and even dwell time across full coffee bed. However, the 1:13.3 concentrated house ratio elevated TDS significantly above standard 1:15–1:17 Palate DNA band — at this concentration, Natural process polyphenols (procyanidins, chlorogenic acid lactones from dried cherry skin) remain in solution without adequate water buffer to suppress bitterness below palate threshold. Sucrose sweetness outcompeted at cool phase. Ratio is the primary extraction variable suppressing the Gesha's characteristic tea-like sweetness. A 1:15–1:17 recipe would likely transform the cup's cool-phase expression entirely. | U57: Solo visit — 08 Jul 2026, 14:15. Double Shot Coffee, Kampong Bahru. Food-free dedicated brew-bar café. Barista warm and knowledgeable — voluntarily walked through all brew parameters (dose, temp, pour structure, grinder) without prompting. Comfortable seating. Visited directly after disappointment-driven palate reset at Nylon Coffee Roasters. First Kotowa Carolina estate entry in archive. First Double Shot Coffee visit. House philosophy: concentrated double-shot style filter — 1:13.3 is intentional format, not an error. | V57: Live Field Audit — Menu photo + barista interview + direct observation (Ditting grinder confirmed, OREA V4 confirmed) | W57: =IF(OR(ISNUMBER(SEARCH("gesha",G57)),ISNUMBER(SEARCH("geisha",G57))),"⭐ GESHA","")
A58: 46211 | B58: Singapore | C58: Nylon Coffee Roasters | D58: La Flor de la Palma | E58: William Manchay Espinoza | F58: Peru | G58: Bourbon | H58: Natural | I58: Filter Roast | J58: xBloom (Flat-Bottom) | K58: Unknown | L58: Unknown | M58: 1:17 | N58: 93 | O58: Unknown | P58: Mahlkönig EK Omnia (98mm Flat Burr) | Q58: 8.5 | R58: Dried Berry; Cherry; Rum & Raisin; Rose | S58: HOT: Berry arrival — bright and light to medium body; minimal aftertaste. MID-COOL: Mellowed; dried berry lingers with an unresolved slightly bitter shadow. COOL: Same persistent bitterness across finish — source identified post-session as chlorogenic acid lactone (CGA lactone) unmasked by lean ratio on this Natural Bourbon. Honest cup, fair for price, not a return target on this bean. | T58: EK Omnia 98mm flat burrs + xBloom flat-bottom at 1:17 created a structural ratio-process mismatch on this Natural Bourbon: lean 1:17 dilution suppressed late-extracting sucrose-ester mass (Rum & Raisin depth), leaving CGA lactone bitterness unmasked at mid-cool and cool phases. 93°C slightly conservative for Bourbon's dense cell wall. Roast date 26 Jun 2026 confirmed by barista (bag showed retail pack date 06 Jul 2026 — not roast date); 12 days rest at consumption, within optimal Natural degassing window. Under-rest was NOT the variable; ratio-process mismatch was. | U58: Return visit to Nylon Coffee Roasters after a disappointing Gesha (Kotowa Carolina) at Double Shot Coffee (Kampong Bahru) earlier same day — Nylon as reliability palate reset. Solo, 15:15 SGT. Peru La Flor de la Palma — Natural Bourbon — first time audited at Nylon under filter conditions. Roast date correction from barista: 26 Jun 2026, not 06 Jul 2026 (bag was retail pack date). Price S$8.50. | V58: Direct observation + bag photo (name/notes reference only) + barista confirmation (roast date 26 Jun 2026) | W58: =IF(OR(ISNUMBER(SEARCH("gesha",G58)),ISNUMBER(SEARCH("geisha",G58))),"⭐ GESHA","")
A59: 46212 | B59: Singapore | C59: Abseil | D59: El Sauce Gesha | E59: El Sauce Farm | F59: Colombia | G59: Gesha | H59: Washed | I59: Light | J59: CT62 Coffee Dripper (Taster's Coffee / DragonFly Design, Taiwan — Engineered Conical, 62° Cone, 24-Groove Active Flow Compensation) | K59: 15 | L59: 232 | M59: 1:15.5 | N59: 91°C (Constant throughout) | O59: 80g (~5.3× dose) — Aggressive CO₂ purge bloom | P59: Option-O Lagom P64 (64mm Flat Burr) | Q59: 21 | R59: Gardenia · Mandarin · Dried Apricot · Green Tea · Honeysuckle | S59: HOT: Honeysuckle and honey immediate — linalool terpenes fully volatilised from aggressive 80g bloom; bright floral clean opening. MID-COOL: Very sugary mid-palate; mandarin orange in background; honey clearly detectable; sucrose dominant as volatile top notes subside — very sweet and clean. COOL: Tea-like and beautifully balanced; mandarin mellowed to background; clean lingering sweetness with zero bitterness — CT62 anti-over-extraction engineering confirmed across all three phases. Overall: elegant, restrained washed Gesha. Upper-tier entry. SGD $21 is steep but the bean quality justifies it. Would return. | T59: Option-O Lagom P64 64mm flat burrs (narrow particle size distribution, minimal fines) combined with CT62's 24-groove active flow compensation system (12 long + 12 short grooves) eliminated standard conical over-extraction risk entirely — the CT62 is a conical in geometry only; its engineered groove architecture regulates flow rate at both high and low water levels, producing extraction consistency comparable to flat-bottom geometry. Aggressive 80g bloom at constant 91°C front-loaded complete linalool terpene dissolution, delivering honeysuckle immediately in the hot phase. Conservative 91°C throughout suppressed chlorogenic acid extraction — confirmed by zero phenolic shadow at cool phase. CT62 won 2023 German Design Award and 2023 China and Korea Brewers Cup. First CT62 entry in archive — classified as Engineered Conical (flow-compensated), distinct from standard V60 conical entries. | U59: Solo visit — Abseil café debut, 09 Jul 2026. Barista Glenda — exceptional engagement, long technical conversation, outstanding hospitality. Rated Joint #1 for barista friendliness alongside Aqil at Zerah Roasters — the two finest barista interactions in the archive. CT62 dripper identity confirmed by Glenda + product screenshot (tasterscoffee.com). Glenda explained bloom logic, confirmed 1:15.5 ratio, and noted El Sauce Gesha has won awards in recent years. Extensive filter menu (4+ Gesha options) and competition-grade hardware setup noted — one of the finest specialty filter setups encountered across all 33 archive cafés. Would return without hesitation. Finca Jurutungo Panama Gesha (SGD $28, Anaerobic Natural) flagged as next priority on return visit. | V59: Live Field Audit — menu photo + equipment photos + barista confirmation (Glenda) + CT62 product research (tasterscoffee.com) | W59: =IF(OR(ISNUMBER(SEARCH("gesha",G59)),ISNUMBER(SEARCH("geisha",G59))),"⭐ GESHA","")
A60: 46213 | B60: Singapore | C60: Oaks Coffee Co. | D60: Finca El Diviso | E60: Nestor Lasso | F60: Colombia | G60: Aji Bourbon | H60: Thermal Shock Anaerobic Natural | I60: Filter Roast | J60: Origami Dripper (Flat-Bottom) | K60: Unknown | L60: Unknown | M60: Unknown | N60: Unknown | O60: Unknown | P60: Option-O Lagom P80 (80mm Flat Burr — assumed) | Q60: 9 | R60: Lychee; Blueberry Jam; Cranberry | S60: Hot phase: punchy lychee and berry dominant — high-intensity bright acidity, strong entry. Mid-cool to cool: fruit character sustained across all phases without evolution — Thermal Shock ester concentration too embedded to dissipate thermally. Strong persistent aftertaste from cranberry anthocyanin compounds. Interesting but not a repeat — process-forward intensity beyond personal palate threshold. | T60: Thermal Shock Anaerobic Natural at 1960 MASL produced extreme ester and anthocyanin concentration (geraniol/nerol lychee monoterpenes; berry anthocyanins) — fermentation signature dominated all three thermal phases without evolution. Process-preference misalignment confirmed: clarity > complexity hierarchy not served by this process. P80 flat-burr precision and Origami flat-bottom geometry could not temper inherent process intensity. | U60: With friend Alex — Oaks Coffee Co., Bukit Timah Road, 10 Jul 2026, 16:30, before Homeground mock-judge session. Second Oaks visit. Milestones: First Thermal Shock Anaerobic Natural, First Aji Bourbon, First Finca El Diviso (Nestor Lasso). | V60: Direct observation + bean card photo | W60: =IF(OR(ISNUMBER(SEARCH("gesha",G60)),ISNUMBER(SEARCH("geisha",G60))),"⭐ GESHA","")

Sheet ☕ Dashboard
B1: ☕ THE HARI COFFEE ARCHIVE — 2026
B2: A Master Extraction Archivist's living record · Singapore · Bali · Mumbai · Johor Bahru
B4: 📊 ARCHIVE VITALS — live formulas, auto-update with every new entry
B6: TOTAL ENTRIES | C6: UNIQUE CAFÉS | D6: CITIES | E6: ORIGIN LOTS | F6: GESHA CUPS | G6: VARIETALS | H6: AVG SGD | I6: FIRST ENTRY | J6: LATEST ENTRY
B7: =COUNTA('Coffee Audit'!A2:A2000) | C7: =SUMPRODUCT(('Coffee Audit'!C2:C2000<>"")/COUNTIF('Coffee Audit'!C2:C2000,'Coffee Audit'!C2:C2000&"")) | D7: =SUMPRODUCT(('Coffee Audit'!B2:B2000<>"")/COUNTIF('Coffee Audit'!B2:B2000,'Coffee Audit'!B2:B2000&"")) | E7: =SUMPRODUCT(('Coffee Audit'!F2:F2000<>"")/COUNTIF('Coffee Audit'!F2:F2000,'Coffee Audit'!F2:F2000&"")) | F7: =COUNTIF('Coffee Audit'!W2:W2000,"⭐ GESHA") | G7: =SUMPRODUCT(('Coffee Audit'!G2:G2000<>"")/COUNTIF('Coffee Audit'!G2:G2000,'Coffee Audit'!G2:G2000&"")) | H7: =AVERAGEIF('Coffee Audit'!Q2:Q2000,">0") | I7: =TEXT(MIN('Coffee Audit'!A2:A2000),"DD MMM") | J7: =TEXT(MAX('Coffee Audit'!A2:A2000),"DD MMM YYYY")
B9: 📖 THE ARCHIVE THESIS
B10: Fifty-nine cups. Thirty-three cafés. Four cities. One palate, decoded in three thermal phases. This archive is a longitudinal study of a single palate: washed-process clarity over fermentation complexity, malic acid and linalool as the north stars, flat burrs and flat-bottom geometry as the preferred physics. Every entry is a field audit — hardware identified, parameters confirmed with the barista where offered, sensory record kept across HOT, MID-COOL and COOL. The data shows a palate that rewards precision: Gesha remains the apex varietal (12 entries), Colombia and Ethiopia the dominant origins, and the archive's verdicts consistently favour cups where process serves terroir rather than replacing it.
B16: 🏆 ARCHIVE HONOURS BOARD
B17: Honour | C17: Holder | D17: Detail
B18: Cup of the Year (to date) | C18: Fluid Collective — Gesha lineage | D18: Thermal-oscillation protocol; National Brewers Cup champion bar
B19: Friendliest Baristas (joint) | C19: Aqil — Zerah Roasters · Glenda — Abseil | D19: Joint #1 across all 59 audits
B20: Most Audited Café | C20: Nylon Coffee Roasters | D20: Reliability anchor of the archive
B21: Best Value Discovery | C21: Oaks Coffee Co. — Floripondio 90 Hours | D21: SGD 9 · Bolivia Pacamara Lactic Honey · café Day 4
B22: Boldest Process Encountered | C22: Finca El Diviso — Thermal Shock Anaerobic | D22: Nestor Lasso · palate threshold boundary confirmed
B23: Process Trilogy Completed | C23: Colombia Gesha — Washed/Honey/Natural | D23: Fluid Collective · Keryi · Homeground

Sheet 🧬 Palate DNA
B1: 🧬 PALATE DNA — PROCESS · GEOMETRY · RATIO
B2: Clarity > Complexity · washed-dominant · flat-bottom preferred · 1:15–1:17 band
B4: 🧪 PROCESS DISTRIBUTION — what the palate actually drank
B5: Process family | C5: Entries | D5: Share
B6: Washed | C6: =COUNTIF('Coffee Audit'!H2:H2000,"*Washed*") | D6: =C6/COUNTA('Coffee Audit'!H2:H2000)
B7: Natural | C7: =COUNTIF('Coffee Audit'!H2:H2000,"*Natural*") | D7: =C7/COUNTA('Coffee Audit'!H2:H2000)
B8: Honey | C8: =COUNTIF('Coffee Audit'!H2:H2000,"*Honey*") | D8: =C8/COUNTA('Coffee Audit'!H2:H2000)
B9: Anaerobic | C9: =COUNTIF('Coffee Audit'!H2:H2000,"*Anaerobic*") | D9: =C9/COUNTA('Coffee Audit'!H2:H2000)
B10: Lactic | C10: =COUNTIF('Coffee Audit'!H2:H2000,"*Lactic*") | D10: =C10/COUNTA('Coffee Audit'!H2:H2000)
B11: Thermal Shock | C11: =COUNTIF('Coffee Audit'!H2:H2000,"*Thermal Shock*") | D11: =C11/COUNTA('Coffee Audit'!H2:H2000)
B12: Wet-Hulled | C12: =COUNTIF('Coffee Audit'!H2:H2000,"*Wet-Hulled*") | D12: =C12/COUNTA('Coffee Audit'!H2:H2000)
B13: Experimental | C13: =COUNTIF('Coffee Audit'!H2:H2000,"*Experimental*") | D13: =C13/COUNTA('Coffee Audit'!H2:H2000)
B14: Note: families overlap (e.g. "Anaerobic Natural" counts in both) — this maps palate exposure, not exclusive buckets.
B22: 📐 BREWER GEOMETRY — the flat-bottom thesis
B23: Geometry | C23: Entries | D23: Archive verdict
B24: Flat-bottom / flatbed | C24: =COUNTIF('Coffee Audit'!J2:J2000,"*Flat*") | D24: Preferred — even bed saturation, zero bypass
B25: Conical (V60 family) | C25: =COUNTIF('Coffee Audit'!J2:J2000,"*V60*")+COUNTIF('Coffee Audit'!J2:J2000,"*Conical*") | D25: ⚠ Over-extraction risk flag — documented repeatedly
B26: Engineered conical (CT62) | C26: =COUNTIF('Coffee Audit'!J2:J2000,"*CT62*") | D26: Own category — 24-groove flow compensation earns exemption
B27: Immersion / hybrid | C27: =COUNTIF('Coffee Audit'!J2:J2000,"*Immersion*")+COUNTIF('Coffee Audit'!J2:J2000,"*Switch*")+COUNTIF('Coffee Audit'!J2:J2000,"*AeroPress*") | D27: Occasional — body over clarity
B28: Espresso-based | C28: =COUNTIF('Coffee Audit'!J2:J2000,"*Espresso*") | D28: Companion / milk calibration entries
B30: ⚖️ RATIO BAND — 1:15–1:17 optimal window
B31: Ratio | C31: Entries | D31: Chemistry note
B32: 1:13–1:14 (concentrated) | C32: =COUNTIF('Coffee Audit'!M2:M2000,"1:13*")+COUNTIF('Coffee Audit'!M2:M2000,"1:14*") | D32: Amplifies polyphenolic bitterness at cool phase; suppresses sucrose — documented at Double Shot & Equate
B33: 1:15 (archive default) | C33: =COUNTIF('Coffee Audit'!M2:M2000,"1:15*") | D33: Default assumption 15g/225g — sweet-spot density
B34: 1:16 | C34: =COUNTIF('Coffee Audit'!M2:M2000,"1:16*") | D34: Most common café service ratio in the archive
B35: 1:17 (lean) | C35: =COUNTIF('Coffee Audit'!M2:M2000,"1:17*") | D35: Risk: insufficient sucrose-ester mass vs CGA lactone bitterness on naturals

Sheet 🌍 Origin & Terroir
B1: 🌍 ORIGIN & TERROIR ATLAS
B2: Where the archive has travelled — by bean, not by boarding pass
B4: 🗺️ ORIGIN LEAGUE TABLE
B5: Origin | C5: Entries | D5: Share
B6: Colombia | C6: =COUNTIF('Coffee Audit'!F2:F2000,"*Colombia*") | D6: =C6/COUNTA('Coffee Audit'!F2:F2000)
B7: Ethiopia | C7: =COUNTIF('Coffee Audit'!F2:F2000,"*Ethiopia*") | D7: =C7/COUNTA('Coffee Audit'!F2:F2000)
B8: Panama | C8: =COUNTIF('Coffee Audit'!F2:F2000,"*Panama*") | D8: =C8/COUNTA('Coffee Audit'!F2:F2000)
B9: Kenya | C9: =COUNTIF('Coffee Audit'!F2:F2000,"*Kenya*") | D9: =C9/COUNTA('Coffee Audit'!F2:F2000)
B10: Bolivia | C10: =COUNTIF('Coffee Audit'!F2:F2000,"*Bolivia*") | D10: =C10/COUNTA('Coffee Audit'!F2:F2000)
B11: Honduras | C11: =COUNTIF('Coffee Audit'!F2:F2000,"*Honduras*") | D11: =C11/COUNTA('Coffee Audit'!F2:F2000)
B12: India | C12: =COUNTIF('Coffee Audit'!F2:F2000,"*India*") | D12: =C12/COUNTA('Coffee Audit'!F2:F2000)
B13: Indonesia | C13: =COUNTIF('Coffee Audit'!F2:F2000,"*Indonesia*") | D13: =C13/COUNTA('Coffee Audit'!F2:F2000)
B14: Peru | C14: =COUNTIF('Coffee Audit'!F2:F2000,"*Peru*") | D14: =C14/COUNTA('Coffee Audit'!F2:F2000)
B15: Brazil | C15: =COUNTIF('Coffee Audit'!F2:F2000,"*Brazil*") | D15: =C15/COUNTA('Coffee Audit'!F2:F2000)
B16: El Salvador | C16: =COUNTIF('Coffee Audit'!F2:F2000,"*El Salvador*") | D16: =C16/COUNTA('Coffee Audit'!F2:F2000)
B17: Myanmar | C17: =COUNTIF('Coffee Audit'!F2:F2000,"*Myanmar*") | D17: =C17/COUNTA('Coffee Audit'!F2:F2000)
B18: China | C18: =COUNTIF('Coffee Audit'!F2:F2000,"*China*") | D18: =C18/COUNTA('Coffee Audit'!F2:F2000)
B19: Ecuador | C19: =COUNTIF('Coffee Audit'!F2:F2000,"*Ecuador*") | D19: =C19/COUNTA('Coffee Audit'!F2:F2000)
B20: Rwanda | C20: =COUNTIF('Coffee Audit'!F2:F2000,"*Rwanda*") | D20: =C20/COUNTA('Coffee Audit'!F2:F2000)
B22: ⭐ THE GESHA REGISTER — apex varietal tracker
B23: Metric | C23: Value
B24: Total Gesha/Geisha entries | C24: =COUNTIF('Coffee Audit'!W2:W2000,"⭐ GESHA")
B25: Washed Gesha | C25: =SUMPRODUCT(('Coffee Audit'!W2:W2000="⭐ GESHA")*(ISNUMBER(SEARCH("washed",'Coffee Audit'!H2:H2000))))
B26: Honey Gesha | C26: =SUMPRODUCT(('Coffee Audit'!W2:W2000="⭐ GESHA")*(ISNUMBER(SEARCH("honey",'Coffee Audit'!H2:H2000))))
B27: Natural Gesha | C27: =SUMPRODUCT(('Coffee Audit'!W2:W2000="⭐ GESHA")*(ISNUMBER(SEARCH("natural",'Coffee Audit'!H2:H2000))))
B28: Avg Gesha price (SGD) | C28: =ROUND(AVERAGEIFS('Coffee Audit'!Q2:Q2000,'Coffee Audit'!W2:W2000,"⭐ GESHA",'Coffee Audit'!Q2:Q2000,">0"),2)
B29: Botanical note: "Gesha" (Gesha forest, Ethiopia) is the correct spelling; "Geisha" is the Panamanian commercial transliteration. The archive tracks both.
B31: 🎯 REMAINING VARIETAL TARGETS
B32: Eugenioides | C32: ❌ MISSING — highest-priority varietal target
B33: Laurina | C33: ✅ Captured — Entry #025
B34: Sudan Rume | C34: ✅ Captured — Entry #038
B35: Aji Bourbon | C35: ✅ Captured — Entry #059 (Oaks, Finca El Diviso)
B36: Pacamara | C36: ✅ Captured — Entry #049 (Oaks, Floripondio)

Sheet ⚙️ Hardware & Extraction
B1: ⚙️ HARDWARE & EXTRACTION PHYSICS
B2: Flat burrs, flat beds, and the physics of clarity
B4: 🔩 GRINDER PLATFORM REGISTER
B5: Platform family | C5: Entries | D5: Note
B6: Option-O Lagom (P64/P80) | C6: =COUNTIF('Coffee Audit'!P2:P2000,"*Lagom*") | D6: Preferred precision platforms — P80 debuted at Oaks (Entry #049)
B7: EK43 / Mahlkönig | C7: =COUNTIF('Coffee Audit'!P2:P2000,"*EK43*")+COUNTIF('Coffee Audit'!P2:P2000,"*Mahlk*") | D7: Café workhorse — 98mm vertical flat
B8: Timemore Sculptor | C8: =COUNTIF('Coffee Audit'!P2:P2000,"*Sculptor*") | D8: 064/078 series
B9: DF series | C9: =COUNTIF('Coffee Audit'!P2:P2000,"*DF*") | D9: DF83V at Zerah — 83mm flat
B10: 120mm hybrid/flat | C10: =COUNTIF('Coffee Audit'!P2:P2000,"*120*") | D10: Kyuukei & Maxi — large-format clarity
B11: Unknown / unrecorded | C11: =COUNTIF('Coffee Audit'!P2:P2000,"Unknown") | D11: Early entries pre-hardware-protocol
B13: 🌡️ TEMPERATURE DOCTRINE
B14: Protocol | C14: Where & why
B15: 88°C constant | C15: LAB-ferment ester preservation — Oaks protocol for lactic honey
B16: 90–93°C standard | C16: Washed-lot default across the archive
B17: Thermal oscillation 70→90→70 | C17: Fluid Collective signature — barista-confirmed across all visits
B18: Dual-temp 90+70 | C18: Lume Café honey-Geisha aromatics/body split
B20: 📜 EXTRACTION LAWS — patterns the archive has proven
B21: 1. Flat-bottom geometry outperforms conical for this palate — conical V60 carries a standing over-extraction risk flag.
B22: 2. 1:13–1:14 concentration amplifies polyphenolic bitterness at cool phase and suppresses sucrose (Entries #032, #055).
B23: 3. 1:17 lean on naturals fails to build sucrose-ester mass against CGA lactone bitterness at cool phase.
B24: 4. Barista confirmation overrides visual inference for hardware ID — always.
B25: 5. Large flat burrs (78–98mm) are non-negotiable for oversized varietals (Pacamara, Maragogipe lineage).
B26: 6. Process intensity ceilings exist: Thermal Shock Anaerobic (Entry #059) confirmed the upper boundary of palate tolerance.

Sheet 💰 Price & Value
B1: 💰 PRICE & VALUE INTELLIGENCE
B2: What clarity costs in Singapore, 2026
B4: 💵 PRICE VITALS (SGD, filter entries with recorded price)
B6: AVERAGE | C6: MEDIAN | D6: MIN | E6: MAX | F6: GESHA AVG | G6: NON-GESHA AVG
B7: =AVERAGEIF('Coffee Audit'!Q2:Q2000,">0") | C7: =MEDIAN('Coffee Audit'!Q2:Q2000) | D7: =SMALL('Coffee Audit'!Q2:Q2000,1) | E7: =MAX('Coffee Audit'!Q2:Q2000) | F7: =ROUND(AVERAGEIFS('Coffee Audit'!Q2:Q2000,'Coffee Audit'!W2:W2000,"⭐ GESHA",'Coffee Audit'!Q2:Q2000,">0"),2) | G7: =ROUND(AVERAGEIFS('Coffee Audit'!Q2:Q2000,'Coffee Audit'!W2:W2000,"<>⭐ GESHA",'Coffee Audit'!Q2:Q2000,">0"),2)
B9: 📈 PRICE BAND DISTRIBUTION
B10: Band (SGD) | C10: Entries
B11: ≤ 7 | C11: =COUNTIFS('Coffee Audit'!Q2:Q2000,">0",'Coffee Audit'!Q2:Q2000,"<=7")
B12: 7.01 – 9 | C12: =COUNTIFS('Coffee Audit'!Q2:Q2000,">7",'Coffee Audit'!Q2:Q2000,"<=9")
B13: 9.01 – 12 | C13: =COUNTIFS('Coffee Audit'!Q2:Q2000,">9",'Coffee Audit'!Q2:Q2000,"<=12")
B14: 12.01 – 15 | C14: =COUNTIFS('Coffee Audit'!Q2:Q2000,">12",'Coffee Audit'!Q2:Q2000,"<=15")
B15: 15+ | C15: =COUNTIFS('Coffee Audit'!Q2:Q2000,">15")
B17: 🏅 VALUE VERDICTS
B18: Best value in the archive | C18: Oaks Coffee Co. — Floripondio 90 Hours · SGD 9 (Bolivia Pacamara Lactic Honey, 1600 MASL)
B19: Premium ceiling | C19: Pocket by Flip — SGD 18 Gesha (highest recorded)
B20: Gesha premium | C20: Gesha entries average ~40–50% above non-Gesha — the apex tax is real and consistently paid willingly
B21: Sweet spot | C21: SGD 9–12 band delivers the archive's highest verdict-per-dollar density

Sheet 📅 Archive Timeline
B1: 📅 ARCHIVE TIMELINE & CITY HEATMAP
B2: The 2026 journey, month by month
B4: 📈 ENTRIES PER MONTH — 2026
B6: Month | C6: Jan | D6: Feb | E6: Mar | F6: Apr | G6: May | H6: Jun | I6: Jul | J6: Aug | K6: Sep | L6: Oct | M6: Nov | N6: Dec
B7: Entries | C7: =COUNTIFS('Coffee Audit'!A2:A2000,">="&DATE(2026,1,1),'Coffee Audit'!A2:A2000,"<"&DATE(2026,2,1)) | D7: =COUNTIFS('Coffee Audit'!A2:A2000,">="&DATE(2026,2,1),'Coffee Audit'!A2:A2000,"<"&DATE(2026,3,1)) | E7: =COUNTIFS('Coffee Audit'!A2:A2000,">="&DATE(2026,3,1),'Coffee Audit'!A2:A2000,"<"&DATE(2026,4,1)) | F7: =COUNTIFS('Coffee Audit'!A2:A2000,">="&DATE(2026,4,1),'Coffee Audit'!A2:A2000,"<"&DATE(2026,5,1)) | G7: =COUNTIFS('Coffee Audit'!A2:A2000,">="&DATE(2026,5,1),'Coffee Audit'!A2:A2000,"<"&DATE(2026,6,1)) | H7: =COUNTIFS('Coffee Audit'!A2:A2000,">="&DATE(2026,6,1),'Coffee Audit'!A2:A2000,"<"&DATE(2026,7,1)) | I7: =COUNTIFS('Coffee Audit'!A2:A2000,">="&DATE(2026,7,1),'Coffee Audit'!A2:A2000,"<"&DATE(2026,8,1)) | J7: =COUNTIFS('Coffee Audit'!A2:A2000,">="&DATE(2026,8,1),'Coffee Audit'!A2:A2000,"<"&DATE(2026,9,1)) | K7: =COUNTIFS('Coffee Audit'!A2:A2000,">="&DATE(2026,9,1),'Coffee Audit'!A2:A2000,"<"&DATE(2026,10,1)) | L7: =COUNTIFS('Coffee Audit'!A2:A2000,">="&DATE(2026,10,1),'Coffee Audit'!A2:A2000,"<"&DATE(2026,11,1)) | M7: =COUNTIFS('Coffee Audit'!A2:A2000,">="&DATE(2026,11,1),'Coffee Audit'!A2:A2000,"<"&DATE(2026,12,1)) | N7: =COUNTIFS('Coffee Audit'!A2:A2000,">="&DATE(2026,12,1),'Coffee Audit'!A2:A2000,"<"&DATE(2027,1,1))
B24: 🔥 CITY × MONTH HEATMAP — conditional colour scale, auto-updates
B26: City | C26: Jan | D26: Feb | E26: Mar | F26: Apr | G26: May | H26: Jun | I26: Jul | J26: Aug | K26: Sep | L26: Oct | M26: Nov | N26: Dec
B27: Singapore | C27: =COUNTIFS('Coffee Audit'!A2:A2000,">="&DATE(2026,1,1),'Coffee Audit'!A2:A2000,"<"&DATE(2026,2,1),'Coffee Audit'!B2:B2000,"*Singapore*") | D27: =COUNTIFS('Coffee Audit'!A2:A2000,">="&DATE(2026,2,1),'Coffee Audit'!A2:A2000,"<"&DATE(2026,3,1),'Coffee Audit'!B2:B2000,"*Singapore*") | E27: =COUNTIFS('Coffee Audit'!A2:A2000,">="&DATE(2026,3,1),'Coffee Audit'!A2:A2000,"<"&DATE(2026,4,1),'Coffee Audit'!B2:B2000,"*Singapore*") | F27: =COUNTIFS('Coffee Audit'!A2:A2000,">="&DATE(2026,4,1),'Coffee Audit'!A2:A2000,"<"&DATE(2026,5,1),'Coffee Audit'!B2:B2000,"*Singapore*") | G27: =COUNTIFS('Coffee Audit'!A2:A2000,">="&DATE(2026,5,1),'Coffee Audit'!A2:A2000,"<"&DATE(2026,6,1),'Coffee Audit'!B2:B2000,"*Singapore*") | H27: =COUNTIFS('Coffee Audit'!A2:A2000,">="&DATE(2026,6,1),'Coffee Audit'!A2:A2000,"<"&DATE(2026,7,1),'Coffee Audit'!B2:B2000,"*Singapore*") | I27: =COUNTIFS('Coffee Audit'!A2:A2000,">="&DATE(2026,7,1),'Coffee Audit'!A2:A2000,"<"&DATE(2026,8,1),'Coffee Audit'!B2:B2000,"*Singapore*") | J27: =COUNTIFS('Coffee Audit'!A2:A2000,">="&DATE(2026,8,1),'Coffee Audit'!A2:A2000,"<"&DATE(2026,9,1),'Coffee Audit'!B2:B2000,"*Singapore*") | K27: =COUNTIFS('Coffee Audit'!A2:A2000,">="&DATE(2026,9,1),'Coffee Audit'!A2:A2000,"<"&DATE(2026,10,1),'Coffee Audit'!B2:B2000,"*Singapore*") | L27: =COUNTIFS('Coffee Audit'!A2:A2000,">="&DATE(2026,10,1),'Coffee Audit'!A2:A2000,"<"&DATE(2026,11,1),'Coffee Audit'!B2:B2000,"*Singapore*") | M27: =COUNTIFS('Coffee Audit'!A2:A2000,">="&DATE(2026,11,1),'Coffee Audit'!A2:A2000,"<"&DATE(2026,12,1),'Coffee Audit'!B2:B2000,"*Singapore*") | N27: =COUNTIFS('Coffee Audit'!A2:A2000,">="&DATE(2026,12,1),'Coffee Audit'!A2:A2000,"<"&DATE(2027,1,1),'Coffee Audit'!B2:B2000,"*Singapore*")
B28: Ubud, Bali | C28: =COUNTIFS('Coffee Audit'!A2:A2000,">="&DATE(2026,1,1),'Coffee Audit'!A2:A2000,"<"&DATE(2026,2,1),'Coffee Audit'!B2:B2000,"*Ubud*") | D28: =COUNTIFS('Coffee Audit'!A2:A2000,">="&DATE(2026,2,1),'Coffee Audit'!A2:A2000,"<"&DATE(2026,3,1),'Coffee Audit'!B2:B2000,"*Ubud*") | E28: =COUNTIFS('Coffee Audit'!A2:A2000,">="&DATE(2026,3,1),'Coffee Audit'!A2:A2000,"<"&DATE(2026,4,1),'Coffee Audit'!B2:B2000,"*Ubud*") | F28: =COUNTIFS('Coffee Audit'!A2:A2000,">="&DATE(2026,4,1),'Coffee Audit'!A2:A2000,"<"&DATE(2026,5,1),'Coffee Audit'!B2:B2000,"*Ubud*") | G28: =COUNTIFS('Coffee Audit'!A2:A2000,">="&DATE(2026,5,1),'Coffee Audit'!A2:A2000,"<"&DATE(2026,6,1),'Coffee Audit'!B2:B2000,"*Ubud*") | H28: =COUNTIFS('Coffee Audit'!A2:A2000,">="&DATE(2026,6,1),'Coffee Audit'!A2:A2000,"<"&DATE(2026,7,1),'Coffee Audit'!B2:B2000,"*Ubud*") | I28: =COUNTIFS('Coffee Audit'!A2:A2000,">="&DATE(2026,7,1),'Coffee Audit'!A2:A2000,"<"&DATE(2026,8,1),'Coffee Audit'!B2:B2000,"*Ubud*") | J28: =COUNTIFS('Coffee Audit'!A2:A2000,">="&DATE(2026,8,1),'Coffee Audit'!A2:A2000,"<"&DATE(2026,9,1),'Coffee Audit'!B2:B2000,"*Ubud*") | K28: =COUNTIFS('Coffee Audit'!A2:A2000,">="&DATE(2026,9,1),'Coffee Audit'!A2:A2000,"<"&DATE(2026,10,1),'Coffee Audit'!B2:B2000,"*Ubud*") | L28: =COUNTIFS('Coffee Audit'!A2:A2000,">="&DATE(2026,10,1),'Coffee Audit'!A2:A2000,"<"&DATE(2026,11,1),'Coffee Audit'!B2:B2000,"*Ubud*") | M28: =COUNTIFS('Coffee Audit'!A2:A2000,">="&DATE(2026,11,1),'Coffee Audit'!A2:A2000,"<"&DATE(2026,12,1),'Coffee Audit'!B2:B2000,"*Ubud*") | N28: =COUNTIFS('Coffee Audit'!A2:A2000,">="&DATE(2026,12,1),'Coffee Audit'!A2:A2000,"<"&DATE(2027,1,1),'Coffee Audit'!B2:B2000,"*Ubud*")
B29: Mumbai | C29: =COUNTIFS('Coffee Audit'!A2:A2000,">="&DATE(2026,1,1),'Coffee Audit'!A2:A2000,"<"&DATE(2026,2,1),'Coffee Audit'!B2:B2000,"*Mumbai*") | D29: =COUNTIFS('Coffee Audit'!A2:A2000,">="&DATE(2026,2,1),'Coffee Audit'!A2:A2000,"<"&DATE(2026,3,1),'Coffee Audit'!B2:B2000,"*Mumbai*") | E29: =COUNTIFS('Coffee Audit'!A2:A2000,">="&DATE(2026,3,1),'Coffee Audit'!A2:A2000,"<"&DATE(2026,4,1),'Coffee Audit'!B2:B2000,"*Mumbai*") | F29: =COUNTIFS('Coffee Audit'!A2:A2000,">="&DATE(2026,4,1),'Coffee Audit'!A2:A2000,"<"&DATE(2026,5,1),'Coffee Audit'!B2:B2000,"*Mumbai*") | G29: =COUNTIFS('Coffee Audit'!A2:A2000,">="&DATE(2026,5,1),'Coffee Audit'!A2:A2000,"<"&DATE(2026,6,1),'Coffee Audit'!B2:B2000,"*Mumbai*") | H29: =COUNTIFS('Coffee Audit'!A2:A2000,">="&DATE(2026,6,1),'Coffee Audit'!A2:A2000,"<"&DATE(2026,7,1),'Coffee Audit'!B2:B2000,"*Mumbai*") | I29: =COUNTIFS('Coffee Audit'!A2:A2000,">="&DATE(2026,7,1),'Coffee Audit'!A2:A2000,"<"&DATE(2026,8,1),'Coffee Audit'!B2:B2000,"*Mumbai*") | J29: =COUNTIFS('Coffee Audit'!A2:A2000,">="&DATE(2026,8,1),'Coffee Audit'!A2:A2000,"<"&DATE(2026,9,1),'Coffee Audit'!B2:B2000,"*Mumbai*") | K29: =COUNTIFS('Coffee Audit'!A2:A2000,">="&DATE(2026,9,1),'Coffee Audit'!A2:A2000,"<"&DATE(2026,10,1),'Coffee Audit'!B2:B2000,"*Mumbai*") | L29: =COUNTIFS('Coffee Audit'!A2:A2000,">="&DATE(2026,10,1),'Coffee Audit'!A2:A2000,"<"&DATE(2026,11,1),'Coffee Audit'!B2:B2000,"*Mumbai*") | M29: =COUNTIFS('Coffee Audit'!A2:A2000,">="&DATE(2026,11,1),'Coffee Audit'!A2:A2000,"<"&DATE(2026,12,1),'Coffee Audit'!B2:B2000,"*Mumbai*") | N29: =COUNTIFS('Coffee Audit'!A2:A2000,">="&DATE(2026,12,1),'Coffee Audit'!A2:A2000,"<"&DATE(2027,1,1),'Coffee Audit'!B2:B2000,"*Mumbai*")
B30: Johor Bahru | C30: =COUNTIFS('Coffee Audit'!A2:A2000,">="&DATE(2026,1,1),'Coffee Audit'!A2:A2000,"<"&DATE(2026,2,1),'Coffee Audit'!B2:B2000,"*Johor Bahru*") | D30: =COUNTIFS('Coffee Audit'!A2:A2000,">="&DATE(2026,2,1),'Coffee Audit'!A2:A2000,"<"&DATE(2026,3,1),'Coffee Audit'!B2:B2000,"*Johor Bahru*") | E30: =COUNTIFS('Coffee Audit'!A2:A2000,">="&DATE(2026,3,1),'Coffee Audit'!A2:A2000,"<"&DATE(2026,4,1),'Coffee Audit'!B2:B2000,"*Johor Bahru*") | F30: =COUNTIFS('Coffee Audit'!A2:A2000,">="&DATE(2026,4,1),'Coffee Audit'!A2:A2000,"<"&DATE(2026,5,1),'Coffee Audit'!B2:B2000,"*Johor Bahru*") | G30: =COUNTIFS('Coffee Audit'!A2:A2000,">="&DATE(2026,5,1),'Coffee Audit'!A2:A2000,"<"&DATE(2026,6,1),'Coffee Audit'!B2:B2000,"*Johor Bahru*") | H30: =COUNTIFS('Coffee Audit'!A2:A2000,">="&DATE(2026,6,1),'Coffee Audit'!A2:A2000,"<"&DATE(2026,7,1),'Coffee Audit'!B2:B2000,"*Johor Bahru*") | I30: =COUNTIFS('Coffee Audit'!A2:A2000,">="&DATE(2026,7,1),'Coffee Audit'!A2:A2000,"<"&DATE(2026,8,1),'Coffee Audit'!B2:B2000,"*Johor Bahru*") | J30: =COUNTIFS('Coffee Audit'!A2:A2000,">="&DATE(2026,8,1),'Coffee Audit'!A2:A2000,"<"&DATE(2026,9,1),'Coffee Audit'!B2:B2000,"*Johor Bahru*") | K30: =COUNTIFS('Coffee Audit'!A2:A2000,">="&DATE(2026,9,1),'Coffee Audit'!A2:A2000,"<"&DATE(2026,10,1),'Coffee Audit'!B2:B2000,"*Johor Bahru*") | L30: =COUNTIFS('Coffee Audit'!A2:A2000,">="&DATE(2026,10,1),'Coffee Audit'!A2:A2000,"<"&DATE(2026,11,1),'Coffee Audit'!B2:B2000,"*Johor Bahru*") | M30: =COUNTIFS('Coffee Audit'!A2:A2000,">="&DATE(2026,11,1),'Coffee Audit'!A2:A2000,"<"&DATE(2026,12,1),'Coffee Audit'!B2:B2000,"*Johor Bahru*") | N30: =COUNTIFS('Coffee Audit'!A2:A2000,">="&DATE(2026,12,1),'Coffee Audit'!A2:A2000,"<"&DATE(2027,1,1),'Coffee Audit'!B2:B2000,"*Johor Bahru*")
B32: 🧭 CHAPTER NARRATIVE
B33: Jan — Bali Origin | C33: The archive begins at Seniman, Ubud — three cups, one habit born.
B34: Feb–Mar — Calibration | C34: Kenya Kiamugumo AA at Kyuukei sets the washed-clarity measuring stick; Mumbai chapter opens.
B35: Apr — Acceleration | C35: Gesha register opens in earnest; JB cross-border audit; ratio chemistry lessons logged.
B36: May–Jun — Depth | C36: Trilogy hunting, hardware literacy peaks, watchlist targets cleared one by one.
B37: Jul — The Discovery Month | C37: Oaks Coffee Co. found on Day 4 of operations; Bolivia/Pacamara/Lactic-Honey/P80 firsts; Abseil & the CT62 classification; mock-judge debut at Homeground.

Sheet 🏙️ Café Directory
B1: 🏙️ CAFÉ DIRECTORY — 33 VENUES · 4 CITIES
B2: Live-verified across SuperGrok · ChatGPT · Gemini · Archive direct observation · July 2026
B4: 🌏 BY CITY — COVERAGE
B6: City | C6: Entries | D6: Cafés | E6: Coverage | F6: Note
B7: Singapore | C7: =COUNTIF('Coffee Audit'!B2:B2000,"*Singapore*") | D7: =SUMPRODUCT(('Coffee Audit'!B2:B2000="Singapore")/COUNTIF('Coffee Audit'!B2:B2000,'Coffee Audit'!B2:B2000&"")) | E7: 28/33 cafés | F7: Primary market
B8: Ubud, Bali | C8: =COUNTIF('Coffee Audit'!B2:B2000,"*Bali*") | D8: 1 | E8: 1 café | F8: Archive origin chapter
B9: Mumbai | C9: =COUNTIF('Coffee Audit'!B2:B2000,"*Mumbai*") | D9: 2 | E9: 2 cafés | F9: Expansion frontier
B10: Johor Bahru | C10: =COUNTIF('Coffee Audit'!B2:B2000,"*Johor*") | D10: 1 | E10: 1 café | F10: Cross-border audit
B12: ☕ COMPLETE VERIFIED DIRECTORY
B14: Café | C14: City | D14: Entries | E14: Gesha | F14: Avg SGD | G14: Verified Address | H14: Instagram | I14: Website | J14: Confidence | K14: Notes
B15: Nylon Coffee Roasters | C15: Singapore | D15: =COUNTIF('Coffee Audit'!C2:C2000,B15) | E15: =SUMPRODUCT(('Coffee Audit'!C2:C2000=B15)*('Coffee Audit'!W2:W2000="⭐ GESHA")) | F15: =IFERROR(ROUND(AVERAGEIFS('Coffee Audit'!Q2:Q2000,'Coffee Audit'!C2:C2000,B15,'Coffee Audit'!Q2:Q2000,">0"),2),"—") | G15: 4 Everton Park, #01-40, Singapore | H15: @nyloncoffeeroasters | I15: nyloncoffee.sg | J15: ✅ HIGH | K15: Reliability anchor · 5 visits
B16: Asylum Coffeehouse | C16: Singapore | D16: =COUNTIF('Coffee Audit'!C2:C2000,B16) | E16: =SUMPRODUCT(('Coffee Audit'!C2:C2000=B16)*('Coffee Audit'!W2:W2000="⭐ GESHA")) | F16: =IFERROR(ROUND(AVERAGEIFS('Coffee Audit'!Q2:Q2000,'Coffee Audit'!C2:C2000,B16,'Coffee Audit'!Q2:Q2000,">0"),2),"—") | G16: 311 Jalan Besar, Singapore 208970 | H16: Unknown | I16: Unknown | J16: ✅ HIGH | K16: 4 visits · 2 Gesha entries
B17: Seniman Coffee Studio | C17: Ubud, Bali | D17: =COUNTIF('Coffee Audit'!C2:C2000,B17) | E17: =SUMPRODUCT(('Coffee Audit'!C2:C2000=B17)*('Coffee Audit'!W2:W2000="⭐ GESHA")) | F17: =IFERROR(ROUND(AVERAGEIFS('Coffee Audit'!Q2:Q2000,'Coffee Audit'!C2:C2000,B17,'Coffee Audit'!Q2:Q2000,">0"),2),"—") | G17: Jl. Sriwedari, Ubud, Bali | H17: @senimancoffee | I17: senimancoffee.com | J17: ◐ MEDIUM | K17: Archive origin venue
B18: Kyuukei Coffee | C18: Singapore | D18: =COUNTIF('Coffee Audit'!C2:C2000,B18) | E18: =SUMPRODUCT(('Coffee Audit'!C2:C2000=B18)*('Coffee Audit'!W2:W2000="⭐ GESHA")) | F18: =IFERROR(ROUND(AVERAGEIFS('Coffee Audit'!Q2:Q2000,'Coffee Audit'!C2:C2000,B18,'Coffee Audit'!Q2:Q2000,">0"),2),"—") | G18: 121 Bukit Merah Ln 1 #01-06 · 5 Kadayanallur St #01-04 | H18: @kyuukeicoffee | I18: kyuukeicoffee.com | J18: ✅ HIGH | K18: 2 outlets · 3 archive visits
B19: Agora Coffee | C19: Singapore | D19: =COUNTIF('Coffee Audit'!C2:C2000,B19) | E19: =SUMPRODUCT(('Coffee Audit'!C2:C2000=B19)*('Coffee Audit'!W2:W2000="⭐ GESHA")) | F19: =IFERROR(ROUND(AVERAGEIFS('Coffee Audit'!Q2:Q2000,'Coffee Audit'!C2:C2000,B19,'Coffee Audit'!Q2:Q2000,">0"),2),"—") | G19: 31 Club Street, #01-02, Singapore 069468 | H19: @agoracoffeecs | I19: Unknown | J19: ✅ HIGH | K19: Gemini + ChatGPT agree
B20: Narrative Coffee Stand | C20: Singapore | D20: =COUNTIF('Coffee Audit'!C2:C2000,B20) | E20: =SUMPRODUCT(('Coffee Audit'!C2:C2000=B20)*('Coffee Audit'!W2:W2000="⭐ GESHA")) | F20: =IFERROR(ROUND(AVERAGEIFS('Coffee Audit'!Q2:Q2000,'Coffee Audit'!C2:C2000,B20,'Coffee Audit'!Q2:Q2000,">0"),2),"—") | G20: No fixed address (stand/pop-up format) | H20: Unknown | I20: Unknown | J20: ⚠️ LOW | K20: Small independent
B21: ASK Coffee Roastery | C21: Singapore | D21: =COUNTIF('Coffee Audit'!C2:C2000,B21) | E21: =SUMPRODUCT(('Coffee Audit'!C2:C2000=B21)*('Coffee Audit'!W2:W2000="⭐ GESHA")) | F21: =IFERROR(ROUND(AVERAGEIFS('Coffee Audit'!Q2:Q2000,'Coffee Audit'!C2:C2000,B21,'Coffee Audit'!Q2:Q2000,">0"),2),"—") | G21: 32 Seah Street, Singapore 188388 | H21: @askcoffeeroastery | I21: Unknown (IG primary) | J21: ✅ HIGH | K21: Gemini + ChatGPT agree · experimental lots
B22: Tiong Hoe Specialty Coffee | C22: Singapore | D22: =COUNTIF('Coffee Audit'!C2:C2000,B22) | E22: =SUMPRODUCT(('Coffee Audit'!C2:C2000=B22)*('Coffee Audit'!W2:W2000="⭐ GESHA")) | F22: =IFERROR(ROUND(AVERAGEIFS('Coffee Audit'!Q2:Q2000,'Coffee Audit'!C2:C2000,B22,'Coffee Audit'!Q2:Q2000,">0"),2),"—") | G22: 170 Stirling Road, #01-1133, Singapore 140170 (flagship; 10 outlets) | H22: Unknown | I22: tionghoe.com | J22: ✅ HIGH | K22: Established multi-outlet roaster
B23: Maxi Coffee Bar | C23: Singapore | D23: =COUNTIF('Coffee Audit'!C2:C2000,B23) | E23: =SUMPRODUCT(('Coffee Audit'!C2:C2000=B23)*('Coffee Audit'!W2:W2000="⭐ GESHA")) | F23: =IFERROR(ROUND(AVERAGEIFS('Coffee Audit'!Q2:Q2000,'Coffee Audit'!C2:C2000,B23,'Coffee Audit'!Q2:Q2000,">0"),2),"—") | G23: 64 Club Street (back entrance), Singapore 069438 | H23: Unknown | I23: maxicoffeebar.com | J23: ✅ HIGH | K23: ChatGPT + Gemini agree · ~4.7 Google
B24: Kurasu | C24: Singapore | D24: =COUNTIF('Coffee Audit'!C2:C2000,B24) | E24: =SUMPRODUCT(('Coffee Audit'!C2:C2000=B24)*('Coffee Audit'!W2:W2000="⭐ GESHA")) | F24: =IFERROR(ROUND(AVERAGEIFS('Coffee Audit'!Q2:Q2000,'Coffee Audit'!C2:C2000,B24,'Coffee Audit'!Q2:Q2000,">0"),2),"—") | G24: 261 Waterloo Street, #01-24, Singapore 180261 | H24: @kurasu.sg | I24: kurasu.sg | J24: ✅ HIGH | K24: Japanese origin · ChatGPT verified
B25: Zerah Roasters | C25: Singapore | D25: =COUNTIF('Coffee Audit'!C2:C2000,B25) | E25: =SUMPRODUCT(('Coffee Audit'!C2:C2000=B25)*('Coffee Audit'!W2:W2000="⭐ GESHA")) | F25: =IFERROR(ROUND(AVERAGEIFS('Coffee Audit'!Q2:Q2000,'Coffee Audit'!C2:C2000,B25,'Coffee Audit'!Q2:Q2000,">0"),2),"—") | G25: 465 North Bridge Road, #02-5063, Singapore | H25: @zerahroasters | I25: zerahcoffeeroasters.com | J25: ✅ HIGH | K25: Barista confirmed · Entry #047
B26: Keryi Coffee | C26: Singapore | D26: =COUNTIF('Coffee Audit'!C2:C2000,B26) | E26: =SUMPRODUCT(('Coffee Audit'!C2:C2000=B26)*('Coffee Audit'!W2:W2000="⭐ GESHA")) | F26: =IFERROR(ROUND(AVERAGEIFS('Coffee Audit'!Q2:Q2000,'Coffee Audit'!C2:C2000,B26,'Coffee Audit'!Q2:Q2000,">0"),2),"—") | G26: 161 Lavender Street, #01-08, Singapore 338750 | H26: @keryicoffee | I26: keryicoffee.com | J26: ✅ HIGH | K26: Gemini + ChatGPT · closed Fri for production
B27: Apartment (Jalan Riang) | C27: Singapore | D27: =COUNTIF('Coffee Audit'!C2:C2000,B27) | E27: =SUMPRODUCT(('Coffee Audit'!C2:C2000=B27)*('Coffee Audit'!W2:W2000="⭐ GESHA")) | F27: =IFERROR(ROUND(AVERAGEIFS('Coffee Audit'!Q2:Q2000,'Coffee Audit'!C2:C2000,B27,'Coffee Audit'!Q2:Q2000,">0"),2),"—") | G27: Jalan Riang, Singapore (weekends only, ~Jun 2025) | H27: @apartmentcoffee.co | I27: apartmentcoffee.co | J27: ✅ HIGH | K27: Roastery branch · weekends only
B28: Homeground Coffee Roasters | C28: Singapore | D28: =COUNTIF('Coffee Audit'!C2:C2000,B28) | E28: =SUMPRODUCT(('Coffee Audit'!C2:C2000=B28)*('Coffee Audit'!W2:W2000="⭐ GESHA")) | F28: =IFERROR(ROUND(AVERAGEIFS('Coffee Audit'!Q2:Q2000,'Coffee Audit'!C2:C2000,B28,'Coffee Audit'!Q2:Q2000,">0"),2),"—") | G28: 911 Bukit Timah Road, Singapore | H28: @homegroundcoffeeroasters | I28: homegroundcoffee.sg | J28: ✅ HIGH | K28: SuperGrok + Project KB
B29: Fluid Collective | C29: Singapore | D29: =COUNTIF('Coffee Audit'!C2:C2000,B29) | E29: =SUMPRODUCT(('Coffee Audit'!C2:C2000=B29)*('Coffee Audit'!W2:W2000="⭐ GESHA")) | F29: =IFERROR(ROUND(AVERAGEIFS('Coffee Audit'!Q2:Q2000,'Coffee Audit'!C2:C2000,B29,'Coffee Audit'!Q2:Q2000,">0"),2),"—") | G29: 24 Opal Crescent, Singapore | H29: @fluidcollective | I29: Unknown | J29: ✅ HIGH | K29: 2025 Brewers Cup champion · elite hardware
B30: Subko Coffee Roasters | C30: Mumbai | D30: =COUNTIF('Coffee Audit'!C2:C2000,B30) | E30: =SUMPRODUCT(('Coffee Audit'!C2:C2000=B30)*('Coffee Audit'!W2:W2000="⭐ GESHA")) | F30: =IFERROR(ROUND(AVERAGEIFS('Coffee Audit'!Q2:Q2000,'Coffee Audit'!C2:C2000,B30,'Coffee Audit'!Q2:Q2000,">0"),2),"—") | G30: Bandra/Khar area, Mumbai, India | H30: @subkocoffee | I30: subko.coffee | J30: ◐ MEDIUM | K30: City-level verified
B31: Grey Soul Coffee Roasters | C31: Mumbai | D31: =COUNTIF('Coffee Audit'!C2:C2000,B31) | E31: =SUMPRODUCT(('Coffee Audit'!C2:C2000=B31)*('Coffee Audit'!W2:W2000="⭐ GESHA")) | F31: =IFERROR(ROUND(AVERAGEIFS('Coffee Audit'!Q2:Q2000,'Coffee Audit'!C2:C2000,B31,'Coffee Audit'!Q2:Q2000,">0"),2),"—") | G31: Mumbai, India | H31: @greysoulcoffee | I31: Unknown | J31: ◐ MEDIUM | K31: City-level verified
B32: Apartment (Selegie Rd) | C32: Singapore | D32: =COUNTIF('Coffee Audit'!C2:C2000,B32) | E32: =SUMPRODUCT(('Coffee Audit'!C2:C2000=B32)*('Coffee Audit'!W2:W2000="⭐ GESHA")) | F32: =IFERROR(ROUND(AVERAGEIFS('Coffee Audit'!Q2:Q2000,'Coffee Audit'!C2:C2000,B32,'Coffee Audit'!Q2:Q2000,">0"),2),"—") | G32: 139 Selegie Road, #01-01, Singapore 188309 | H32: @apartmentcoffee.co | I32: apartmentcoffee.co | J32: ✅ HIGH | K32: SuperGrok (TimeOut + official site) · #6 world ranked
B33: Lume Café | C33: Singapore | D33: =COUNTIF('Coffee Audit'!C2:C2000,B33) | E33: =SUMPRODUCT(('Coffee Audit'!C2:C2000=B33)*('Coffee Audit'!W2:W2000="⭐ GESHA")) | F33: =IFERROR(ROUND(AVERAGEIFS('Coffee Audit'!Q2:Q2000,'Coffee Audit'!C2:C2000,B33,'Coffee Audit'!Q2:Q2000,">0"),2),"—") | G33: 108 Robinson Road, #01-01, Singapore 068900 | H33: @lume_sg | I33: lume.sg | J33: ✅ HIGH | K33: Gemini + ChatGPT agree (official site + DFD)
B34: Alchemist (Raffles Place) | C34: Singapore | D34: =COUNTIF('Coffee Audit'!C2:C2000,B34) | E34: =SUMPRODUCT(('Coffee Audit'!C2:C2000=B34)*('Coffee Audit'!W2:W2000="⭐ GESHA")) | F34: =IFERROR(ROUND(AVERAGEIFS('Coffee Audit'!Q2:Q2000,'Coffee Audit'!C2:C2000,B34,'Coffee Audit'!Q2:Q2000,">0"),2),"—") | G34: 16 Raffles Quay, #01-08, Hong Leong Building, Singapore 048581 | H34: @alchemist.global | I34: alchemist.global | J34: ✅ HIGH | K34: SuperGrok · distinct from OFC branch
B35: The Community Coffee (Hamilton) | C35: Singapore | D35: =COUNTIF('Coffee Audit'!C2:C2000,B35) | E35: =SUMPRODUCT(('Coffee Audit'!C2:C2000=B35)*('Coffee Audit'!W2:W2000="⭐ GESHA")) | F35: =IFERROR(ROUND(AVERAGEIFS('Coffee Audit'!Q2:Q2000,'Coffee Audit'!C2:C2000,B35,'Coffee Audit'!Q2:Q2000,">0"),2),"—") | G35: Hamilton Road, Singapore (exact unit unconfirmed) | H35: Unknown | I35: Unknown | J35: ⚠️ LOW | K35: Small independent · area verified only
B36: Alchemist (Ocean Financial Centre) | C36: Singapore | D36: =COUNTIF('Coffee Audit'!C2:C2000,B36) | E36: =SUMPRODUCT(('Coffee Audit'!C2:C2000=B36)*('Coffee Audit'!W2:W2000="⭐ GESHA")) | F36: =IFERROR(ROUND(AVERAGEIFS('Coffee Audit'!Q2:Q2000,'Coffee Audit'!C2:C2000,B36,'Coffee Audit'!Q2:Q2000,">0"),2),"—") | G36: 10 Collyer Quay, #01-K1, Singapore 049315 | H36: @alchemist.global | I36: alchemist.global | J36: ✅ HIGH | K36: SuperGrok (official stores page)
B37: PPP Coffee (Funan) | C37: Singapore | D37: =COUNTIF('Coffee Audit'!C2:C2000,B37) | E37: =SUMPRODUCT(('Coffee Audit'!C2:C2000=B37)*('Coffee Audit'!W2:W2000="⭐ GESHA")) | F37: =IFERROR(ROUND(AVERAGEIFS('Coffee Audit'!Q2:Q2000,'Coffee Audit'!C2:C2000,B37,'Coffee Audit'!Q2:Q2000,">0"),2),"—") | G37: Funan Mall, 107 North Bridge Road, Singapore | H37: Unknown | I37: Unknown | J37: ✅ HIGH | K37: Project KB + mall directory
B38: 2050 Coffee | C38: Singapore | D38: =COUNTIF('Coffee Audit'!C2:C2000,B38) | E38: =SUMPRODUCT(('Coffee Audit'!C2:C2000=B38)*('Coffee Audit'!W2:W2000="⭐ GESHA")) | F38: =IFERROR(ROUND(AVERAGEIFS('Coffee Audit'!Q2:Q2000,'Coffee Audit'!C2:C2000,B38,'Coffee Audit'!Q2:Q2000,">0"),2),"—") | G38: 267 Beach Road, #01-01, Singapore 199545 | H38: @2050.coffee | I38: Unknown (IG primary) | J38: ✅ HIGH | K38: ChatGPT + Gemini · automated tap concept · opened Jan 2025
B39: Corner Corner | C39: Singapore | D39: =COUNTIF('Coffee Audit'!C2:C2000,B39) | E39: =SUMPRODUCT(('Coffee Audit'!C2:C2000=B39)*('Coffee Audit'!W2:W2000="⭐ GESHA")) | F39: =IFERROR(ROUND(AVERAGEIFS('Coffee Audit'!Q2:Q2000,'Coffee Audit'!C2:C2000,B39,'Coffee Audit'!Q2:Q2000,">0"),2),"—") | G39: 16 Duxton Road, Singapore 089482 (daytime vinyl concept inside RPM) | H39: @corner___corner | I39: Unknown | J39: ✅ HIGH | K39: ChatGPT + Gemini · daytime only ~11am-5pm
B40: Clod Coffee Bar & Roasters | C40: Johor Bahru | D40: =COUNTIF('Coffee Audit'!C2:C2000,B40) | E40: =SUMPRODUCT(('Coffee Audit'!C2:C2000=B40)*('Coffee Audit'!W2:W2000="⭐ GESHA")) | F40: =IFERROR(ROUND(AVERAGEIFS('Coffee Audit'!Q2:Q2000,'Coffee Audit'!C2:C2000,B40,'Coffee Audit'!Q2:Q2000,">0"),2),"—") | G40: 123, Jln Beringin, Taman Melodies, 80250 Johor Bahru, Johor, Malaysia | H40: Unknown | I40: Unknown | J40: ✅ LOCK | K40: Direct confirmation — replaces Unknown
B41: Equate Coffee | C41: Singapore | D41: =COUNTIF('Coffee Audit'!C2:C2000,B41) | E41: =SUMPRODUCT(('Coffee Audit'!C2:C2000=B41)*('Coffee Audit'!W2:W2000="⭐ GESHA")) | F41: =IFERROR(ROUND(AVERAGEIFS('Coffee Audit'!Q2:Q2000,'Coffee Audit'!C2:C2000,B41,'Coffee Audit'!Q2:Q2000,">0"),2),"—") | G41: 1 Tanjong Pagar Plaza, #02-25, Singapore 082001 | H41: @equatecoffee | I41: equate.sg | J41: ✅ HIGH | K41: SuperGrok (IG + Wanderlog)
B42: Pocket by Flip (Flip Coffee Roasters) | C42: Singapore | D42: =COUNTIF('Coffee Audit'!C2:C2000,B42) | E42: =SUMPRODUCT(('Coffee Audit'!C2:C2000=B42)*('Coffee Audit'!W2:W2000="⭐ GESHA")) | F42: =IFERROR(ROUND(AVERAGEIFS('Coffee Audit'!Q2:Q2000,'Coffee Audit'!C2:C2000,B42,'Coffee Audit'!Q2:Q2000,">0"),2),"—") | G42: 619H Bukit Timah Road, Singapore | H42: @flipcoffeeroasters | I42: Unknown | J42: ✅ HIGH | K42: Project KB
B43: Cowpresso Coffee Roasters | C43: Singapore | D43: =COUNTIF('Coffee Audit'!C2:C2000,B43) | E43: =SUMPRODUCT(('Coffee Audit'!C2:C2000=B43)*('Coffee Audit'!W2:W2000="⭐ GESHA")) | F43: =IFERROR(ROUND(AVERAGEIFS('Coffee Audit'!Q2:Q2000,'Coffee Audit'!C2:C2000,B43,'Coffee Audit'!Q2:Q2000,">0"),2),"—") | G43: 21 Lor Kilat, #01-07, Singapore 598123 | H43: @cowpressocoffee | I43: cowpressocoffee.sg | J43: ✅ HIGH | K43: SuperGrok (ClassPass + Wanderlog)
B44: Pinhole Coffee Bar | C44: Singapore | D44: =COUNTIF('Coffee Audit'!C2:C2000,B44) | E44: =SUMPRODUCT(('Coffee Audit'!C2:C2000=B44)*('Coffee Audit'!W2:W2000="⭐ GESHA")) | F44: =IFERROR(ROUND(AVERAGEIFS('Coffee Audit'!Q2:Q2000,'Coffee Audit'!C2:C2000,B44,'Coffee Audit'!Q2:Q2000,">0"),2),"—") | G44: 27 Purvis Street, #01-02, Singapore 188604 | H44: @pinholecoffeebar | I44: pinhole.cafe | J44: ✅ HIGH | K44: SuperGrok (middleclass.sg + TimeOut)
B45: Oaks Coffee Co. | C45: Singapore | D45: =COUNTIF('Coffee Audit'!C2:C2000,B45) | E45: =SUMPRODUCT(('Coffee Audit'!C2:C2000=B45)*('Coffee Audit'!W2:W2000="⭐ GESHA")) | F45: =IFERROR(ROUND(AVERAGEIFS('Coffee Audit'!Q2:Q2000,'Coffee Audit'!C2:C2000,B45,'Coffee Audit'!Q2:Q2000,">0"),2),"—") | G45: 619H Bukit Timah Road, Singapore 269728 | H45: @oakscoffeeco | I45: oakscoffeeco.com | J45: ✅ LOCK | K45: Direct confirmation · Day 4 of operations at visit
B46: Abseil | C46: Singapore | D46: =COUNTIF('Coffee Audit'!C2:C2000,B46) | E46: =SUMPRODUCT(('Coffee Audit'!C2:C2000=B46)*('Coffee Audit'!W2:W2000="⭐ GESHA")) | F46: =IFERROR(ROUND(AVERAGEIFS('Coffee Audit'!Q2:Q2000,'Coffee Audit'!C2:C2000,B46,'Coffee Audit'!Q2:Q2000,">0"),2),"—") | G46: 70 Shenton Way, #01-14, Eon Shenton, Singapore 079118 | H46: @abseil.coffee | I46: abseilcoffee.com | J46: ✅ HIGH | K46: SuperGrok (indulgentism + eatbook) · hours vary — verify IG
B49: 🔑 ADDRESS VERIFICATION LEGEND
B51: ✅ HIGH | C51: 2+ independent sources agree (SuperGrok + ChatGPT/Gemini/Project KB)
B52: ✅ LOCK | C52: Direct confirmation by Hari — overrides all AI sources
B53: ◐ MEDIUM | C53: 1 source only or area-level verified — archive observation primary
B54: ⚠️ LOW | C54: No fixed address found — stand/pop-up or micro-independent

Sheet Legend
B1: 📖 LEGEND & MAINTENANCE GUIDE
B2: How to read — and how to grow — this archive
B4: 🎨 COLOUR LEGEND — Coffee Audit sheet
C5: Even-row banding (auto via conditional formatting)
C6: Odd-row banding (auto)
C7: ⭐ GESHA row — auto-applied when Varietal contains Gesha/Geisha
C8: Header — dark espresso with cream text
B10: 🛠️ HOW TO ADD A NEW ENTRY (keeps everything live)
B11: 1. Add the new row directly below the last entry on the Coffee Audit sheet (columns A–V).
B12: 2. Copy the Gesha_Alert formula (column W) down from the row above — it self-detects Gesha/Geisha.
B13: 3. Row colours, Dashboard vitals, Directory counts, Timeline, heatmap and price stats all update automatically (formulas scan to row 2000).
B14: 4. Enter Price/Dose/Yield as numbers where known; text "Unknown" is safely ignored by all statistics.
B15: 5. New café? Add one row to the Café Directory table (name must match column C exactly) — counts go live instantly.
B16: 6. New origin or process family? Add a row to the relevant league table on Origin/Palate sheets and copy the COUNTIF pattern.
B17: 7. Charts read the helper tables — no chart editing needed for routine entries.
B18: 8. Editorial panels (Thesis, Honours, Chapters, Value Verdicts) are curated by hand — update after milestone visits.
B20: 📜 ARCHIVE INTEGRITY RULES
B21: Uploaded files are the authoritative baseline — entries are appended, never reconstructed from memory.
B22: Entry numbers derive from sequential archive count only.
... B27: The archive records one palate only — external notes are reference, never overwrite.

Sheet Stats
A1: Consolidation Summary
A3: Total unique entries | B3: =COUNTA('Coffee Audit'!A2:A2000)
A4: Merged (both sources) | B4: 15
A5: ChatGPT-only (new) | B5: 8
A6: Gemini-only (retained) | B6: 5
A7: Cities covered | B7: =SUMPRODUCT(('Coffee Audit'!B2:B2000<>"")/COUNTIF('Coffee Audit'!B2:B2000,'Coffee Audit'!B2:B2000&""))
A8: Unique cafes | B8: =SUMPRODUCT(('Coffee Audit'!C2:C2000<>"")/COUNTIF('Coffee Audit'!C2:C2000,'Coffee Audit'!C2:C2000&""))
A9: Date range | B9: =TEXT(MIN('Coffee Audit'!A2:A2000),"YYYY-MM-DD")&" → "&TEXT(MAX('Coffee Audit'!A2:A2000),"YYYY-MM-DD")
