Workbook

Sheet Coffee Audit
A1: Date | B1: City | C1: Cafe_Name | D1: Coffee_Name | E1: Producer_Farm | F1: Origin | G1: Varietal | H1: Process | I1: Roast_Level | J1: Brew_Method | K1: Dose_g | L1: Yield_g | M1: Ratio | N1: Water_Temp_C | O1: Bloom | P1: Grinder | Q1: Price_SGD | R1: Official_Notes | S1: Your_Verdict | T1: Technical_Enrichment | U1: Visit_Context | V1: Source | W1: Gesha_Alert | X1: Address
A2: 46025 | B2: Ubud, Bali | C2: Seniman Coffee Studio | D2: Bali Karana Kintamanis | E2: Unknown | F2: Kintamani, Bali | G2: Unknown | H2: Natural | I2: Light | J2: Filter | K2: Unknown | L2: Unknown | M2: Unknown | N2: Unknown | O2: Unknown | P2: Unknown | Q2: Unknown | R2: Clean citrus; floral | S2: Excellent clarity for a natural process; clean citrus and floral notes. | T2: Natural processing contributed mild fruit-forward esters with relatively clean finish; foundational exposure to local Indonesian origins. | U2: Bali family trip | V2: Merged (Gemini + ChatGPT) | W2: =IF(OR(ISNUMBER(SEARCH("gesha",G2)),ISNUMBER(SEARCH("geisha",G2))),"⭐ GESHA","") | X2: Jl. Sri Wedari No.5, Ubud, Gianyar, Bali 80571, Indonesia
A3: 46026 | B3: Ubud, Bali | C3: Seniman Coffee Studio | D3: Sulawesi Toraja | E3: Unknown | F3: Sulawesi, Indonesia | G3: Unknown | H3: Wet-Hulled | I3: Medium | J3: Pour-over | K3: Unknown | L3: Unknown | M3: Unknown | N3: Unknown | O3: Unknown | P3: Unknown | Q3: Unknown | R3: Cocoa; earthy structures | S3: Heavy body with rich cocoa and earthy notes; low acidity; dense mouthfeel. | T3: Classic Giling Basah wet-hulled process emphasized earthy compounds and syrupy mouthfeel; structural density confirmed. | U3: Bali family trip | V3: Merged (Gemini + ChatGPT) | W3: =IF(OR(ISNUMBER(SEARCH("gesha",G3)),ISNUMBER(SEARCH("geisha",G3))),"⭐ GESHA","") | X3: Jl. Sri Wedari No.5, Ubud, Gianyar, Bali 80571, Indonesia
A4: 46026 | B4: Ubud, Bali | C4: Seniman Coffee Studio | D4: House Blend | E4: Unknown | F4: Unknown | G4: Unknown | H4: Unknown | I4: Espresso Roast | J4: Piccolo | K4: Unknown | L4: Unknown | M4: Unknown | N4: Unknown | O4: Unknown | P4: Unknown | Q4: Unknown | R4: Balanced | S4: Great milk integration; standard espresso + milk calibration. | T4: Baseline milk pairing; milk fats softened acidity and amplified sweetness and body. | U4: Bali family trip | V4: Merged (Gemini + ChatGPT) | W4: =IF(OR(ISNUMBER(SEARCH("gesha",G4)),ISNUMBER(SEARCH("geisha",G4))),"⭐ GESHA","") | X4: Jl. Sri Wedari No.5, Ubud, Gianyar, Bali 80571, Indonesia
A5: 46063 | B5: Singapore | C5: Kyuukei Coffee | D5: Kenya Kiamugumo AA | E5: New Ngariama Farmer's Cooperative Society | F5: Kiamugumo, Murang'a County, Kenya | G5: SL28 / SL34 | H5: Washed | I5: Unknown | J5: Pour-over (Flat-Bottom) | K5: 15 | L5: 240 | M5: 1:16 | N5: 93 | O5: Unknown | P5: 120mm Hybrid Burr | Q5: 8 | R5: Blackcurrant, Lemon, Citrus Zest, Mineral Finish | S5: Extremely clean and structured — classic Kenyan profile. Bright blackcurrant acidity layered with lemon and light white grape sweetness. Clarity was the standout: no fermentation noise, no muddiness — precise, well-executed extraction. Compelling demonstration of how a well-processed washed coffee performs when roasted and brewed correctly. Phosphoric acid signature fully confirmed across all phases. | T5: 120mm hybrid burr grinder delivered uniform particle distribution; flat-bottom pour-over geometry ensured even extraction across the full puck. 93°C water temp and 1:16 lean ratio preserved SL28/SL34 phosphoric acid clarity without over-extracting into bitterness. Brew time 2:45 consistent with controlled drawdown on flat-bottom geometry. Kenyan phosphoric acid and anthocyanin-driven blackcurrant notes are varietal signatures of Scott Laboratories SL28/SL34 genetics. | U5: Solo visit — early archive period, first Kyūkei filter audit | V5: Direct observation + infographic + Google review (10 Feb 2026) | W5: =IF(OR(ISNUMBER(SEARCH("gesha",G5)),ISNUMBER(SEARCH("geisha",G5))),"⭐ GESHA","") | X5: 121 Bukit Merah Lane 1, #01-06, Singapore 150121
A6: 46082 | B6: Mumbai | C6: Subko Coffee Roasters | D6: Project Pearl Ratnagiri | E6: Ratnagiri Estate | F6: India | G6: Unknown | H6: Anaerobic Natural | I6: Light (Agtron 89) | J6: Filter | K6: Unknown | L6: Unknown | M6: Unknown | N6: Unknown | O6: Unknown | P6: Unknown | Q6: Unknown | R6: Unknown | S6: Clean and balanced; interesting but restrained anaerobic expression. | T6: Very light roast (Agtron 89) suppressed ester development despite anaerobic process; muted expected fermented intensity. | U6: Mumbai café exploration | V6: Merged (Gemini + ChatGPT) | W6: =IF(OR(ISNUMBER(SEARCH("gesha",G6)),ISNUMBER(SEARCH("geisha",G6))),"⭐ GESHA","") | X6: Mary Lodge, 21A Chapel Rd, Ranwar, Bandra West, Mumbai 400050, India
A7: 46089 | B7: Mumbai | C7: Grey Soul Coffee Roasters | D7: Raspberry in Loop - Zoya Estate | E7: Zoya Estate | F7: India | G7: Unknown | H7: Multi-stage Anaerobic | I7: Medium | J7: Filter | K7: Unknown | L7: Unknown | M7: Unknown | N7: Unknown | O7: Unknown | P7: Unknown | Q7: Unknown | R7: Chocolate | S7: Heavy body; over-smoothed expression muted brightness and terroir. | T7: Higher development in medium roast reduced aggressive fruit acidity; heavy multi-stage fermentation suppressed terroir expression. | U7: Mumbai café exploration | V7: Merged (Gemini + ChatGPT) | W7: =IF(OR(ISNUMBER(SEARCH("gesha",G7)),ISNUMBER(SEARCH("geisha",G7))),"⭐ GESHA","") | X7: Dr Ambedkar Rd, Pali Village, Bandra West, Mumbai 400050, India
A8: 46099 | B8: Singapore | C8: Narrative Coffee Stand | D8: Finca La Siberia | E8: Unknown | F8: El Salvador | G8: Pacamara | H8: Natural | I8: Light | J8: Pour-over | K8: Unknown | L8: Unknown | M8: Unknown | N8: Unknown | O8: Unknown | P8: Unknown | Q8: Unknown | R8: Unknown | S8: Stewed apples; Apricot; Pu'er tea — Aanya's first specialty filter experience. | T8: Natural Pacamara generated beginner-friendly fruit esters and approachable sweetness; large Pacamara bean size aided even extraction. | U8: Father-daughter coffee exploration | V8: ChatGPT only | W8: =IF(OR(ISNUMBER(SEARCH("gesha",G8)),ISNUMBER(SEARCH("geisha",G8))),"⭐ GESHA","") | X8: Blk 231 Bain St, #01-05, Singapore 180231
A9: 46099 | B9: Singapore | C9: Narrative Coffee Stand | D9: El Puente | E9: Unknown | F9: Honduras | G9: Catuai | H9: Washed | I9: Medium-Light | J9: Espresso | K9: Unknown | L9: Unknown | M9: Unknown | N9: Unknown | O9: Unknown | P9: Unknown | Q9: Unknown | R9: Unknown | S9: Black cherry; Apricot; Pecan — ordered for espresso contrast. | T9: Washed Central American espresso balanced nutty sweetness and fruit acidity; Catuai's consistent cell structure aided uniform extraction. | U9: Father-daughter coffee exploration | V9: ChatGPT only | W9: =IF(OR(ISNUMBER(SEARCH("gesha",G9)),ISNUMBER(SEARCH("geisha",G9))),"⭐ GESHA","") | X9: Blk 231 Bain St, #01-05, Singapore 180231
A10: 46099 | B10: Singapore | C10: ASK Coffee Roastery | D10: Honduras Masaguara (S13) | E10: Unknown | F10: Honduras | G10: Catuai / Caturra | H10: Washed Co-Ferment | I10: Light | J10: Pour-over | K10: Unknown | L10: Unknown | M10: Unknown | N10: Unknown | O10: Unknown | P10: Unknown | Q10: 15 | R10: Lychee; Brandy; Honeydew; Milk Chocolate | S10: Premium but memorable; highly complex tropical profile. | T10: Co-fermentation amplified tropical ester complexity; co-ferment substrates introduced lychee lactones and brandy-like ethyl esters. | U10: Father-daughter coffee exploration | V10: ChatGPT only | W10: =IF(OR(ISNUMBER(SEARCH("gesha",G10)),ISNUMBER(SEARCH("geisha",G10))),"⭐ GESHA","") | X10: 32 Seah St, Singapore 188388
A11: 46099 | B11: Singapore | C11: ASK Coffee Roastery | D11: House Blend | E11: Unknown | F11: Unknown | G11: Unknown | H11: Unknown | I11: Unknown | J11: Magic (Ristretto Milk) | K11: Unknown | L11: Unknown | M11: Unknown | N11: Unknown | O11: Unknown | P11: Unknown | Q11: Unknown | R11: Unknown | S11: Contrast milk calibration; excellent concentrated cocoa expression. | T11: Ristretto milk extraction increased sweetness density and concentrated cocoa compounds through reduced water content. | U11: Father-daughter coffee exploration | V11: ChatGPT only | W11: =IF(OR(ISNUMBER(SEARCH("gesha",G11)),ISNUMBER(SEARCH("geisha",G11))),"⭐ GESHA","") | X11: 32 Seah St, Singapore 188388
A12: 46103 | B12: Singapore | C12: Apartment (Selegie Rd) | D12: Colombia Don Gallego - Wush Wush | E12: Don Gallego | F12: Colombia | G12: Wush Wush | H12: Washed | I12: Light | J12: Pour-over (Flat-Bottom) | K12: Unknown | L12: Unknown | M12: 1:17 | N12: Unknown | O12: Unknown | P12: Unknown | Q12: Unknown | R12: Tea-like | S12: Incredible tea-like clarity; transparent floral expression. | T12: Lean 1:17 ratio maximized aromatic separation; Wush Wush's Ethiopian-lineage genetics produced delicate phenolic and floral complexity. | U12: Solo specialty calibration | V12: Merged (Gemini + ChatGPT) | W12: =IF(OR(ISNUMBER(SEARCH("gesha",G12)),ISNUMBER(SEARCH("geisha",G12))),"⭐ GESHA","") | X12: 139 Selegie Rd, #01-01, Singapore 188309
A13: 46105 | B13: Singapore | C13: Kyuukei Coffee | D13: Kenya Ndiaini AA | E13: Unknown | F13: Kenya | G13: SL28 / SL34 / Ruiru 11 | H13: Washed | I13: Unknown | J13: Pour-over | K13: Unknown | L13: Unknown | M13: Unknown | N13: Unknown | O13: Unknown | P13: Unknown | Q13: 9 | R13: Redcurrant; Elderflower; Lemon; Apricot | S13: Acidic and interesting; well balanced; high clarity. | T13: Ruiru 11 introduced structural body alongside classic SL28/SL34 brightness; further Kenyan terroir depth confirmed. | U13: Solo specialty calibration | V13: Merged (Gemini + ChatGPT) | W13: =IF(OR(ISNUMBER(SEARCH("gesha",G13)),ISNUMBER(SEARCH("geisha",G13))),"⭐ GESHA","") | X13: 121 Bukit Merah Lane 1, #01-06, Singapore 150121
A14: 46106 | B14: Singapore | C14: Agora Coffee | D14: Nicaragua Matagalpa - Finca La Virgen | E14: Finca La Virgen | F14: Nicaragua | G14: Unknown | H14: Fully Washed | I14: Espresso Roast | J14: Flat White | K14: Unknown | L14: Unknown | M14: Unknown | N14: Unknown | O14: Unknown | P14: Unknown | Q14: Unknown | R14: Caramel; Chocolate; Red Apple | S14: Solid milk beverage; clean apple acidity preserved in milk integration. | T14: Fully washed Central American profile preserved clean malic acidity in milk; espresso roast development amplified caramel Maillard notes. | U14: Solo specialty calibration | V14: Merged (Gemini + ChatGPT) | W14: =IF(OR(ISNUMBER(SEARCH("gesha",G14)),ISNUMBER(SEARCH("geisha",G14))),"⭐ GESHA","") | X14: 31 Club St, #01-02, Singapore 069468
A15: 46108 | B15: Singapore | C15: Agora Coffee | D15: Ethiopia Yirgacheffe Beloya | E15: Beloya | F15: Yirgacheffe, Ethiopia | G15: Heirloom | H15: Natural | I15: Filter Roast | J15: V60 | K15: 15 | L15: 220 | M15: 1:14.6 | N15: Unknown | O15: Unknown | P15: Mahlkönig EK43 | Q15: Unknown | R15: Blackcurrant; Strawberry; White Floral | S15: Bright, floral, and distinct strawberry; classic natural Ethiopian profile. | T15: EK43 98mm flat burrs reduced fines and preserved clarity despite natural processing; 1:14.6 ratio retained fruity body. | U15: Solo specialty calibration | V15: Merged (Gemini + ChatGPT) | W15: =IF(OR(ISNUMBER(SEARCH("gesha",G15)),ISNUMBER(SEARCH("geisha",G15))),"⭐ GESHA","") | X15: 31 Club St, #01-02, Singapore 069468
A16: 46109 | B16: Singapore | C16: Tiong Hoe Specialty Coffee | D16: Brazil Mogiana | E16: Unknown | F16: Mogiana, Brazil | G16: Unknown | H16: Natural | I16: Medium | J16: Pour-over | K16: 15 | L16: 225 | M16: 1:15 | N16: Unknown | O16: Unknown | P16: Unknown | Q16: 8 | R16: Red Dates; Chocolates; Honey | S16: Chocolate-heavy and satisfying; classic dense Brazilian profile. | T16: Tighter 1:15 ratio increased body and amplified Maillard-derived caramel sweetness; medium roast caramelized sugars without losing origin character. | U16: Solo specialty calibration | V16: Merged (Gemini + ChatGPT) | W16: =IF(OR(ISNUMBER(SEARCH("gesha",G16)),ISNUMBER(SEARCH("geisha",G16))),"⭐ GESHA","") | X16: 1 Harbourfront Walk, VivoCity Fairprice Xtra, #B2-23, Singapore 098585
A17: 46109 | B17: Singapore | C17: Tiong Hoe Specialty Coffee | D17: Smoky Quartz Blend | E17: Unknown | F17: Brazil + India | G17: Unknown | H17: Unknown | I17: Unknown | J17: Piccolo Latte | K17: Unknown | L17: Unknown | M17: Unknown | N17: Unknown | O17: Unknown | P17: Unknown | Q17: 5.1 | R17: Dark Chocolates; Hazelnut; Smoky | S17: Strong milk side calibration; excellent concentrated cocoa expression. | T17: Low milk volume in piccolo format concentrated cocoa and hazelnut compounds; cross-origin blend leveraged Indian robusta structural density. | U17: Solo specialty calibration | V17: ChatGPT only | W17: =IF(OR(ISNUMBER(SEARCH("gesha",G17)),ISNUMBER(SEARCH("geisha",G17))),"⭐ GESHA","") | X17: 1 Harbourfront Walk, VivoCity Fairprice Xtra, #B2-23, Singapore 098585
A18: 46110 | B18: Singapore | C18: Asylum Coffeehouse | D18: Peru Cajamarca Gesha (Iced) | E18: Wilder Garcia | F18: Cajamarca, Peru | G18: Gesha | H18: Washed | I18: Medium | J18: Iced Pour-over | K18: 15 | L18: 240 | M18: 1:16 | N18: 92.5 | O18: Unknown | P18: Option-O Lagom P64 | Q18: 11 | R18: Jasmine; Caramel; Lime; Cacao Nibs | S18: Super floral and elegant; flash-chilled expression of Gesha purity. | T18: Flash-chilled extraction via Option-O Lagom P64 preserved volatile floral monoterpenes (linalool); cold dilution stabilized aromatic compounds. | U18: Solo specialty calibration | V18: ChatGPT only | W18: =IF(OR(ISNUMBER(SEARCH("gesha",G18)),ISNUMBER(SEARCH("geisha",G18))),"⭐ GESHA","") -> ⭐ GESHA | X18: 311 Jln Besar, Singapore 208970
A19: 46113 | B19: Singapore | C19: Maxi Coffee Bar | D19: La Laja | E19: James Fernandez | F19: Cauca, Colombia | G19: Sudan Rume | H19: Washed | I19: Light | J19: Pour-over (Flat-Bottom) | K19: 15 | L19: 230 | M19: 1:15.3 | N19: 90-92 | O19: Unknown | P19: FM Grinder 120mm Flat Burr / Timemore Sculptor 078 | Q19: 9 | R19: Raspberry; Nectarine; Floral | S19: Nectarine and raspberry extremely clear; barista sophistication superb; technical milestone. | T19: 120mm flat burr geometry maximized uniform particle distribution; flat-bottom brewer enhanced sweetness while preserving Sudan Rume's rare genetic clarity. | U19: CBD lunch calibration | V19: Merged (Gemini + ChatGPT) | W19: =IF(OR(ISNUMBER(SEARCH("gesha",G19)),ISNUMBER(SEARCH("geisha",G19))),"⭐ GESHA","") | X19: 64 Club St, Back Entrance, Singapore 069438
A20: 46113 | B20: Singapore | C20: Lume Café | D20: Corpachi Panama Geisha | E20: Corpachi | F20: Boquerón, Chiriquí, Panama | G20: Geisha | H20: Red Honey | I20: Filter Roast | J20: V60 | K20: Unknown | L20: Unknown | M20: 1:15 | N20: 90 + 70 | O20: Unknown | P20: Mahlkönig EK43 | Q20: 12 | R20: Mandarin Candy; Jasmine; Apricot | S20: Clearly perceived apricot and structured sweetness. | T20: Dual-temperature extraction balanced aromatics and body in honey-process Geisha; red honey partial mucilage retention amplified structured sweetness. | U20: Rainy CBD lunch calibration | V20: ChatGPT only | W20: =IF(OR(ISNUMBER(SEARCH("gesha",G20)),ISNUMBER(SEARCH("geisha",G20))),"⭐ GESHA","") -> ⭐ GESHA | X20: 108 Robinson Rd, #01-01, Singapore 068900
A21: 46117 | B21: Singapore | C21: Asylum Coffeehouse | D21: Castillo Watermelon (Jairo Arcila) | E21: Jairo Arcila | F21: Armenia, Quindío, Colombia | G21: Castillo | H21: Washed Co-Ferment (Watermelon Anaerobic) | I21: Unknown | J21: Pour-over (V60) | K21: 15 | L21: 225 | M21: 1:15 | N21: 90 + 70 | O21: Unknown | P21: Mahlkönig EK43 | Q21: 12.5 | R21: Watermelon; Mint; Lime; Chocolate | S21: Distinct fruit-forward expression; sweetness layered rather than sharp; experimental but controlled. | T21: Watermelon co-fermentation enhanced volatile ester complexity; dual-temperature extraction preserved layered aromatic architecture. | U21: Father-daughter coffee session | V21: Merged (Gemini + ChatGPT) | W21: =IF(OR(ISNUMBER(SEARCH("gesha",G21)),ISNUMBER(SEARCH("geisha",G21))),"⭐ GESHA","") | X21: 311 Jln Besar, Singapore 208970
A22: 46117 | B22: Singapore | C22: Asylum Coffeehouse | D22: Peru Gesha (Wilder Garcia) | E22: Wilder Garcia | F22: Jaén, Peru | G22: Gesha | H22: Washed | I22: Filter Roast | J22: Pour-over (V60) | K22: 15 | L22: 225 | M22: 1:15 | N22: 90 + 70 | O22: Unknown | P22: Mahlkönig EK43 | Q22: 12.5 | R22: Jasmine; Caramel; Lime; Cacao Nibs | S22: Clean, structured, high-clarity cup; apricot-like sweetness and excellent structure. | T22: Dual-temperature extraction engineered aromatic separation and body control; Gesha genetics delivered intrinsic phenolic complexity with minimal processing interference. | U22: Father-daughter coffee session | V22: Merged (Gemini + ChatGPT) | W22: =IF(OR(ISNUMBER(SEARCH("gesha",G22)),ISNUMBER(SEARCH("geisha",G22))),"⭐ GESHA","") -> ⭐ GESHA | X22: 311 Jln Besar, Singapore 208970
A23: 46120 | B23: Singapore | C23: Maxi Coffee Bar | D23: La Villa #1 | E23: Eduard Gaviria | F23: Huila, Colombia | G23: Papayo | H23: Natural | I23: Unknown | J23: Pour-over (Flat-Bottom) | K23: 15 | L23: 225 | M23: 1:15 | N23: Unknown | O23: Unknown | P23: Timemore Sculptor 078 | Q23: 9 | R23: Stewed Forest Berries; Grape; Black Forest Cake | S23: Dense fruit profile with rounded sweetness. | T23: Flat-bottom geometry and tight 1:15 ratio emphasized body; Papayo varietal's high sugar content amplified by natural processing into rich fruit-cake profile. | U23: Lunch catch-up with Yichen | V23: ChatGPT only | W23: =IF(OR(ISNUMBER(SEARCH("gesha",G23)),ISNUMBER(SEARCH("geisha",G23))),"⭐ GESHA","") | X23: 64 Club St, Back Entrance, Singapore 069438
A24: 46130 | B24: Johor Bahru | C24: Clod Coffee Bar & Roasters | D24: Hacienda La Florida | E24: Unknown | F24: Unknown | G24: Typica Mejorado | H24: Anaerobic Washed | I24: Unknown | J24: Origami (Conical) | K24: 18 | L24: 277 | M24: 1:15.4 | N24: Unknown | O24: 42g / 30s (1:2.3) | P24: Mahlkönig EK Omnia | Q24: 11.08 | R24: Lemon verbena; Red plum; Citronella; Hibiscus | S24: Excellent. Lime when hot, distinct plum as it cooled. | T24: EK Omnia precision grind and Origami conical drove extreme clarity; thermal phase shift perfectly isolated citric-to-malic acid transition (lime → plum). | U24: Unknown | V24: Gemini only | W24: =IF(OR(ISNUMBER(SEARCH("gesha",G24)),ISNUMBER(SEARCH("geisha",G24))),"⭐ GESHA","") | X24: 123 Jalan Beringin, Taman Melodies, 80250 Johor Bahru, Malaysia
A25: 46136 | B25: Singapore | C25: Agora Coffee | D25: Brazil Santuário Sul | E25: Unknown | F25: Carmo de Minas, Brazil | G25: Unknown | H25: Natural Fermentation | I25: Light-Medium | J25: V60 | K25: 16 | L25: 224 | M25: 1:14 | N25: 95 | O25: Unknown | P25: Mahlkönig EK43 | Q25: Unknown | R25: Blackcurrant; Black Cherry; Dark Chocolate | S25: Full body; prominent blackcurrant; clear chocolaty finish. | T25: Tight 1:14 ratio engineered maximum body; EK43 98mm burrs maintained clarity to keep fermented natural fruit clean and non-bitter. | U25: Midday specialty calibration | V25: Merged (Gemini + ChatGPT) | W25: =IF(OR(ISNUMBER(SEARCH("gesha",G25)),ISNUMBER(SEARCH("geisha",G25))),"⭐ GESHA","") | X25: 31 Club St, #01-02, Singapore 069468
A26: 46148 | B26: Singapore | C26: Nylon Coffee Roasters | D26: Brazil FAF Organic | E26: Unknown | F26: Brazil | G26: Arara | H26: Natural | I26: Filter Roast | J26: xBloom (Flat-Bottom) | K26: Unknown | L26: Unknown | M26: 1:17 | N26: Unknown | O26: Unknown | P26: Mahlkönig EK Omnia | Q26: 7.5 | R26: Red Apple; Cherry; Raisin; Milk Chocolate | S26: Solid body with crisp green apple (malic) front, resolving into smooth milk chocolate finish. | T26: High-quality Arara natural processing yielded excellent structural body while maintaining crisp malic acidity; xBloom flat-bottom avoided heavy fermentation mud. | U26: Unknown | V26: Gemini only | W26: =IF(OR(ISNUMBER(SEARCH("gesha",G26)),ISNUMBER(SEARCH("geisha",G26))),"⭐ GESHA","") | X26: 4 Everton Park, #01-40, Singapore 080004
A27: 46148 | B27: Singapore | C27: Nylon Coffee Roasters | D27: Brazil Serra dos Ciganos | E27: Unknown | F27: Brazil | G27: Catucai 24/137 | H27: Natural | I27: Espresso Roast | J27: Flat White | K27: Unknown | L27: Unknown | M27: Unknown | N27: Unknown | O27: Unknown | P27: Unknown | Q27: Unknown | R27: Sultana; Dried Apricot; Praline; Roasted Hazelnut | S27: Good cup with pleasant lingering sweet aftertaste. | T27: Milk fats bound perfectly with natural processed espresso; Catucai 24/137 high-density bean structure created long, comforting finish. | U27: Unknown | V27: Gemini only | W27: =IF(OR(ISNUMBER(SEARCH("gesha",G27)),ISNUMBER(SEARCH("geisha",G27))),"⭐ GESHA","") | X27: 4 Everton Park, #01-40, Singapore 080004
A28: 46149 | B28: Singapore | C28: Nylon Coffee Roasters | D28: Ethiopia Banko Gotiti | E28: Unknown | F28: Ethiopia | G28: Heirloom | H28: Washed | I28: Filter Roast | J28: xBloom (Flat-Bottom) | K28: Unknown | L28: Unknown | M28: 1:17 | N28: Unknown | O28: Unknown | P28: Mahlkönig EK Omnia | Q28: 8.5 | R28: Lemonade; Raspberry; Peach; Bergamot | S28: Lemon front, heavy melon mid-cup, fading into clean white tea finish. | T28: 1:17 lean ratio isolated volatile citric acids; xBloom flat-bottom geometry stabilized mid-cup sugars before clean tannin-forward white tea finish. | U28: Unknown | V28: Gemini only | W28: =IF(OR(ISNUMBER(SEARCH("gesha",G28)),ISNUMBER(SEARCH("geisha",G28))),"⭐ GESHA","") | X28: 4 Everton Park, #01-40, Singapore 080004
A29: 46149 | B29: Singapore | C29: Nylon Coffee Roasters | D29: Nicaragua Buena Vista | E29: Unknown | F29: Nicaragua | G29: Parainema | H29: Natural Anaerobic | I29: Espresso Roast | J29: Single Espresso | K29: Unknown | L29: Unknown | M29: ~1:2 | N29: Unknown | O29: Unknown | P29: Unknown | Q29: Unknown | R29: Chiku; Stewed Cherry; Dried Apricot; Brazil Nut | S29: Thick, syrupy body. Highly fermented, savory/not sweet, very long lingering finish. | T29: Anaerobic fermentation metabolized sugars into complex savory esters; 9-bar pressure emulsification drove heavy oil-based viscosity and extended aftertaste. | U29: Unknown | V29: Gemini only | W29: =IF(OR(ISNUMBER(SEARCH("gesha",G29)),ISNUMBER(SEARCH("geisha",G29))),"⭐ GESHA","") | X29: 4 Everton Park, #01-40, Singapore 080004
A30: 46150 | B30: Singapore | C30: Alchemist (Ocean Financial Centre) | D30: El Morito | E30: Unknown | F30: Colombia | G30: Marshell | H30: Washed | I30: Filter Roast | J30: V60 Pour-over (Conical) | K30: 15 | L30: 240 | M30: 1:16 | N30: Unknown | O30: Unknown | P30: Mahlkönig EK43S (98mm Flat Burr) | Q30: Unknown | R30: Yellow Plum; Orange; Cane Sugar | S30: Simultaneous citric-malic acid overlap with integrated cane sugar — smooth and refreshing with excellent mid-palate juiciness. Confirmed: I love this bean. | T30: EK43S 98mm flat burrs + V60 conical at 1:16 delivered perfect dual-acid integration (citric orange + malic plum) without single-note dominance. Sucrose extraction at 1:16 bridged acid structure into clean cane sugar finish. Marshell is an extremely rare Colombian varietal — natural mutation prized for simultaneous citric-malic acid duality. | U30: Solo visit — Alchemist Raffles Place | V30: Master CSV (hari_coffee_audit_master_2026) | W30: =IF(OR(ISNUMBER(SEARCH("gesha",G30)),ISNUMBER(SEARCH("geisha",G30))),"⭐ GESHA","") | X30: 10 Collyer Quay, #01-K1, Singapore 049315
A31: 46154 | B31: Singapore | C31: Kurasu | D31: Indonesia Frinsa Estate | E31: Frinsa Estate | F31: West Java, Indonesia | G31: Local Varietals | H31: Extended Fermentation Honey | I31: Light | J31: Pour-over (Hario Alpha — Flat-Bottom) | K31: 15 | L31: 225 | M31: 1:16 | N31: 80 → 95 → 80 | O31: Unknown | P31: Mahlkönig EK43S (98mm Flat Burr) | Q31: 9.5 | R31: Floral aroma; Stewed Strawberries; Grapefruit; Brown Sugar; Black Tea | S31: Floral taste with a sweet coating on the tongue that gradually sticks and fades off cleanly — sugar and tea aftertaste. Well-executed Indonesian honey with unusual clarity for the origin. | T31: Multi-temperature pour (80→95→80°C) with Hario Alpha flat-bottom perfectly managed heavy honey-process mucilage sugars — clear floral extraction at lower temps, dissolving jammy mucilage at peak heat, finishing cleanly. Extended fermentation honey adds structured sweetness without heavy ferment-funk. First Indonesian-mainland entry in archive (distinct from Bali entries). | U31: Solo visit — Kurasu Singapore | V31: Master CSV (hari_coffee_audit_master_2026) | W31: =IF(OR(ISNUMBER(SEARCH("gesha",G31)),ISNUMBER(SEARCH("geisha",G31))),"⭐ GESHA","") | X31: 261 Waterloo St, #01-24, Singapore 180261
A32: 46155 | B32: Singapore | C32: The Community Coffee (Hamilton) | D32: Jose Mancia Honduras | E32: Jose Mancia | F32: Honduras | G32: Typica | H32: Natural | I32: Filter Roast | J32: Pour-over (Hario Switch — Immersion/Percolation) | K32: 15 | L32: 255 | M32: 1:17 | N32: Unknown | O32: Unknown | P32: Mahlkönig EK43 (98mm Flat Burr) | Q32: 9 | R32: Kiwi; Oolong Tea; Chocolate Truffle | S32: Pretty good. Kiwi and oolong tea style — full bodied. Short finish with slight hints of chocolate. Clean and approachable natural without heavy fermentation noise. | T32: Typica inherent lipid clarity + raised-bed drying produced clean tea-structure body. EK43 98mm flat burrs + Hario Switch immersion phase stabilised full mouthfeel at lean 1:17. Short finish consistent with 15-days-off-roast volatile taper — kiwi and oolong top notes fade rapidly. Honduras Typica at altitude expresses tea-like clarity atypical of natural-process expectations. | U32: Solo visit — The Community Coffee Hamilton | V32: Master CSV (hari_coffee_audit_master_2026) | W32: =IF(OR(ISNUMBER(SEARCH("gesha",G32)),ISNUMBER(SEARCH("geisha",G32))),"⭐ GESHA","") | X32: 38 Hamilton Rd, Singapore 209208
A33: 46157 | B33: Singapore | C33: Alchemist (Ocean Financial Centre) | D33: Ijen Laurina | E33: Ijen Plateau | F33: East Java, Indonesia | G33: Hybrid Laurina | H33: Anaerobic Natural | I33: Light | J33: V60 Pour-over (Conical) | K33: 15 | L33: 240 | M33: 1:16 | N33: 90 | O33: Unknown | P33: Mahlkönig EK43S (98mm Flat Burr) | Q33: 8.5 | R33: Hibiscus; Red Apple; Hawthorn | S33: Felt hibiscus hot. Mid temp showed apple paste. Cooled to a honeyed character. Full bodied. Textbook style flavours — definitely a good one. Clean progressive thermal arc. | T33: 90°C brew temp suppressed lactic ester over-extraction while preserving volatile anthocyanin hibiscus esters. Laurina low-caffeine mutation allows intrinsic sucrose to express as clean honeyed finish without alkaloid bitterness. Anaerobic Natural transformed malic acid into jammy apple paste mid-phase. First Hybrid Laurina varietal in archive — new genetic category unlocked. Hibiscus = anthocyanin; Apple paste = malic lactone; Honey = sucrose at sub-50°C. | U33: Solo visit — Alchemist Ocean Financial Centre | V33: Master CSV (hari_coffee_audit_master_2026) | W33: =IF(OR(ISNUMBER(SEARCH("gesha",G33)),ISNUMBER(SEARCH("geisha",G33))),"⭐ GESHA","") | X33: 10 Collyer Quay, #01-K1, Singapore 049315
A34: 46158 | B34: Singapore | C34: Fluid Collective | D34: El Obraje | E34: El Obraje | F34: Huila, Colombia | G34: Gesha | H34: Washed | I34: Light | J34: Flatbed Dripper (Flat-Bottom) | K34: 15 | L34: 230 | M34: 1:15.3 | N34: 92 | O34: Unknown | P34: Option-O Lagom P64 (64mm Flat Burr) | Q34: 14 | R34: Mango; Orange Blossom; Nectarine; Honey | S34: Damn the taste so nice — the orange nectarine finishing with that honey is terrific. Love this one. So far my favourite. Honey sweetness lingers and taste changes as temperature cools. Best Gesha washed in archive at time of logging. | T34: Lagom P64 64mm flat burrs deliver near-unimodal particle distribution — same hardware platform as Asylum Coffeehouse entries, enabling pure terroir delta comparison between Colombia Gesha (El Obraje, Huila) and Peru Gesha (Wilder Garcia, Jaén). 92°C at 1:15.3 maximised linalool floral ester retention while stabilising malic acid mango-nectarine backbone. Flat-bottom eliminated bypass and ensured even bed saturation — critical for preserving fragile Gesha aromatics. Honey finish = sucrose preserved at washed-process mucilage removal stage. | U34: Solo visit — FLUID Singapore | V34: Master CSV (hari_coffee_audit_master_2026) | W34: =IF(OR(ISNUMBER(SEARCH("gesha",G34)),ISNUMBER(SEARCH("geisha",G34))),"⭐ GESHA","") -> ⭐ GESHA | X34: 24 Opal Cres, Singapore 328418
A35: 46161 | B35: Singapore | C35: Pocket by Flip (Flip Coffee Roasters) | D35: Ecuador La Papaya | E35: La Papaya Farm | F35: Loja, Ecuador | G35: Geisha | H35: Washed | I35: Light | J35: Filter Hot — Flat-Bottom (Hario Alpha) | K35: 15 | L35: 225 | M35: 1:15 | N35: 92 → 75 → 92 | O35: Unknown | P35: Mahlkönig CORE (54mm Flat Burr) | Q35: 18 | R35: Fresh Apricot; Rooibos; Lemon Thyme; Toffee Apple | S35: Opening: tartaric apricot + rooibos aspalathin. Mid: thymol terpene coat — lipid-binding, persistent to midway. Cooling: malic apple shift + caramelised sucrose. Clean transparent fade. No linalool/jasmine — terpene-forward character distinct from Peru Geisha entries. Highest-altitude Geisha in archive at 2,100 MASL. | T35: Triple-temp cascade (92→75→92°C) on CORE 54mm flat burr + Hario Alpha flat-bottom preserved heat-sensitive thymol terpenes from 2,100 MASL Loja terroir. 75°C mid-pour is the critical terpene-stabilisation variable — thymol is lipid-binding and volatile above 80°C, so mid-temp pour is the architecture delivering the persistent midpalate coat. Ecuador Geisha = terpene-forward (Thymol/Aspalathin) clearly differentiated from linalool-forward Peru Geisha (Jasmine/Citric). First Ecuador-origin entry in archive. | U35: Solo visit — Pocket by Flip, 30 Stevens Road | V35: Master CSV (hari_coffee_audit_master_2026) | W35: =IF(OR(ISNUMBER(SEARCH("gesha",G35)),ISNUMBER(SEARCH("geisha",G35))),"⭐ GESHA","") -> ⭐ GESHA | X35: 30 Stevens Rd, #01-08, Singapore 257840
A36: 46167 | B36: Singapore | C36: 20 Grams Coffee Roastery | D36: Rwanda Nyabihu — Red Bourbon | E36: Josue Dusengiyumva, Shyira Washing Station | F36: Nyabihu District, Rwanda | G36: Red Bourbon | H36: Washed | I36: Light (Nordic Roast) | J36: Pourover | K36: 17 | L36: 270 | M36: 1:16 | N36: Unknown | O36: Unknown | P36: Ditting 804 (Flat Burr) | Q36: 10 | R36: Hibiscus; Raspberry; Tropical Fruit | S36: Palate confirmed: peach, stone fruit, malic clarity. "Soft, peach-forward, malic clarity — light and approachable. First Rwanda origin entry. Terroir-pure expression of Nyabihu volcanic terroir." 4/5 stars. | T36: 1:16 lean ratio (vs 1:15 standard) suppresses body/TDS to amplify volatile aromatics — deliberate strategy to showcase Rwandan terroir delicacy. Malic-acid-dominant, smooth rounded onset consistent with washed Red Bourbon genetics. | U36: Twenty Grams Roastery, MacPherson — first Rwanda origin entry | V36: Field entry (infographic-derived) | W36: =IF(OR(ISNUMBER(SEARCH("gesha",G36)),ISNUMBER(SEARCH("geisha",G36))),"⭐ GESHA","") | X36: 14 Arumugam Rd, #01-05 LTC Building C, Singapore 409959
A37: 46167 | B37: Singapore | C37: 20 Grams Coffee Roastery | D37: Kenya Nyeri Hill — SL28 | E37: Nyeri Hill Factory | F37: Kiambu District, Kenya | G37: SL28 | H37: Washed | I37: Unknown | J37: Cortado (Espresso-based) | K37: Unknown | L37: Unknown | M37: ~1:1 (espresso/milk) | N37: Unknown | O37: N/A — espresso format | P37: Ditting Lab Sweet 403 | Q37: 9 | R37: Apple; Grape; Blackcurrant | S37: Palate confirmed: clean, nice, excellent lingering finish. "Clean, structured, with an exceptional lingering phosphoric finish — textbook SL28 Kenyan expression perfectly delivered in cortado format." 4/5 stars. | T37: 9-bar extraction emulsifies coffee lipids into the crema matrix; ~1:1 milk ratio softens entry while SL28's signature phosphoric acid structure dominates the finish — classic Kenyan cortado profile. | U37: Twenty Grams Roastery, MacPherson — same visit as Rwanda pourover | V37: Field entry (infographic-derived) | W37: =IF(OR(ISNUMBER(SEARCH("gesha",G37)),ISNUMBER(SEARCH("geisha",G37))),"⭐ GESHA","") | X37: 14 Arumugam Rd, #01-05 LTC Building C, Singapore 409959
A38: 46168 | B38: Singapore | C38: Zerah Roasters | D38: El Diviso — Caturra Chiroso (Ester Bomb) | E38: El Diviso Farm | F38: Huila, Colombia | G38: Caturra Chiroso | H38: Yeast Anaerobic Natural | I38: Filter Roast | J38: Flat-Bottom Dripper | K38: 15 | L38: 240 | M38: 1:16 | N38: 92 | O38: 38g / Unknown seconds | P38: DF64 Gen 2 (64mm Flat Burr — aftermarket upgrade) | Q38: 12 | R38: Passionfruit; Plum Wine; Mango | S38: Goddamn the smell is intense. Flavor burst — acid or strong flavor, super punchy. Passionfruit with enhanced fruit, funky. Plums. After cooling — sugars came out. Interesting. Strong flavor gone. Overall: funky, fermentation-driven. Processing-dominant cup. Three completely different cups in one — ester detonation hot, funk phase mid, mango sweetness cool. | T38: Yeast strains WLPU07 + LALVIN 71B at 96hr fermentation, pH 3.72, 100% anaerobic sealed tank (1.2 bar, 23.4°C) produced extreme ester complexity: γ-decalactone (passionfruit lactone) dominant hot, tartaric esters + acetic acid (plum wine/funk) mid, fructose ester chains (mango sweetness) cold. 1:16 lean ratio was critical safety valve — prevented cloying ester overload and enabled three-phase thermal tracking. Flat-bottom geometry amplified body and even bed saturation. DF64 Gen 2 with aftermarket 64mm flat burrs: first DF64 platform entry in archive. Caturra Chiroso = elongated cell structure, Geisha-adjacent clarity potential overridden by fermentation intensity. Yeast Anaerobic Natural distinct process category from Wild Anaerobic. | U38: Solo visit — Zerah Roasters, Singapore, 26 May 2026. Barista explained fermentation process, flat-bottom geometry rationale, 1:16 ratio decision in detail. Warm educational session on 2nd floor cosy space. Barista recommended Glyph Supply Co (Jurong). | V38: Infographic (Entry #025 Ester Bomb) + Google Maps review + Google review authored by Hari | W38: =IF(OR(ISNUMBER(SEARCH("gesha",G38)),ISNUMBER(SEARCH("geisha",G38))),"⭐ GESHA","") | X38: 465 North Bridge Rd, #02-5063, Singapore 188720
A39: 46183 | B39: Singapore | C39: Nylon Coffee Roasters | D39: Colombia Juan Martin | E39: Banexport | F39: Colombia | G39: Red Striped Bourbon | H39: Washed | I39: Filter Roast | J39: xBloom (Flat-Bottom) | K39: Unknown | L39: Unknown | M39: 1:17 | N39: Unknown | O39: Unknown | P39: Mahlkönig EK Omnia (98mm Flat Burr) | Q39: 7.5 | R39: Berry, Red Plum, Nectarine, Orange Tea | S39: Orange-type aromatic afterfeel when hot — bright and encapsulating. Clearly fruity character throughout. Mellows cleanly as it cools; sugars emerge distinctly at mid-cool phase. Nice and light overall — 1:17 lean ratio working well on this varietal. | T39: EK Omnia 98mm flat burrs + xBloom flat-bottom geometry maintained body integrity at 1:17 lean ratio. Retail bag on shelf dated 10 Jun 2026 but filter batch roast date unconfirmed — cup behaviour (clean sugar emergence, well-integrated stone fruit at cool phase) is consistent with a properly rested lot of 10–21 days post-roast. Red Striped Bourbon sucrose density confirmed by clean sweetness at cool phase. | U39: Solo visit — office lunch break, 13:15 | V39: Direct observation + bag photo (retail stock) | W39: =IF(OR(ISNUMBER(SEARCH("gesha",G39)),ISNUMBER(SEARCH("geisha",G39))),"⭐ GESHA","") | X39: 4 Everton Park, #01-40, Singapore 080004
A40: 46186 | B40: Singapore | C40: Kurasu | D40: Rwanda Nkara Soil Project Lot 1204 | E40: Nkara Soil Project | F40: Rwanda | G40: Red Bourbon | H40: Fully Washed | I40: Filter Roast | J40: V60 Pour-over (Conical) | K40: Unknown | L40: Unknown | M40: Unknown | N40: Unknown | O40: Unknown | P40: Mahlkönig EK43 (98mm Flat Burr) | Q40: 9.27 | R40: Floral aroma, taste of mandarin orange, baked apple and grapefruit, brown sugar-like sweetness and accompanying aftertaste | S40: Strong aftertaste with slight bitterness noted. Baked apple taste dominates and persists across all phases. Sugars emerge clearly on cooling — brown sugar sweetness confirmed at cool phase. Rated average. Rwanda Nkara terroir pushes more citrus-floral (mandarin/grapefruit) vs prior Rwanda entry at Twenty Grams (Entry #024) which was peach/stone fruit dominant. | T40: EK43 98mm flat burrs paired with conical V60 geometry — key hardware distinction vs prior Kurasu Frinsa entry. V60 conical creates faster flow rate and higher bypass risk vs flat-bottom; the slight bitterness is consistent with conical geometry allowing fine particles to over-extract at the drain. Washed Red Bourbon at altitude delivers classic Rwandan citric-malic duality (mandarin + baked apple). Baked apple dominance = malic acid thermally stabilised — persists across full thermal arc unlike volatile citric top notes which fade. Brown sugar aftertaste is sucrose retention signature of Red Bourbon genetics. | U40: Solo visit — 13 Jun 2026 | V40: Direct observation + bean card photo | W40: =IF(OR(ISNUMBER(SEARCH("gesha",G40)),ISNUMBER(SEARCH("geisha",G40))),"⭐ GESHA","") | X40: 261 Waterloo St, #01-24, Singapore 180261
A41: 46187 | B41: Singapore | C41: KerYi Coffee | D41: Colombia Finca La Esmaralda | E41: Finca La Esmaralda | F41: Colombia | G41: Gesha | H41: Honey | I41: Light Roast | J41: Hario Switch (Immersion/Percolation Hybrid) | K41: 15 | L41: 210 | M41: 1:14 | N41: 91 → 78 | O41: 60g (~4:1) | P41: Ditting 98mm flat burr | Q41: 15 | R41: Citrus, white florals, lychee, sugar-cane sweetness | S41: Smooth body throughout. Lychee & white florals lead in the hot phase — fragile linalool terpenes survived the tight 1:14 concentration. Citrus surfaces mid-cool as perceived sweetness rises; honey-derived sweetness rounds the cool-phase finish into progressive smoothness. Rated highly — a fine, relaxing Gesha. Clarity held; upper Gesha tier (cf. El Obraje washed favourite, Hiu Los Lajones honey Panama). | T41: Ditting 98mm flat burrs deliver lab-grade narrow particle distribution with minimal fines — the key variable licensing an aggressive 1:14 ratio without astringency. Descending pour (91°C bloom/first pour → 78°C final) uses temperature as a brake on the extraction tail: high heat early extracts volatile terpenes, acids & sugars; the cool final pour reaches target volume while suppressing late-stage chlorogenic-acid bitterness. Hario Switch valve-closed immersion develops honey-process mucilage sweetness & body evenly before percolative drain adds finish definition — conical geometry runs against the flat-bottom affinity but suits this process. | U41: Solo relaxation visit — Sunday 14 Jun 2026, 11 AM; barista-led brew interview (grinder/ratio/temp confirmed) | V41: Direct observation + menu photo + barista interview | W41: =IF(OR(ISNUMBER(SEARCH("gesha",G41)),ISNUMBER(SEARCH("geisha",G41))),"⭐ GESHA","") -> ⭐ GESHA | X41: 161 Lavender St, #01-08, Singapore 338750
A42: 46192 | B42: Singapore | C42: Corner Corner | D42: Malaysia My Liberica | E42: My Liberica (Jason Liew), Kulai, Johor | F42: Malaysia, Kulai, Johor | G42: Liberica (Coffea liberica) | H42: JH Natural (Jekyll & Hyde controlled fermentation - proprietary My Liberica process) | I42: Light | J42: Pour Over (filter) | K42: 13 | L42: 190 | M42: 1:14.6 | N42: 90-92 (steady throughout) | O42: Unknown | P42: Timemore (conical Gold burr, coarse) | Q42: 13 | R42: Root beer / Tropical fruit punch / Raspberry candy / Rambutan / Longan / Sarsi (roaster: One Half) | S42: Interesting and approachable - 'not so funky but different for sure'; picked out longan-type fruit. First non-arabica capture in the archive; landed as a positive novelty rather than rejected. | T42: First Liberica (Coffea liberica) and first Malaysia/Johor origin in archive; near-sea-level farm (26-30 MASL). Low 13g dose at ~1:14.6 ratio with steady 90-92C and a conical Timemore Gold burr deliberately tames Liberica's smoky-woody funk into a cleaner, longan-forward cup; the small dose + generous water dilutes intensity for legibility. NOTE: barista verbally cited ~1:16, but stated 13g:190g computes to 1:14.6. | U42: Roaster: One Half (light-roast filter program). Corner Corner is a vinyl-record listening bar/cafe; walls of LPs, warm low lighting, Japanese-style carafe-and-cup serve. Friday 19 June 2026, ~15:15. Rated awesome by Hari. | V42: Field audit (Claude) | W42: =IF(OR(ISNUMBER(SEARCH("gesha",G42)),ISNUMBER(SEARCH("geisha",G42))),"⭐ GESHA","") | X42: 16 Duxton Rd, Singapore 089482
A43: 46192 | B43: Singapore | C43: Equate Coffee | D43: Colombia Huila La Pradera | E43: La Pradera | F43: Colombia, Huila | G43: Gesha | H43: Washed | I43: Unknown | J43: Pour Over (Orea V4) | K43: 15 | L43: 210 | M43: 1:14 | N43: 90-92 (pours 1-2), 68-70 (pours 3-4) | O43: Unknown | P43: EK43 | Q43: 13 | R43: Peach Jam / Orange / Honey Sweetness | S43: Average - strong isolated peach note but jam/honey sweetness underdeveloped; suspects 1:15 ratio would have balanced acid/sweetness better | T43: Flat-burr EK43 (98mm) paired with flat-bottom Orea V4 geometry and a descending 90-92C to 68-70C thermal pulse profile; the 1:14 ratio (tighter than Hari's 1:15-1:17 default) front-loaded malic acid extraction (strong peach) while leaving honey/sweetness underdeveloped due to reduced dilution and low back-half temperature. | U43: 2nd-floor minimalist cafe; pastel interiors, spacious, dog-friendly; cakes-only food menu (banana cake); benchmark ambience per Hari. | V43: Field audit (Claude) | W43: =IF(OR(ISNUMBER(SEARCH("gesha",G43)),ISNUMBER(SEARCH("geisha",G43))),"⭐ GESHA","") -> ⭐ GESHA | X43: 1 Tanjong Pagar Plaza, #02-25, Singapore 082001
A44: 46194 | B44: Singapore | C44: Apartment Roastery | D44: Colombia Javier Quintero | E44: Javier Quintero, Buena Vista Farm | F44: Inza, Cauca, Colombia | G44: Bourbon Aruzi | H44: Washed | I44: Light (Filter Roast) | J44: Pour-over (Hand Brew) | K44: 13 | L44: 220 | M44: 1:16.9 | N44: 95 | O44: Unknown | P44: Mahlkönig EK43 | Q44: 9.5 | R44: White peach; blackberry; jasmine | S44: White peach dominant, well-balanced; clean washed expression, very enjoyable | T44: High-temp (95C) and 1:16.9 ratio on EK43 flat burr favored extraction of volatile floral/peach esters (linalool, lactones) over heavier blackberry polyphenolics, producing a peach-forward, high-clarity cup. 200g bag roasted 15 June 2026 (6 days post-roast at time of visit). | U44: Sister branch of Apartment (Selegie Rd), located Jalan Riang, Serangoon Gardens. First visit to this branch. | V44: Field audit (Claude) | W44: =IF(OR(ISNUMBER(SEARCH("gesha",G44)),ISNUMBER(SEARCH("geisha",G44))),"⭐ GESHA","") | X44: Jln Riang, #15-9, Singapore 358987
A45: 46198 | B45: Singapore | C45: PPP Coffee (Funan) | D45: Ethiopia Suke Quto | E45: Suke Quto Farm (Tesfaye Bekele) | F45: Ethiopia | G45: Welicho & Kurume (blend) | H45: Fully-Washed | I45: Light Filter Roast | J45: V60 Pour-over (Conical) | K45: 15 | L45: 225 | M45: 1:15 | N45: Unknown | O45: Unknown | P45: Mazzer MM (83mm Flat Burr) | Q45: 9 | R45: Nectarine, White Florals, Citrus | S45: Sharp unripe orange dominated all thermal phases — no floral lift, no mid-cool malic sweetness, no phase shift detected. Citric over-extraction signature suppressed linalool volatiles and sucrose emergence. Hardware execution miss — Guji terroir likely unrealised. Rated below average. | T45: Mazzer MM 83mm flat burrs produce wider fines distribution than 98mm reference tier; fine particle accumulation at V60 conical drain drove chlorogenic-acid over-extraction, presenting as persistent sharp citrus and blunting the Welicho & Kurume floral/nectarine terroir expression across the full thermal arc. Second V60 conical over-extraction pattern in archive (cf. Entry #31, Kurasu Rwanda). | U45: Solo visit — 25 Jun 2026; Funan mall location; bean card photographed; no barista consultation | V45: Direct observation + bean card photo + menu photo | W45: =IF(OR(ISNUMBER(SEARCH("gesha",G45)),ISNUMBER(SEARCH("geisha",G45))),"⭐ GESHA","") | X45: 107 N Bridge Rd, #02-19, Singapore 179105
A46: 46200 | B46: Singapore | C46: Apartment Roastery | D46: China Yunnan Meng Hai | E46: Blang and Dai Family Farms | F46: Menghai, Xishuangbanna, Yunnan, China | G46: Purple Leaf Caturra | H46: Double Washed | I46: Light (Filter Roast) | J46: Pour-over (Hand Brew) | K46: 13 | L46: 215 | M46: 1:16.5 | N46: 95 | O46: 4-pour progressive ~30s intervals; Bloom 30g; to 120g (+90g); to 180g (+60g); to 215g (+35g). Descending pour volumes confirmed by barista. | P46: Mahlkönig EK43 | Q46: 9.5 | R46: Dried tangerine peel; red apple; pandan (origin card) / Dried orange peel; red apple; pandan (menu — discrepancy flagged) | S46: Bright vibrant opening (hot); crisp malic clarity; mellowed gracefully at cool with no dominant note; pandan as background aromatic binder; well-balanced; no bitterness; genuinely pleasant surprise for non-core-palate origin | T46: Double Washed process + EK43 flat burr uniformity produced exceptional acid clarity across all thermal phases; constant 95C 4-pour progressive with descending pour volumes (30g bloom → +90g → +60g → +35g) front-loaded solubles extraction then completed gently without bed agitation; Purple Leaf Caturra anthocyanin complexity confirmed at cool phase. | U46: Second visit to Apartment (Jalan Riang); Saturday 27 Jun 2026, 10:45am. Menu note: dried orange peel (menu) vs dried tangerine peel (origin card) — origin card used as authoritative. First Chinese-origin entry in archive (entry #36). | V46: Field audit (Claude) | W46: =IF(OR(ISNUMBER(SEARCH("gesha",G46)),ISNUMBER(SEARCH("geisha",G46))),"⭐ GESHA","") | X46: Jln Riang, #15-9, Singapore 358987
A47: 46201 | B47: Singapore | C47: KerYi Coffee | D47: Ethiopia Urabeast G1 | E47: Unknown | F47: Uraga, Guji, Ethiopia | G47: 74110 / 74112 | H47: Mosto Fermentation | I47: Filter Roast | J47: Hario Switch (Immersion/Percolation Hybrid) | K47: 15 | L47: 210 | M47: 1:14 | N47: 88 → 70 | O47: Unknown | P47: Ditting 98mm flat burr | Q47: 13 | R47: Winey; Raspberry; Purple grapes | S47: First mosto fermentation entry in archive — process milestone. Bright raspberry and florals dominate hot phase; fruit esters volatile and immediate confirming correct low-entry-temp calibration at 88°C. Thermal transition mid-cool reveals progressive winey character as acetic compounds emerge post-ester dissipation. Purple grape ambiguous — raspberry clearly dominant throughout. Light-to-medium body with clean short finish consistent with 74110/74112 JARC varietal genetics. Fruity, controlled, process-honest expression. Rated excellent. | T47: 88°C descending to 70°C entry temp is deliberate suppression of acetic acid volatilisation — allows fruit esters to express cleanly before winey compounds dominate. Ditting 98mm flat burr uniformity protected raspberry ester clarity; 1:14 tight ratio on Hario Switch immersion built even body without over-extracting fermentation-derived acetic acids. 2-minute brew time limited lipid extraction keeping finish clean rather than syrupy. Mosto fermentation uses cherry pulp juice as fermentation medium — produces restrained winey complexity vs full natural while retaining dark fruit ester complexity. | U47: Solo visit — 28 Jun 2026, 10:30AM. Keryi return visit (Entry #31 ref: Colombia Finca La Esmaralda). First mosto fermentation process in archive. | V47: Field audit (Claude) — direct barista confirmation | W47: =IF(OR(ISNUMBER(SEARCH("gesha",G47)),ISNUMBER(SEARCH("geisha",G47))),"⭐ GESHA","") | X47: 161 Lavender St, #01-08, Singapore 338750
A48: 46201 | B48: Singapore | C48: Asylum Coffeehouse | D48: Yellow Sudan Rume | E48: Felipe Arcila - Jardines Del Eden | F48: Pijiao, Quindío, Colombia | G48: Sudan Rume (Yellow) | H48: Extended Fermentation Natural (EF2) | I48: Filter Roast | J48: April Brewer (Flat-Bottom) | K48: 15 | L48: 240 | M48: 1:16 | N48: 90 | O48: 110g (first pour) → 240g (second pour) | P48: Option-O Lagom P64 | Q48: 14 | R48: Lemongrass, Vanilla, Red Fruits, Brown Sugar | S48: Hot phase: red fruits dominant, bright and acidic, light-to-medium body. Mid-cool: lemongrass clarifies as geraniol emerges; vanilla appears as background aromatic. Cool: brown sugar sweetness confirmed, mellowed, clean lingering finish with pleasant mouthfeel. Overall excellent — bright, fruity, balanced, varietal-honest. First Yellow Sudan Rume natural-process entry in archive. | T48: EF2 24-hour Grainpro aerobic fermentation at sub-22°C produced controlled ester development without acetic acid overproduction — cup reads bright and clean vs winey (contrast Entry #37 mosto). Red fruit dominance hot phase = ethyl butyrate/hexanoate fermentation esters. Lemongrass/geraniol mid-cool = Sudan Rume varietal-native genetic signature, not process-derived. Vanillin + brown sugar sucrose emerges sub-55°C at cool phase. April flat-bottom two-pour (110g + 130g) at 90°C maintained even bed saturation preserving delicate geraniol top notes. Three milestones: first Yellow Sudan Rume mutation in archive; first EF2 Extended Fermentation Natural process category; new producer Felipe Arcila / Jardines Del Eden. | U48: Solo visit — 28 Jun 2026, 11:06AM. Second stop of dual-session day (Entry #37 Keryi Coffee mosto fermentation same morning). Receipt SGD 14.00 confirmed. | V48: Field audit (Claude) — bean card + receipt + hardware photos | W48: =IF(OR(ISNUMBER(SEARCH("gesha",G48)),ISNUMBER(SEARCH("geisha",G48))),"⭐ GESHA","") | X48: 311 Jln Besar, Singapore 208970
A49: 46203 | B49: Singapore | C49: 2050 Coffee | D49: Myanmar Arakan Mountain | E49: Asho Chin Coffee Association | F49: Magway, Myanmar | G49: Catimor | H49: Fully Washed & Honey | I49: Light Roast | J49: Automated Tap Dispenser (Filter) | K49: N/A — batch-dispensed, no per-cup brew event | L49: N/A — batch-dispensed, no per-cup brew event | M49: N/A — batch-dispensed, no per-cup brew event | N49: N/A — batch-dispensed, no per-cup brew event | O49: Unknown | P49: N/A — batch-dispensed, no per-cup brew event | Q49: 6 | R49: Yellow Pear, Dried Fruits, Brown Sugar, Almond | S49: Fruity and acidic with pear dominant and a light nutty edge — closely matches official notes (Yellow Pear, Almond). But flat across the cup: none of the hot/mid-cool/cool thermal progression of a manual pourover, reading as machine-consistent rather than barista-crafted. Hari's verdict: not worth a repeat visit — and on principle, he considers it a bad idea to automate the pourover format specifically. Pourover's whole identity rests on a human reading the bed and adjusting pour/temperature in real time; a tap dispenser removes that variable entirely, so even a technically clean cup like this one reads as inert rather than expressive. | T49: Tap-dispensed batch brewing removes the two levers that define pourover's identity — pulse-pour agitation and a controlled, declining temperature curve — collapsing what should be a three-phase thermal arc into one static, averaged extraction state. Consistent, but expressively inert; this backs up Hari's stated view that automation and pourover are a poor philosophical fit. Catimor's rust-resistant hybrid lineage plus the sub-1,050m altitude also compress the acid/aromatic ceiling well below the 1,700m+ Bourbon/Gesha lots this benchmarks against. Automation suits high-throughput formats (espresso, batch drip, cold brew) where uniformity is the point; it works against the reason pourover exists in the first place. Machine-brewed psychological discount applies per scoring convention. | U49: First visit — automated tap filter bar (2050 Coffee), novelty try. First Myanmar origin and first Catimor varietal in archive. Hari has ruled out a return visit and holds a firm general view that automating pourover-format filter brewing is conceptually flawed, regardless of cup quality. | V49: Direct observation + bean card photo | W49: =IF(OR(ISNUMBER(SEARCH("gesha",G49)),ISNUMBER(SEARCH("geisha",G49))),"⭐ GESHA","") | X49: 267 Beach Rd, #01-01, Singapore 199545
A50: 46204 | B50: Singapore | C50: Kyuukei Coffee | D50: Ethiopia Worka Chelchele | E50: Kyūkei Coffee (In-house roast) — confirmed via Instagram DM | F50: Gedeb, Gedeo Zone, Ethiopia | G50: Dega, Wolisho, Kurume (Landrace Triad) | H50: Washed | I50: Light | J50: Pour-over (Deep27, Flat-Bottom, Immersion-Assist) — confirmed by Kyūkei Coffee via Instagram DM | K50: 16 | L50: 240 | M50: 1:15 | N50: 85 → 95 (ramped) | O50: 30 seconds | P50: Unknown — Kyūkei DM did not address grinder; tall cylindrical flat-burr unit visible in bar photo, model unconfirmed | Q50: 9 | R50: Lemon, Peach, Bergamot, Apricot | S50: Floral hit and citrus brightness dominated the hot phase — lime/lemon citric clarity with linalool florals leading. Mid-cool: brightness tapered into balanced malic structure; slight chlorogenic bitter tinge after slurp — contained, not a flaw. Cool phase: nectarine and stone fruit sugars emerged cleanly; jasmine/berry aftertaste lingered beyond the cup. Excellent 4/4 palate alignment with roaster notes. Barista confirmed "bright" — accurate. Berry-jasmine aftertaste tail identified as likely Wolisho landrace signature beyond stated roaster notes. | T50: Deep27 flat-bottom immersion-assist brewer (confirmed by Kyūkei via DM) — the "D something" brewer identified in-session. Immersion-assist geometry ensures full and even bed saturation before drawdown, explaining the exceptional extraction clarity and balanced thermal arc observed. Grinder model unconfirmed — tall cylindrical flat-burr unit visible on bar but not identified by Kyūkei in DM. House ratio confirmed as 16g/240g (1:15) — within the 1:15–1:17 Palate DNA comfort band. Bloom confirmed 30 seconds. In-house roast confirmed. | U50: Solo visit — Kyūkei Coffee Maxwell lunch audit, 01 Jul 2026, 13:04 | V50: Direct observation + receipt + barista confirmation | W50: =IF(OR(ISNUMBER(SEARCH("gesha",G50)),ISNUMBER(SEARCH("geisha",G50))),"⭐ GESHA","") | X50: 121 Bukit Merah Lane 1, #01-06, Singapore 150121
A51: 46206 | B51: Singapore | C51: Zerah Roasters | D51: Finca Villarazo — Pink Bourbon | E51: Finca Villarazo | F51: Colombia | G51: Pink Bourbon | H51: Washed | I51: Filter Roast | J51: Pour-over (Orea V4 — Flat-Bottom) | K51: 15 | L51: 240 | M51: 1:16 | N51: 92 (constant) | O51: 50g / 40s (1:3.3 bloom ratio) | P51: DF83V (83mm Flat Burr) | Q51: 9 | R51: Lively and juicy; Pomegranate; Mandarin; Lingering Florals | S51: Hot phase: simultaneous pomegranate + mandarin orange hit — bright, punchy, fruity. Low-to-medium body throughout. Mid-cool: sugar emergence as brightness decreases — sucrose surfacing as citric volatiles dissipate. Cool phase: sugar dominant with pomegranate aftertaste lingering cleanly. Floral presence subtle — linalool under the citric punch. Official notes confirmed across all three thermal phases. First Pink Bourbon in archive. | T51: DF83V 83mm flat burrs (Chinese-market variant) — first DF83 platform entry in archive, largest consumer flat burr diameter logged (83mm vs prior max 98mm commercial). Larger burr surface area + higher RPM produces near-zero fines, explaining exceptional acid clarity at hot phase. Orea V4 flat-bottom geometry: zero bypass, full bed saturation via wave filter — isolated Pink Bourbon citric-malic duality without channeling interference. 22 days off roast (roasted 11 Jun 2026) — one day past optimal 10-21 day degas window; citric top notes (mandarin) still present but beginning to fade, explaining why mid-cool sugar emergence was earlier and stronger than expected. Bloom 50g/40s (1:3.3 ratio) — generous bloom on 15g dose ensured full CO₂ purge before extraction. Constant 92°C with no temperature step-down: single-temp protocol on washed Pink Bourbon works because the bean has no heavy mucilage sugars requiring lower-temp management. Pink Bourbon genetic signature confirmed: ellagic acid esters (pomegranate, thermally stable) + citric acid (mandarin, volatile) co-present hot phase; sucrose density characteristic of Bourbon mutation reveals at cool. In-house micro-roastery adjacent to café — Zerah roasts own beans on-site. | U51: Solo visit — Zerah Roasters, Singapore. Friday lunch break, 12:30 PM, 3 Jul 2026. Second Zerah visit (Entry #035 ref: El Diviso Ester Bomb, 26 May 2026). Bean card photo confirmed. In-house roast, micro-roastery on-site next to café. Barista: Aqil — most friendly and enthusiastic barista across all 48 archive visits to date. Explained brew parameters, roast date, and flat-bottom geometry rationale unprompted. Standout human element — educational and warm throughout. | V51: Field audit (Claude) — bean card + barista confirmation | W51: =IF(OR(ISNUMBER(SEARCH("gesha",G51)),ISNUMBER(SEARCH("geisha",G51))),"⭐ GESHA","") | X51: 465 North Bridge Rd, #02-5063, Singapore 188720
A52: 46207 | B52: Singapore | C52: Oaks Coffee Co. | D52: Floripondio 90 Hours | E52: Los Rodriguez | F52: Bolivia | G52: Pacamara | H52: Lactic Honey | I52: Filter Roast | J52: Origami Dripper (Flat-Bottom) | K52: 15 | L52: 240 | M52: 1:16 | N52: 88 (constant) | O52: 80-90g first pour (3-pour protocol) | P52: Option-O Lagom P80 (80mm Flat Burr) | Q52: 9 | R52: Mango; Passionfruit | S52: Hot phase: mango and passionfruit dominant — bright punchy LAB ester burst. Mid-cool: tropicals recede, sugar clarity emerges, lactic-glycerol creaminess surfaces. Cool phase: clean nectarine emergence — Pacamara varietal-native genetic signature. Clean honey sweetness, thermally stable finish. Bright, fruity, well-structured throughout. Highly enjoyable. | T52: P80 80mm flat burrs delivered near-unimodal distribution on Pacamara's oversized bean mass; 88°C constant temperature preserved LAB-derived fruit esters and lactic-glycerol creaminess from 90-hour fermentation without volatilising into sharpness; Origami flat-bottom zero-bypass architecture protected aromatic integrity across all three thermal phases. | U52: Solo visit — Oaks Coffee Co., Bukit Timah Road, 4 Jul 2026, 16:00. Café Day 4 of operations. Milestones: First Bolivia, First Pacamara, First Lactic Honey, First P80 platform. Barista warm and knowledgeable. | V52: Direct observation + bean card photo + barista confirmation | W52: =IF(OR(ISNUMBER(SEARCH("gesha",G52)),ISNUMBER(SEARCH("geisha",G52))),"⭐ GESHA","") | X52: 619H Bukit Timah Road, Singapore 269728
A53: 46208 | B53: Singapore | C53: Homeground Coffee Roasters | D53: Colombia Inmaculada Gesha Natural | E53: Inmaculada Estate | F53: Valle del Cauca, Colombia | G53: Gesha | H53: Natural | I53: Light | J53: Origami Dripper (Ceramic — Flat-Bottom Stand) | K53: 15 | L53: 247 | M53: 1:16.5 | N53: 86-90 | O53: Unknown | P53: Mahlkönig EK43 (98mm Flat Burr) | Q53: 19 | R53: Hibiscus, Pomegranate, Stewed Peach, Darjeeling Tea | S53: HOT: Hibiscus and pomegranate bright and balanced — clean anthocyanin-driven floral punch, excellent opening. | MID-COOL: Flavour tapered gracefully; Darjeeling tea polyphenol structure emerged, smooth and soothing. | COOL: Tea backbone confirmed with slight sugar aftercoat — cherry-dried sucrose persisting cleanly at sub-50°C. Overall: excellent and deeply relaxing; Gesha varietal identity held under natural process layer. Top-tier entry — starred. | T53: EK43 98mm flat burrs at 24–26 click equivalent; 86–90°C natural protocol deliberately suppresses acetic acid volatilisation while preserving anthocyanin-driven hibiscus esters and Gesha linalool-floral DNA. Lean 1:16.5 ratio dilutes fermentation-derived sugar density to reveal Gesha varietal structure underneath. Origami flat-bottom stand confirmed by direct observation — same pink ceramic unit used for both cups. 21 days off roast (roasted 14 Jun 2026, tasted 5 Jul 2026) — optimal degas window per bean card guidance; volatile aromatics intact, zero stale oxidation. Darjeeling tea polyphenol structure held clean across all thermal phases confirming precision aerobic fermentation at Inmaculada. First Colombia Gesha Natural in archive; completes washed/honey/natural Colombia Gesha process trilogy. First Homeground entry; first Origami brewer logged. | U53: Father-daughter visit — Homeground Coffee Roasters Bukit Timah Experience Room; 5 Jul 2026 10:30 AM | V53: Field audit (Claude) — bean card + barista confirmed + direct observation | W53: =IF(OR(ISNUMBER(SEARCH("gesha",G53)),ISNUMBER(SEARCH("geisha",G53))),"⭐ GESHA","") -> ⭐ GESHA | X53: 911 Bukit Timah Rd, Singapore 589622
A54: 46208 | B54: Singapore | C54: Homeground Coffee Roasters | D54: Bolivia Los Rodriguez Caturra Washed | E54: Los Rodriguez | F54: Samaipata, Bolivia | G54: Caturra | H54: Washed | I54: Light | J54: Origami Dripper (Ceramic — Flat-Bottom Stand) | K54: 15 | L54: 244 | M54: 1:16.2 | N54: 90-93 | O54: Unknown | P54: Mahlkönig EK43 (98mm Flat Burr) | Q54: 10 | R54: Apricot, Apple, Honey | S54: Aanya's cup (companion entry). Fruity and clean throughout — apricot and stone fruit character apparent from opening; honey sweetness emerged clearly at cool phase. Both Hari and Aanya enjoyed; approachable, well-structured, and clean finish with no bitterness. Excellent introduction-level specialty filter. | T54: EK43 98mm flat burrs at 26–28 click equivalent (coarser than Gesha Natural — consistent with washed protocol building structured body); 90–93°C higher temp than natural protocol to fully dissolve Caturra's denser post-pulping cellulose structure. Origami flat-bottom stand confirmed by direct observation — same pink ceramic unit as Gesha. Flat-bottom geometry builds even puck saturation preserving malic apricot-apple clarity. Samaipata Bolivia high-altitude Caturra: compact varietal frame produces clean malic acid structure with honey-sucrose finish. Bean card specifies 14-day minimum rest. Roast date unknown. | U54: Father-daughter visit — Homeground Coffee Roasters Bukit Timah Experience Room; 5 Jul 2026 10:30 AM; Aanya's cup | V54: Field audit (Claude) — bean card confirmed + direct observation | W54: =IF(OR(ISNUMBER(SEARCH("gesha",G54)),ISNUMBER(SEARCH("geisha",G54))),"⭐ GESHA","") | X54: 911 Bukit Timah Rd, Singapore 589622
A55: 46208 | B55: Singapore | C55: Cowpresso Coffee Roasters | D55: Geisha Colombia Las Nubes | E55: Unknown | F55: Valle de Cauca, Colombia | G55: Geisha | H55: Natural | I55: Medium | J55: Pour-over (Cowpresso Custom 3-Hole Ceramic Dripper — Conical) | K55: 15 | L55: 225 | M55: 1:15 | N55: 92 | O55: Unknown | P55: DF83 (83mm Flat Burr) — barista confirmed | Q55: 9.9 | R55: Lychee, Strawberry, Blueberry, Floral, Lemons | S55: HOT: Explosive berry and lemon citric punch; fruity-forward ester detonation with isoamyl lychee dominant and acetic back-note trailing from Natural process. | MID-COOL: Acid persistence — lychee ester adheres to palate; malic backbone emerges as citric fades; still assertive rather than settling. | COOL: Lychee and body hold clean to final temperature; no notable sugar emergence — melanoidin body from medium roast persists. Verdict: An aggressive Geisha expression — Natural process × medium roast drives a fruit-heavy, body-forward profile divergent from the archive's Washed Geisha baseline. Enjoyable on its own terms; confirms Palate DNA preference for calmer washed clarity. First Natural Geisha in archive. Father-daughter visit with Aanya; barista Aung (Myanmar) gifted a complimentary sea salt latte — standout warmth and hospitality. Excellent café ambience and visual aesthetics noted. | T55: Natural process ester chemistry (isoamyl acetate/lychee, berry esters) amplified by the custom Cowpresso 3-hole conical ceramic dripper's extended bed contact geometry, explaining the assertive acid punch and lychee persistence across all three thermal phases; medium roast Maillard contribution added unusual body mass for a Geisha, compressing linalool florals but sustaining melanoidin mouthfeel to cool — third conical-geometry entry in archive, consistent with the documented over-extraction pattern. DF83 83mm flat burrs provided low-fines grind consistency, moderating fermentation-derived acetic acid amplification. 10 days off roast (roasted 25 Jun 2026) — opening edge of optimal rest window; residual CO₂ may have contributed to slightly compressed clarity. | U55: Father-daughter visit with Aanya — Cowpresso Coffee Roasters Singapore, 5 Jul 2026, 17:00. Second café of the day after Homeground Coffee Roasters morning session (2 Geishas in one day). Post-hike afternoon visit. Barista: Aung (from Myanmar) — warm and hospitable; gifted a complimentary sea salt latte for tasting. Excellent café ambience and visual aesthetics. Roast date: 25 Jun 2026 (10 days off roast at time of visit). Coffee name 'Las Nubes' from menu/receipt; bean bag reads 'Valle de Cauca' — Las Nubes likely estate name, unconfirmed. | V55: Direct observation + bean bag photo + receipt + barista confirmation (Aung) | W55: =IF(OR(ISNUMBER(SEARCH("gesha",G55)),ISNUMBER(SEARCH("geisha",G55))),"⭐ GESHA","") -> ⭐ GESHA | X55: 21 Lor Kilat, #01-07, Singapore 598123
A56: 46209 | B56: Singapore | C56: Fluid Collective | D56: Alo Coffee — Natural Anaerobic Ethiopia 74158 | E56: Tamiru Tadesse | F56: Ethiopia | G56: 74158 | H56: Natural Anaerobic | I56: Light | J56: Hario Switch (Flat-Bottom Immersion Hybrid) | K56: 15 | L56: 225 | M56: 1:15 | N56: 70 → 90 → 70°C (Thermal Oscillation Protocol) | O56: Unknown | P56: Lagom P64 | Q56: 11 | R56: Lychee | Purple Grape | White Peach | S56: HOT: Perfect balance — lychee and white peach hit immediately. Clean tropical entry, no fermented funk. Light to medium body. WARM: Medium body settles; winey grape character emerges — controlled anaerobic expression, no acetic sharpness. COOL: Brightness recedes, grape clarifies and becomes dominant signal. Less vivid but more structured. Clarity increases as heat dissipates. Overall: well done. Fluid tamed the anaerobic variable cleanly. | T56: 74158 (JARC Ethiopian selection) under anaerobic natural protocol: sealed-tank fermentation produces geraniol and rose oxide compounds — lychee and white peach dominant in hot phase. Ethyl acetate and anthocyanins unlock in warm phase as winey grape. Cool phase: volatile esters dissipate, structural anthocyanin compounds clarify into clean grape signal — classic anaerobic thermal behaviour. Fluid's 70→90→70°C protocol preserved fermentation character without amplifying acetic sharpness. Third Fluid visit confirms thermal oscillation protocol consistent across all menu rotations. Served in white handled mug — different serveware vs previous Fluid visits. | U56: Third visit to Fluid Collective, 6 July 2026, 13:10, lunch. Menu fully rotated — all three filter offerings new. First cup of two ordered today. Experimental mood — chose anaerobic. Barista confirmed: ratio 1:15, temp 70→90→70°C, standard Fluid protocol. | V56: Live Field Audit — Third Visit | W56: =IF(OR(ISNUMBER(SEARCH("gesha",G56)),ISNUMBER(SEARCH("geisha",G56))),"⭐ GESHA","") | X56: 24 Opal Cres, Singapore 328418
A57: 46209 | B57: Singapore | C57: Fluid Collective | D57: Gara Agena | E57: Gara Agena Washing Station | F57: Ethiopia | G57: Heirloom Ethiopian Varieties | H57: Washed Special Prep | I57: Light | J57: Hario Switch (Flat-Bottom Immersion Hybrid) | K57: 15 | L57: 225 | M57: 1:15 | N57: 70 → 90 → 70°C (Thermal Oscillation Protocol) | O57: Unknown | P57: Lagom P64 | Q57: 9 | R57: Nectarine | Mandarin Orange | Floral Honey | S57: HOT: Bright nectarine hit immediate and clean. Floral light orange present from the first sip. Honey detectable even at high temperature — extremely clean washed expression, orange character very clear. WARM: Honey gains ground and becomes the dominant note. Coffee calms and cleans further. Orange recedes to background — gentle, not forward. COOL: Very nice to drink. Washed clarity fully expresses. Nectarine returns cleaner and more defined at lower temperature. Top of my list for what I like. Exceptional. | T57: Gara Agena Washing Station — Gedeo Zone, Ethiopia. Washed Special Prep designation = Ethiopian Coffee Exchange highest sorting standard, defect-free, hand-selected. Heirloom Ethiopian varieties carry exceptional linalool ester diversity expressing as mandarin orange and floral honey. Nectarine = malic acid dominant — Hari's core palate signal. Clean three-phase thermal arc: nectarine/orange hot → honey grounds warm → washed clarity + nectarine cool. Same Fluid hardware and protocol as all prior visits. Perfect post-anaerobic palate reset — washed clarity after fermentation complexity creates maximum contrast in same session. | U57: Second cup of two at Fluid Collective third visit, 6 July 2026. Followed Alo Coffee Natural Anaerobic — deliberate contrast pairing. Gara Agena placed top of personal preference list by Hari. SGD 9 — outstanding value for Special Prep Ethiopian heirloom. | V57: Live Field Audit — Third Visit | W57: =IF(OR(ISNUMBER(SEARCH("gesha",G57)),ISNUMBER(SEARCH("geisha",G57))),"⭐ GESHA","") | X57: 24 Opal Cres, Singapore 328418
A58: 46210 | B58: Singapore | C58: Pinhole Coffee Bar | D58: Santa Barbara #1 — Gesha Honey Colombia | E58: Jhon Samboni — Santa Barbara #1 | F58: Colombia — Huila | G58: Gesha | H58: Honey | I58: Light | J58: Hario V60 Ceramic (Conical — Single Aperture) | K58: 13.5 | L58: 200 | M58: 1:14.8 | N58: 92°C (Constant) | O58: 52g (3.85× dose) | P58: Mahlkönig EK43 Mini (64mm Flat Burr) | Q58: 15 | R58: White Florals, Berry Candy, Tangerines | S58: HOT: Tea-like and light — less acidic than expected. Bergamot and white florals present from the first sip, characteristic Gesha linalool signature. Not loud; elegant and restrained. WARM: Subtle tangerine and stone fruit emerge as malic acid takes over from citric. Lychee hit — geraniol expression surfacing at lower temperature. Honey sweetness begins layering in. Brightness tapers cleanly with no harsh edge. COOL: Cup fully opens. Mandarin orange clarifies as the dominant acid signal — malic at low temp, softer and rounder than tangerine. Honey sweetness crystallises and lingers as a clean aftertaste. Best phase of the cup — this is a cold-cup Gesha. Patience rewarded. | T58: Jhon Samboni's Santa Barbara #1 roasted by Slurp Coffee Project (Roast Gate 15 June — 22 days off-roast, peak filter window). EK43 Mini (64mm flat burrs) — compact single-dose grinder with 64mm flat burrs, tighter particle distribution than full-size EK43 98mm; superior grind uniformity for single-dose filter; V60 conical geometry concentrates fines at apex creating flow restriction risk — mitigated here by fast 2-minute draw-down. 1:14.8 ratio (below Palate DNA band 1:15–1:17) amplified sweetness but compressed hot-phase aromatic lift. Honey process ketone-derived berry/stone fruit compounds require temperature below 65°C to fully volatilise — explains cold-phase revelation. Flat-bottom geometry would have delivered wider aromatic headspace in hot phase. | U58: Solo audit — Café debut, Watchlist visit fulfilled. 7 July 2026, 12:30 PM. Two offerings on menu: this Gesha at SGD 15 (Santa Barbara #1, Slurp Coffee Project) and Peru Natural Sidra+Caturra at SGD 12 (Elvis Tineo, Cajamarca). Chose Gesha. Pinhole Barista's Stash SGD 10 blind option also available. First Slurp Coffee Project roast in the archive. Barista noted V60 usage is legacy from previous management; current team considering switch to flat-bottom or siphon in future. | V58: Live Field Audit — Café Debut + Bean Card (Slurp Coffee Project) + Barista Confirmation (dose/temp/pour protocol) | W58: =IF(OR(ISNUMBER(SEARCH("gesha",G58)),ISNUMBER(SEARCH("geisha",G58))),"⭐ GESHA","") -> ⭐ GESHA | X58: 27 Purvis St, #01-02, Singapore 188604
A59: 46211 | B59: Singapore | C59: Double Shot Coffee | D59: Kotowa Carolina Gesha | E59: Kotowa Estate — Carolina Lot | F59: Boquete, Chiriquí, Panama | G59: Gesha | H59: Natural | I59: Unknown | J59: OREA V4 (Flat-Bottom) | K59: 13.5 | L59: 180 | M59: 1:13.3 | N59: 92°C | O59: 50g bloom (4-pour: 50/50/50/30g) | P59: Ditting 63.5mm Flat Burr | Q59: 16 | R59: White Floral · Peach · White Grape | S59: HOT: Bright and immediate peach hit — ethyl ester fraction opening cleanly with malic brightness. Promising, high-energy opening. MID-COOL: White florals and peach clarity emerging together — linalool terpenes surfacing as expected for Gesha genetics. Both official notes (white floral, peach) tracking accurately. COOL: Cup mellows significantly. Peach recedes to background. Sucrose sweetness underperforms expectation — sugars suppressed by concentrated house ratio. Lingering bitterness detected — procyanidin and tannin expression from Natural cherry skin polyphenols amplified by 1:13.3 TDS. White grape polyphenol reads as astringent rather than sweet at cool. Overall rated average. Bean quality likely higher than this ratio reveals. Would revisit at 1:15–1:17 to properly isolate Kotowa terroir ceiling. | T59: Ditting 63.5mm flat burr delivered tight PSD with minimal fines migration and low heat transfer — correct hardware for a delicate Natural Gesha. OREA V4 flat-bottom geometry ensured uniform bed extraction and even dwell time across full coffee bed. However, the 1:13.3 concentrated house ratio elevated TDS significantly above standard 1:15–1:17 Palate DNA band — at this concentration, Natural process polyphenols (procyanidins, chlorogenic acid lactones from dried cherry skin) remain in solution without adequate water buffer to suppress bitterness below palate threshold. Sucrose sweetness outcompeted at cool phase. Ratio is the primary extraction variable suppressing the Gesha's characteristic tea-like sweetness. A 1:15–1:17 recipe would likely transform the cup's cool-phase expression entirely. | U59: Solo visit — 08 Jul 2026, 14:15. Double Shot Coffee, Kampong Bahru. Food-free dedicated brew-bar café. Barista warm and knowledgeable — voluntarily walked through all brew parameters (dose, temp, pour structure, grinder) without prompting. Comfortable seating. Visited directly after disappointment-driven palate reset at Nylon Coffee Roasters. First Kotowa Carolina estate entry in archive. First Double Shot Coffee visit. House philosophy: concentrated double-shot style filter — 1:13.3 is intentional format, not an error. | V59: Live Field Audit — Menu photo + barista interview + direct observation (Ditting grinder confirmed, OREA V4 confirmed) | W59: =IF(OR(ISNUMBER(SEARCH("gesha",G59)),ISNUMBER(SEARCH("geisha",G59))),"⭐ GESHA","") -> ⭐ GESHA | X59: 19 Kampong Bahru Rd, L1, Singapore 169348
A60: 46211 | B60: Singapore | C60: Nylon Coffee Roasters | D60: La Flor de la Palma | E60: William Manchay Espinoza | F60: Peru | G60: Bourbon | H60: Natural | I60: Filter Roast | J60: xBloom (Flat-Bottom) | K60: Unknown | L60: Unknown | M60: 1:17 | N60: 93 | O60: Unknown | P60: Mahlkönig EK Omnia (98mm Flat Burr) | Q60: 8.5 | R60: Dried Berry; Cherry; Rum & Raisin; Rose | S60: HOT: Berry arrival — bright and light to medium body; minimal aftertaste. MID-COOL: Mellowed; dried berry lingers with an unresolved slightly bitter shadow. COOL: Same persistent bitterness across finish — source identified post-session as chlorogenic acid lactone (CGA lactone) unmasked by lean ratio on this Natural Bourbon. Honest cup, fair for price, not a return target on this bean. | T60: EK Omnia 98mm flat burrs + xBloom flat-bottom at 1:17 created a structural ratio-process mismatch on this Natural Bourbon: lean 1:17 dilution suppressed late-extracting sucrose-ester mass (Rum & Raisin depth), leaving CGA lactone bitterness unmasked at mid-cool and cool phases. 93°C slightly conservative for Bourbon's dense cell wall. Roast date 26 Jun 2026 confirmed by barista (bag showed retail pack date 06 Jul 2026 — not roast date); 12 days rest at consumption, within optimal Natural degassing window. Under-rest was NOT the variable; ratio-process mismatch was. | U60: Return visit to Nylon Coffee Roasters after a disappointing Gesha (Kotowa Carolina) at Double Shot Coffee (Kampong Bahru) earlier same day — Nylon as reliability palate reset. Solo, 15:15 SGT. Peru La Flor de la Palma — Natural Bourbon — first time audited at Nylon under filter conditions. Roast date correction from barista: 26 Jun 2026, not 06 Jul 2026 (bag was retail pack date). Price S$8.50. | V60: Direct observation + bag photo (name/notes reference only) + barista confirmation (roast date 26 Jun 2026) | W60: =IF(OR(ISNUMBER(SEARCH("gesha",G60)),ISNUMBER(SEARCH("geisha",G60))),"⭐ GESHA","") | X60: 4 Everton Park, #01-40, Singapore 080004
A61: 46212 | B61: Singapore | C61: Abseil | D61: El Sauce Gesha | E61: El Sauce Farm | F61: Colombia | G61: Gesha | H61: Washed | I61: Light | J61: CT62 Coffee Dripper (Taster's Coffee / DragonFly Design, Taiwan — Engineered Conical, 62° Cone, 24-Groove Active Flow Compensation) | K61: 15 | L61: 232 | M61: 1:15.5 | N61: 91°C (Constant throughout) | O61: 80g (~5.3× dose) — Aggressive CO₂ purge bloom | P61: Option-O Lagom P64 (64mm Flat Burr) | Q61: 21 | R61: Gardenia · Mandarin · Dried Apricot · Green Tea · Honeysuckle | S61: HOT: Honeysuckle and honey immediate — linalool terpenes fully volatilised from aggressive 80g bloom; bright floral clean opening. MID-COOL: Very sugary mid-palate; mandarin orange in background; honey clearly detectable; sucrose dominant as volatile top notes subside — very sweet and clean. COOL: Tea-like and beautifully balanced; mandarin mellowed to background; clean lingering sweetness with zero bitterness — CT62 anti-over-extraction engineering confirmed across all three phases. Overall: elegant, restrained washed Gesha. Upper-tier entry. SGD $21 is steep but the bean quality justifies it. Would return. | T61: Option-O Lagom P64 64mm flat burrs (narrow particle size distribution, minimal fines) combined with CT62's 24-groove active flow compensation system (12 long + 12 short grooves) eliminated standard conical over-extraction risk entirely — the CT62 is a conical in geometry only; its engineered groove architecture regulates flow rate at both high and low water levels, producing extraction consistency comparable to flat-bottom geometry. Aggressive 80g bloom at constant 91°C front-loaded complete linalool terpene dissolution, delivering honeysuckle immediately in the hot phase. Conservative 91°C throughout suppressed chlorogenic acid extraction — confirmed by zero phenolic shadow at cool phase. CT62 won 2023 German Design Award and 2023 China and Korea Brewers Cup. First CT62 entry in archive — classified as Engineered Conical (flow-compensated), distinct from standard V60 conical entries. | U61: Solo visit — Abseil café debut, 09 Jul 2026. Barista Glenda — exceptional engagement, long technical conversation, outstanding hospitality. Rated Joint #1 for barista friendliness alongside Aqil at Zerah Roasters — the two finest barista interactions in the archive. CT62 dripper identity confirmed by Glenda + product screenshot (tasterscoffee.com). Glenda explained bloom logic, confirmed 1:15.5 ratio, and noted El Sauce Gesha has won awards in recent years. Extensive filter menu (4+ Gesha options) and competition-grade hardware setup noted — one of the finest specialty filter setups encountered across all 33 archive cafés. Would return without hesitation. Finca Jurutungo Panama Gesha (SGD $28, Anaerobic Natural) flagged as next priority on return visit. | V61: Live Field Audit — menu photo + equipment photos + barista confirmation (Glenda) + CT62 product research (tasterscoffee.com) | W61: =IF(OR(ISNUMBER(SEARCH("gesha",G61)),ISNUMBER(SEARCH("geisha",G61))),"⭐ GESHA","") -> ⭐ GESHA | X61: 70 Shenton Way, #01-14 Eon Shenton, Singapore 079118
A62: 46213 | B62: Singapore | C62: Oaks Coffee Co. | D62: Finca El Diviso | E62: Nestor Lasso | F62: Colombia | G62: Aji Bourbon | H62: Thermal Shock Anaerobic Natural | I62: Filter Roast | J62: Origami Dripper (Flat-Bottom) | K62: Unknown | L62: Unknown | M62: Unknown | N62: Unknown | O62: Unknown | P62: Option-O Lagom P80 (80mm Flat Burr) | Q62: 9 | R62: Lychee; Blueberry Jam; Cranberry | S62: Hot phase: punchy lychee and berry dominant — high-intensity bright acidity, strong entry. Mid-cool to cool: fruit character sustained across all phases without evolution — Thermal Shock ester concentration too embedded to dissipate thermally. Strong persistent aftertaste from cranberry anthocyanin compounds. Interesting but not a repeat — process-forward intensity beyond personal palate threshold. | T62: Thermal Shock Anaerobic Natural at 1960 MASL produced extreme ester and anthocyanin concentration (geraniol/nerol lychee monoterpenes; berry anthocyanins) — fermentation signature dominated all three thermal phases without evolution. Process-preference misalignment confirmed: clarity > complexity hierarchy not served by this process. P80 flat-burr precision and Origami flat-bottom geometry could not temper inherent process intensity. | U62: With friend Alex — Oaks Coffee Co., Bukit Timah Road, 10 Jul 2026, 16:30, before Homeground mock-judge session. Second Oaks visit. Milestones: First Thermal Shock Anaerobic Natural, First Aji Bourbon, First Finca El Diviso (Nestor Lasso). | V62: Direct observation + bean card photo | W62: =IF(OR(ISNUMBER(SEARCH("gesha",G62)),ISNUMBER(SEARCH("geisha",G62))),"⭐ GESHA","") | X62: 619H Bukit Timah Road, Singapore 269728
A63: 46214 | B63: Singapore | C63: Pour.traits Roasters | D63: Thailand Sirinya Geisha Amarone | E63: Sirinya Farm | F63: Chiang Rai, Thailand | G63: Geisha | H63: Anaerobic Natural | I63: Filter Roast | J63: Solo Dripper by Mazelab (Flat-Bottom, 40° angle, Wave 155 filter) | K63: 15 | L63: 225 | M63: 1:15 | N63: 92→75→92→75°C (alternating 4-pour) | O63: Unknown | P63: Mahlkönig EK43S (98mm Flat Burr) | Q63: 10 | R63: Rose, Plum, Mandarin Orange, Honey | S63: HOT: Bright citric front with vivid rose geraniol — aromatic and immediate; rose florals dominant and unmistakable. MID-COOL: Mandarin orange emerges cleanly as citric volatiles dissipate — Harry's signature malic acid marker arriving on schedule. Body noticeably full and structured — medium-strong tea weight, not the light tea elegance of washed Geisha expressions; fuller than any prior washed Geisha entry. COOL: Plum (not peach — darker malic stone fruit consistent with Anaerobic Natural fermentation profile shifting acid toward wine-adjacent fruit rather than bright nectarine); honey-type sweetness rounds the finish — sucrose ester retention from Natural process mucilage rather than fructose-type bright fruit sugar; slight bitterness present at cool phase but fades cleanly — likely residual CGA lactone from Natural process fermentation rather than hardware-derived; clean finish confirms it did not persist. Verdict: Moderately aggressive Geisha — varietal genetics clearly present but Anaerobic Natural process adds lipid body and fermentation weight absent from washed expressions. SGD $10 exceptional value for a Thailand Geisha. Archive firsts: first Thailand origin, first Thailand Geisha, first Nippy Coffee Roaster (Chiang Rai) entry. First Geisha roasted on Stronghold S7X smart electric roaster. | T63: Nippy Coffee Roaster (Chiang Rai, Thailand) — roasted on Stronghold S7X (electric smart roaster with programmable roast curves — high precision). 4-pour alternating temperature protocol (92→75→92→75°C) is a sophisticated extraction engineering choice: 92°C bloom releases CO₂ and extracts volatile geraniol/rose and linalool Geisha aromatics; 75°C cool pour suppresses CGA acid extraction preventing Anaerobic Natural acetic fermentation load from tipping into sourness; 92°C third pour extracts mid-range sucrose esters — honey and plum sweetness from Natural process mucilage; 75°C final pour completes volume while suppressing late-stage CGA lactone bitterness. Residual cool-phase bitterness (fades) consistent with V60 conical bypass fraction rather than process fault — flat-bottom geometry would likely eliminate entirely. EK43S 98mm flat burrs (S-variant: smaller footprint, same burr geometry as EK43) delivered clean floral terpene separation. 1:15 ratio at 15g/225g preserved full lipid body mass — correct choice for Anaerobic Natural's elevated polysaccharide and lipid content. Anaerobic Natural fermentation at Chiang Rai specifically produces elevated geraniol (rose), plum malic esters, and honey sucrose retention vs washed process which strips mucilage entirely. | U63: Solo post-gym visit — Pour.traits Roasters, Outram Park, Singapore. Saturday 11 July 2026, 13:30 SGT. Café relaxed and quiet at this hour — comfortable extended sit. Barista Elaine: exceptional engagement, warm, knowledgeable, and friendly. 2022 barista competition winner — now focused on training other baristas and travelling. Pre-session menu analysis conducted live with Claude (pre-gym morning). Guest bean board featured 20+ offerings from international roasters including Livid Coffee Roasters, flowerchild coffee, nippy coffee roaster, Shake Coffee, Glyph Supply Co and others — extremely rich rotating guest bean program. TUESDAY INTEL: Guest barista from Thailand visiting Pour.traits next Tuesday 15 July 2026, 10AM–2PM — bringing special Thai coffee lot, limited quantity with high sell-out risk. Arrive at 10AM to secure a cup. Serving vessel: bulbous pink ceramic cup (no handle) — concentrates aromatics. First café visit to Pour.traits Roasters. | V63: Live Field Audit — menu photos + bean card photo (Nippy Coffee Roaster bag) + barista confirmation (Elaine) + hardware observation | W63: =IF(OR(ISNUMBER(SEARCH("gesha",G63)),ISNUMBER(SEARCH("geisha",G63))),"⭐ GESHA","") -> ⭐ GESHA | X63: 2 Havelock Rd, #01-14, Singapore 059763
A64: 46215 | B64: Singapore | C64: Fluid Collective | D64: Alo Peaberry — Washed Ethiopia | E64: Tamiru Tadesse | F64: Ethiopia | G64: 74158 (Peaberry) | H64: Washed | I64: Filter Roast | J64: Hario Switch (Flat-Bottom Immersion Hybrid) | K64: 15 | L64: 225 | M64: 1:15 | N64: 70 → 90 → 70°C (Thermal Oscillation Protocol — Fluid Standard) | O64: Unknown | P64: Option-O Lagom P64 (64mm Flat Steel Burrs) | Q64: 10 | R64: Bergamot | Honeysuckle | Mandarin Orange | White Peach | S64: HOT: Excellent clarity and brightness from the very first sip. Bergamot and honeysuckle arrive clean and immediate — floral, refined, quiet. Smooth washed character from the start; zero fermentation noise. Mandarin orange not yet present — patience required. WARM: "Goddamn mandarin orange clearly coming on mid phase." Heavier citrus compounds unlock as the volatile florals recede — a delayed reveal, not an absence. COOL: Honeysuckle, white peach and mandarin orange pop together in balance. The full flavour picture assembles at cool temperature simultaneously. Very nice to drink at this stage. Verdict: Clear, clean and elegant coffee — in simple words. | T64: CONTROLLED 74158 EXPERIMENT — NOW COMPLETE. Same producer (Tamiru Tadesse), same varietal (74158), compared against Entry #056 (Alo Natural Anaerobic, 6 Jul 2026): Washed process strips all fermentation character entirely — no lychee, no winey grape, no tropical ferment signature. Instead: pure floral-citrus varietal expression via bergamot (linalyl acetate, C₁₂H₂₀O₂) and honeysuckle (geraniol, C₁₀H₁₈O). Mandarin orange delayed expression = limonene/hesperidin unlocking as volatile florals recede in the warm phase — masked at high temperature, not absent. WHITE PEACH CONFIRMED IN BOTH 74158 CUPS: appeared in Natural Anaerobic and confirmed again today in Washed Peaberry — this is 74158's intrinsic genetic fingerprint, process-independent. Peaberry format: single round bean (vs standard two flat halves), higher nutrient concentration per cherry → elevated floral intensity. Fluid's 70→90→70°C thermal oscillation protocol confirmed consistent across all four visits — Ong Shen Choy present on bar. | U64: Fourth visit to Fluid Collective, Saturday 12 July 2026, lunch. Ong Shen Choy — 2025 Singapore National Brewers Cup Champion — confirmed on bar. His presence is a consistent highlight across all Fluid visits. Menu: Kainamui PB Washed Kenya (SGD 9), Alo Peaberry Washed Ethiopia 74158 (SGD 10), Alo Anaerobic Natural Ethiopia 74158 (SGD 11). Notably: two versions of the same 74158 varietal on the menu simultaneously — washed and anaerobic natural. Fluid Collective benchmark status confirmed across four consecutive visits. | V64: Live Field Audit — Fourth Visit | Bean card + menu photo | W64: =IF(OR(ISNUMBER(SEARCH("gesha",G64)),ISNUMBER(SEARCH("geisha",G64))),"⭐ GESHA","") | X64: 24 Opal Cres, Singapore 328418
A65: 46217 | B65: Singapore | C65: Pour.traits Roasters | D65: Finca Sophia Torcaza Grand Reserve Washed Geisha | E65: Finca Sophia, Torcaza | F65: Panama | G65: Geisha | H65: Washed | I65: Filter Roast | J65: Hario x Tri-Up FLOW Dripper by Erik Liao (Flat-Bottom, Ceramic, Taiwan) | K65: 12.5 | L65: 190 | M65: 1:15.2 | N65: 91→91→82°C (3-pour descending — WBRC competition protocol) | O65: Unknown | P65: Mahlkönig EK43 (98mm Flat Burr) | Q65: 60 | R65: Lemon Honey, Bergamot, Orange | S65: HOT: Bright orange and lemon arriving simultaneously in perfect co-expression — citric and malic acid neither dominating the other. Honey present in background as sweetness foundation, not feature. Supreme clarity — all flavours hitting at once; every volatile aromatic compound in simultaneous perfect expression without any single note overwhelming. MID-COOL: Clarity builds rather than fades — lemon becomes more visible as citric top notes thermally stabilise; malic acid backbone structured and persistent. COOL: Orange and bergamot settle as lime tinge emerges — tartaric acid expressing as clean lime whisper once volatile citric and malic compounds dissipate. Slight lime aftertaste lingers on tongue — fine, sophisticated, pure. No bitterness, no CGA lactone, no fermentation noise. Verdict: THE finest cup in the archive. New #1 — displaces El Obraje Washed Colombia Gesha (Fluid Collective, Entry #016, 6-month champion). 'Fine and sophisticated — not because of the $60, because of what was in the cup.' SGD $60 most expensive cup in archive history (previous record SGD $18). Worth every cent without qualification. Archive firsts: First Panama Washed Geisha from Finca Sophia/Torcaza, first Hario x Tri-Up FLOW Dripper entry, first WBRC competitor guest brew, first Livid Coffee Roasters entry. | T65: Hario x Tri-Up FLOW Dripper designed by Erik Liao (2023 Taiwan Brewers Cup Champion, founder Tri-Up Coffee) — ceramic flat-bottom with thinner bed depth; single central column with embedded magnets serves three functions: (1) secures filter paper in place without adhesive, (2) prevents fine coffee grounds from compacting and settling at the base which would clog and stall flow, (3) encourages water to saturate the coffee bed evenly rather than channelling down the sides — ensuring a constant vertical flow path throughout the entire brew. Body ribbed design reduces bypass water; base rib design stabilises overall flow rate. Developed over 4 years in partnership with Hario — the FLOW name reflects the design goal: steady, unobstructed, limitation-free flow at any grind size. TaoTao (Inthat Ueasakaree) chose this dripper for his WBRC Brussels 2026 competition routine — the central column's even saturation guarantee is precisely why the cup expressed every flavour simultaneously with supreme clarity and zero channelling noise. 3-pour descending temperature protocol (91→91→82°C): dual 91°C pours extract full volatile aromatic spectrum — linalool florals, citric/malic acid esters, sucrose foundations; 82°C final pour suppresses CGA lactone bitterness completely, preserving clean tartaric acid lime finish. 12.5g/190g at 1:15.2 — within Harry's preferred 1:15–1:17 band. EK43 98mm flat burrs delivered competition-level particle uniformity. | U65: Livid Coffee Roasters x Pour.traits Guest Pop-Up — Tuesday 14 July 2026, 10:00–14:00 SGT. Guest brewer: Inthat Ueasakaree (TaoTao) — Thailand Brewers Cup Champion, WBRC 7th Place Brussels 2026, architectural designer by trade (credits structural precision thinking to brewing approach). Pop-up announced via @grindandshinepodcast Monthly Singapore Coffee Agenda. TaoTao brewing his actual WBRC Brussels 2026 competition coffee and routine concept — beans and recipe fresh off the world stage, days after Brussels. Four competition coffees offered: (1) Mt. Totumas Dela Rosa Natural Geisha — Red Berries, Floral, Stone Fruits; (2) Finca Sophia Torcaza Grand Reserve Washed Geisha — Lemon Honey, Bergamot, Orange [ORDERED]; (3) Los Lajones 8B Geisha Natural — Red Berries, Tropical Fruits, Floral; (4) Los Cenizos Geisha Lot 172 Natural — Red Grape, Black Currant, Floral. SGD $60 — archive price record (previous ceiling SGD $18). Second Pour.traits visit (first: 11 July 2026, Entry #063). Return driven by Elaine's Tuesday intel from first visit — intel confirmed and far exceeded all expectations. | V65: Live Field Audit — competition menu photo + direct competitor confirmation (Inthat Ueasakaree / TaoTao) + WBRC Brussels 2026 official graphic confirmation | W65: =IF(OR(ISNUMBER(SEARCH("gesha",G65)),ISNUMBER(SEARCH("geisha",G65))),"⭐ GESHA","") -> ⭐ GESHA | X65: 2 Havelock Rd, #01-14, Singapore 059763
A66: 46218 | B66: Singapore | C66: Equate Coffee | D66: Peru Cajamarca Lorenzo Arbildo — Washed Gesha | E66: Lorenzo Arbildo | F66: Cajamarca, Peru | G66: Gesha | H66: Washed | I66: Filter Roast | J66: OREA V4 — OPEN Bottom (Flat-Bottom) | K66: 15 | L66: 210 | M66: 1:14 | N66: 92°C → 65°C (descending — pours 1–3 at 92°C, pour 4 at 65°C) | O66: 60g bloom (4-pour: 60g / 120g / 170g / 210g — 0:30 / 0:55 / 1:20 / 2:00) | P66: Mahlkönig EK43 (98mm Flat Burr) | Q66: 12 | R66: Raspberry; Peach; Floral | S66: HOT: Bright immediate malic brightness — simultaneous raspberry ester + peach lactone hit; both official notes tracking accurately from first sip. High-energy, clean opening. MID-COOL: Flavours mellowed; linalool florals emerging as ester volatiles dissipate — textbook Gesha terpene thermal behaviour. Cajamarca citric tinge appearing as a background dimension (terroir marker, not recipe flaw). Excellent clarity, nothing coating the tongue. Peach and berry settling to background with good separation. COOL (Best Phase): Clean short berry aftertaste persisting post-ester dissipation; sucrose-ester tail lingering cleanly. Nice body for washed process. No bitter phenolics — 65°C final pour executed correctly. Overall: First Peru Gesha in archive. Significant upgrade on Entry #040 (Colombia Huila La Pradera, Equate, same ratio 1:14, 19 Jun 2026) — Peru Arbildo lot intrinsically more expressive at this concentration. Washed Peru × Gesha axis confirmed as archive-calibre. Second Equate visit redeems the café Gesha record. | T66: EK43 98mm flat burr delivered uniform PSD with zero fines migration — protected malic acid ester clarity (raspberry, peach) and linalool terpene architecture (floral) across all three thermal phases. OREA V4 OPEN Bottom flat geometry: single central drainage hole ensures full bed saturation and even dwell time; zero bypass; uniform extraction front across flat coffee bed. Aggressive 92°C → 65°C descending temperature protocol: first three pours at 92°C front-loaded volatile ester and sugar extraction from Gesha lipid and sucrose fraction; 65°C final pour (pour 4) suppressed chlorogenic acid lactone extraction in back half, preventing bitter finish at cool phase — explaining clean aftertaste. TROGAMID brewer construction insulates heat in coffee bed during low-temp final pour, maintaining extraction efficiency despite cool input. Ratio 1:14 below Palate DNA band (1:15–1:17) but Peru Arbildo Cajamarca terroir has sufficient malic acid density to express clearly at this concentration — explains upgrade over prior 1:14 Colombia Gesha entry at same café. | U66: Solo visit — Equate Coffee, Tanjong Pagar (1 Tanjong Pagar Plaza, #02-25, Singapore 082001). Wednesday 15 July 2026. Second Equate visit (Entry #040 ref: Colombia Huila La Pradera Gesha Washed, 19 Jun 2026). Barista: new joiner, few days on the job — following written recipe card (photographed). Recipe card confirmed: LORENZO / (FAST)(SLOW) designations; GS:15g / T:92°&65°C / W:210g; pour structure 60-120-170-210g; timings 0:30/0:55/1:20/2:00; OPEN DAMPER noted. First Peru × Washed × Gesha axis in archive. Archive entry #065. | V66: Live Field Audit — barista recipe card photo (authoritative) + bean card photo + direct barista confirmation | W66: =IF(OR(ISNUMBER(SEARCH("gesha",G66)),ISNUMBER(SEARCH("geisha",G66))),"⭐ GESHA","") -> ⭐ GESHA | X66: 1 Tanjong Pagar Plaza, #02-25, Singapore 082001
A67: 46219 | B67: Singapore | C67: Mame (SIGEP Asia booth) | D67: Bambito Estate | E67: Bambito Estate — Priscilla Amar Sitton | F67: Panama (1660–1800 m.a.s.l., per bean card) | G67: Geisha | H67: Washed | I67: Unknown | J67: Pour-over — 2 pours only (7g microdose festival format; brewer not stated → Unknown) | K67: 7 | L67: 105 | M67: 1:15 | N67: 93°C (barista-confirmed) | O67: Unknown | P67: Timemore (model unstated — official SIGEP Asia / SNCC 2026 event grinder) | Q67: 16 | R67: Jasmine · Orange Blossom · Yellow Peach | S67: HOT: orange blossom dominant with a distinct "orange hit" — intensely floral, pronounced tea-like structure. MID-COOL→COOL: drinks beautifully cool; orange blossom sweetens and steps forward; clean citric-orange tinge lands on the aftertaste. Verdict: "a fine Geisha." Tea-like character persistent across all phases. S$16 (¥1,990) for a 7g microdose pour ≈ S$34 full-cup equivalent — second most expensive in the portfolio on a full-cup-equivalent basis, behind Finca Sophia Torcaza (S$60, Pour.traits). Menu correction logged: S$25 = 20g beans price; S$16 = per-cup price. | T67: 7g microdose at 1:15 (105g yield) with only 2 pours at 93°C compressed the extraction into a short, high-clarity window — fewer pour cycles limited agitation and fines migration, favouring volatile linalool/geraniol aromatics (jasmine, orange blossom) over body and sugar-browning depth. Timemore burrs (SIGEP official event grinder) held washed-process clarity; tea-like tactile profile consistent with lean microdose format rather than under-extraction. | U67: SIGEP Asia 2026, Day 2 (16 Jul), Roaster Village — Harry's first-ever coffee festival. MAME booth: Zurich roastery founded 2016 by Emi Fukahori (2018 World Brewers Cup Champion) & Mathieu Theis; "Mame" = "beans" in Japanese. Cup served with personalised bean card ("HARISH"). Same visit: watched Singapore National Brewers Cup live (Timemore official sponsor), SCA/BETTR education, Hario booth tasters, Timemore hardware browsing (purchase deferred), Dutch Colony oat piccolo (excluded — milk drink). | V67: Live Field Audit — Mame menu board photo + bean card photo (authoritative: Geisha spelling, Panama 1660–1800 masl, Washed) + barista-confirmed parameters (7g/105g, 1:15, 93°C, 2 pours, Timemore) + price corrected by Harry (¥1,990 / S$16 per cup; S$25 = 20g beans) | W67: =IF(OR(ISNUMBER(SEARCH("gesha",G67)),ISNUMBER(SEARCH("geisha",G67))),"⭐ GESHA","") -> ⭐ GESHA | X67: Sands Expo & Convention Centre, 10 Bayfront Ave, Singapore 018956 (SIGEP Asia 2026, Roaster Village)
A68: 46224 | B68: Singapore | C68: Pour.traits Roasters | D68: Toki | E68: Unknown | F68: Galyani Vadhana, Chiang Mai, Thailand · 1500 masl | G68: Mixed Local | H68: Natural | I68: Filter Roast | J68: Solo Dripper by Mazelab (Flat-Bottom, 40° angle, Wave 155 filter) — consistent with 11 Jul visit house setup, not barista-reconfirmed this visit | K68: Unknown | L68: Unknown | M68: ~1:15 (taste-inferred by Harry, not barista-confirmed) | N68: Unknown | O68: Unknown | P68: Mahlkönig EK43S (98mm Flat Burr) — consistent with 11 Jul visit house setup, not barista-reconfirmed this visit | Q68: 10 | R68: Pear, Apple, Orange | S68: HOT: Very bright and acidic — vivid, high-toned opening. Apple notes present from hot through mid-phase, consistent with the official card. MID: Apple continuing to carry the cup. COOL: Orange blossom and apple emerge together, with a clean citric acid lift; texture very smooth throughout. Verdict: exceptionally high clarity for a Natural process coffee — Harry noted the cup did not carry the fermentation weight typically expected from Natural processing; drinks more like a clean washed cup despite the process tag. Strong value: SGD $10 for a Chiang Mai Thailand origin, second Thailand-origin entry in the archive after the Sirinya Amarone (Entry #063). Archive first: first Toki (roaster) entry, first Galyani Vadhana Chiang Mai origin, first 'Mixed Local' varietal entry. | T68: Roaster: Toki (Thailand) — bean card confirms Galyani Vadhana, Chiang Mai, 1500 masl, Mixed Local varietal, Natural process. High elevation (1500 masl) for a Thai origin likely supports the acid clarity Harry noted despite Natural processing — higher-altitude Naturals typically retain brighter, cleaner acidity versus lowland Naturals which trend toward heavier fermentation-forward profiles. Brew hardware (Solo Dripper by Mazelab, flat-bottom, EK43S 98mm flat burr) carried over from the 11 Jul visit house setup as a reasonable assumption, NOT independently reconfirmed by barista this visit — dose, yield, precise ratio, and temperature are logged as Unknown accordingly. Harry's taste-inferred ~1:15 ratio is plausible given the flat-bottom brewer's typical operating band but is not archive-verified data. | U68: Lunchtime solo visit — Pour.traits Roasters, Outram Park, Singapore. Monday 21 July 2026, 13:10 SGT. Third visit to Pour.traits (previous: 11 Jul Entry #063 Thailand Sirinya Geisha Amarone; 14 Jul Entry #065 TaoTao WBRC crown entry). Coffee ordered from Livid Coffee Roasters guest bean rotation. Quick lunchtime session — parameters not confirmed with barista this visit; logged per archive integrity rules as Unknown where unconfirmed rather than assumed. | V68: Live Field Audit — bean card photo (Toki roaster bag) + Harry's sensory notes; brew hardware carried forward from prior visit as reasonable but unconfirmed assumption | W68: =IF(OR(ISNUMBER(SEARCH("gesha",G68)),ISNUMBER(SEARCH("geisha",G68))),"⭐ GESHA","") | X68: 2 Havelock Rd, #01-14, Singapore 059763
A69: 46227 | B69: Singapore | C69: Alchemist (Khong Guan Building) | D69: El Frutal | E69: Efraín Castillo | F69: Huehuetenango, Guatemala | G69: Castillo | H69: Washed | I69: Filter | J69: V60 Pour-over (Ceramic Conical) | K69: 15 | L69: 225 | M69: 1:15 | N69: 90 | O69: Unknown | P69: Mahlkönig EK43S (98mm Flat Burr) | Q69: 8.5 | R69: Orange, Apple, Milk Chocolate | S69: HOT: bright, acidic apple hit. MID: mild sourness reading as ripe orange, not a flaw. COOL: mellows to a chocolate-adjacent note, distinct from apple/orange. Sequential note release matched official notes across all three thermal phases — good cup, clean process expression. | T69: EK43S 98mm flat burrs + ceramic V60 conical at 1:15/90°C delivered classic sequential acid handoff: malic apple esters release first (fast, volatile, hot-phase dominant), citric orange notes emerge mid-phase as malic top notes recede, chocolate-adjacent Maillard/sucrose-browning compounds surface last as volatiles dissipate cool. Castillo varietal + 18hr ferment washed process (Efraín Castillo, farm since 2004) preserved structural clarity while allowing the softer sweetness through. First Guatemala + first Castillo varietal + first El Frutal in archive. | U69: Working from home, new Alchemist branch (Khong Guan Building), Friday 24 Jul 2026, discussion with barista on brew recipe. Coffee selection was barista-recommended — she suggested El Frutal specifically citing the washed process for superior clarity over other options on the menu; recommendation confirmed accurate, cup delivered as promised. Barista friendliness: high — warm, engaged, receptive to questions (name not captured this visit). Café notes: this Khong Guan Building branch differs structurally from the typical small-format, mostly-takeaway Alchemist branches — proper seating available, including bar seating directly facing the brew station allowing direct observation of the barista's process. Housed in a heritage/old building; strong ambiance, felt like a genuine sit-down café experience rather than a grab-and-go counter. | V69: Live Field Audit — barista confirmation + menu screenshot + direct observation; Varietal/Producer/Roast confirmed via alchemist.global/products/el-frutal | W69: =IF(OR(ISNUMBER(SEARCH("gesha",G69)),ISNUMBER(SEARCH("geisha",G69))),"⭐ GESHA","") | X69: 2 MacTaggart Rd, #01-01 Khong Guan Building, Singapore 368078
A70: 46227 | B70: Singapore | C70: Prodigal Roasters | D70: Rea | E70: Finca Los Santos | F70: Peru | G70: Geisha | H70: Natural | I70: Light | J70: Origami V60 (Ribbed, Conical) | K70: 16 | L70: 272 | M70: 1:17 | N70: 93 | O70: 40g / 45 sec (4-pour, center-pour technique) | P70: Mahlkönig EK43 (98mm Flat Burr) | Q70: 12 | R70: Grape jello, orange marmalade, jasmine florals | S70: HOT: floral, bright, acidic clarity — jasmine and malic brightness leading. MID-COOL: jasmine fades as florals de-gas; grape and orange marmalade sweetness dominates, flavor calms and becomes very fruity. COOL: sweetness rounds out further, favorite phase — aided by the larger 272g yield giving the fermentation-derived sugars room to develop without cloying. Interesting, well-balanced Geisha. | T70: 16g/1:17 lean ratio + EK43 98mm flat burr particle uniformity preserved floral/acid clarity at HOT despite Natural process; as the cup cooled, fermentation-driven sugars (grape, orange marmalade) emerged predictably per Natural-process chemistry, with the larger 272g yield giving those sugars room to round out rather than concentrate into cloying sweetness. Origami ribbed conical geometry with center-pour technique limited channeling despite conical bypass risk. | U70: Second café of the day, lunchtime, Friday 24 Jul 2026 — visited after Alchemist (Khong Guan Building) same morning, logged in a separate session window. Roastery visit, not a standalone café (Prodigal has no public seating/service yet — serves visitors on-site by arrangement). Spent ~30 minutes in conversation with Jason, who works green beans, roasting, and brewing at Prodigal — self-motivated, passionate, knowledgeable, and generous in sharing information; invited Hari back when in the area. Jason added to Hari's 'great barista/roaster conversations' recognition (alongside Ong Shen Choy, Aqil, Elysia Tan) — separate from the friendliness leaderboard. | V70: Live Field Audit — barista-confirmed brew parameters (Jason) + direct observation | W70: =IF(OR(ISNUMBER(SEARCH("gesha",G70)),ISNUMBER(SEARCH("geisha",G70))),"⭐ GESHA","") -> ⭐ GESHA | X70: 1 MacTaggart Rd, #02-02, Singapore 368089
A71: 46228 | B71: Singapore | C71: Alchemist (Khong Guan Building) | D71: La Betania | E71: Unknown | F71: Tolima, Colombia | G71: Unknown | H71: Washed | I71: Filter | J71: V60 Pour-over (Ceramic Conical) | K71: 15 | L71: 242 | M71: 1:16.1 | N71: 90 | O71: 46g bloom, circular pour to 180-186g, straight center final pour to 242g | P71: Mahlkönig EK43S (98mm Flat Burr) | Q71: 10.5 | R71: Red Apple, Nectarine, Toffee | S71: HOT: apple + orange, bright, high clarity. MID-COOL: apple carries, nectarine sweetness emerges. COOL: nectarine + toffee, clarity continues improving (unusual — most entries peak mid-phase), toffee finish with brief milk-like impression that fades quickly and pleasantly. Excellent — layered, bright, clarity throughout. Fully worth $10.5. | T71: 1:16.1 ratio via EK43S 98mm flat burr + ceramic V60 conical, 90°C. Straight center final pour (vs. circular) reduced late-stage turbulence/fines migration, likely driving the atypical cool-phase clarity increase. New Tolima Colombia sub-region for archive; first La Betania entry. | U71: Second visit to Alchemist (Khong Guan Building) within 24 hours, Saturday 25 Jul 2026, 11:30 AM weekend visit. Same grinder/brewer setup as prior-day visit, barista-confirmed. | V71: Live Field Audit — direct observation, barista-confirmed brew parameters | W71: =IF(OR(ISNUMBER(SEARCH("gesha",G71)),ISNUMBER(SEARCH("geisha",G71))),"⭐ GESHA","") | X71: 2 MacTaggart Rd, #01-01 Khong Guan Building, Singapore 368078
A72: 46231 | B72: Singapore | C72: Apartment (Selegie Rd) | D72: Peru Wilder Garcia | E72: Wilder Garcia | F72: Jaén, Cajamarca, Peru | G72: Gesha | H72: Washed | I72: Light (Filter Roast) | J72: V60 Hand Brew (Conical) | K72: Unknown | L72: Unknown | M72: Unknown | N72: Unknown | O72: Unknown | P72: Option-O Lagom P64 (64mm Flat Burr) | Q72: 9.5 | R72: Nectarine; White Grape; Honeysuckle | S72: HOT: Quiet clarity; nectarine and white grape on entry — clean malic acid onset, moderate intensity, not pyrazine-bright. MID-COOL: Honey sweetness forward; nectarine clarifying and coming up more clearly. COOL: Honey dominant, stable; zero bitterness throughout. Cleanest cool-phase Wilder Garcia across all archive encounters. Producer longitudinal study entry #4 (prior: Asylum Iced #017, Asylum Hot #021, Equate #065). | T72: Option-O Lagom P64 64mm flat burrs on V60 conical: narrower particle size distribution than EK43 98mm burrs, minimal fines generation — eliminates standard conical bypass risk. Explains quiet clean HOT phase and zero cool-phase bitterness. Wilder Garcia 1750–1950 masl Cajamarca altitude: slow cell development concentrates malate esters (nectarine) and linalool/geraniol terpenes (honeysuckle). Harvest 2025. Second Apartment Selegie Rd visit (first: Entry #011, 22 Mar 2026). First Selegie Rd entry with barista-confirmed grinder data. | U72: Solo lunch visit — Apartment Coffee, 139 Selegie Rd, #01-01, Singapore 188309. Tuesday 28 Jul 2026, 12:45 SGT. Second visit to Apartment (Selegie Rd) — first: 22 Mar 2026 Entry #011. Third Apartment brand visit overall. Barista confirmed grinder: Option-O Lagom P64. Brew parameters (dose/yield/temp) not obtained. Fourth Wilder Garcia encounter in archive. | V72: Live Field Audit — bean card photo (Origin: Jaén, Cajamarca; Variety: Gesha; Altitude: 1750–1950 masl; Processing: Washed; Harvest: 2025) + barista grinder confirmation (Lagom P64) + direct sensory observation | W72: =IF(OR(ISNUMBER(SEARCH("gesha",G72)),ISNUMBER(SEARCH("geisha",G72))),"⭐ GESHA","") -> ⭐ GESHA | X72: 139 Selegie Rd, #01-01, Singapore 188309
A73: 46231 | B73: Singapore | C73: Apartment (Selegie Rd) | D73: Kenya Maganjo | E73: Rumukia FCS (Cooperative) | F73: Nyeri, Kenya | G73: SL28 / SL34 / Ruiru 11 | H73: Washed | I73: Light (Filter Roast) | J73: V60 Hand Brew (Conical) | K73: 13 | L73: 215 | M73: 1:16.5 | N73: Unknown | O73: Unknown | P73: Option-O Lagom P64 (64mm Flat Burr) | Q73: 9 | R73: Redcurrant; Pomegranate; Rosehip | S73: HOT: Bright and pinchy phosphoric acid entry; redcurrant and berries hitting immediately — sharper, more aggressive than Wilder Garcia (same session). MID-COOL: Toned down; pomegranate appearing clearly over berry base. COOL: Best phase — berry juice cocktail character; pomegranate and redcurrant together with SL28 sucrose sweetness underneath; rich, hedonistic, fruity. Barista confirmed ratio changes daily — today 13g/215g (1:16.5). First Ruiru 11 varietal entry in archive. | T73: Rumukia FCS cooperative, Nyeri Kenya — SL28/SL34/Ruiru 11 triple-varietal blend at 1550–2300 masl, Harvest 2026. Lagom P64 at 1:16.5 lean ratio: deliberate recipe for this blend — Ruiru 11 phenolics amplify into harsh bitterness at higher TDS; lean ratio keeps SL28/SL34 phosphoric brightness clean while Ruiru 11 contributes body. Berry juice cocktail cool phase = SL34 anthocyanin-driven redcurrant + SL28 phosphoric pomegranate layering with SL28 sucrose density providing juice body weight. Ruiru 11 (CABI hybrid, Coffee Research Foundation Kenya) contributes distinctive phenolic complexity — first Ruiru 11 in archive. Hardware constant with Entry #072 (same V60 conical + Lagom P64, same session). | U73: Solo lunch visit — Apartment Coffee, 139 Selegie Rd, #01-01, Singapore 188309. Tuesday 28 Jul 2026, ~13:30 SGT. Second cup of the session after Entry #072 (Peru Wilder Garcia). Barista confirmed today's ratio: 13g/215g (ratio changes daily). First Kenya hand-brew filter entry at any Apartment branch. Back-to-back comparison with Entry #072 — hardware constant, different origin and varietal. | V73: Live Field Audit — bean card photo (Origin: Nyeri, Kenya; Cooperative: Rumukia FCS; Variety: SL28/SL34/Ruiru 11; Altitude: 1550–2300 masl; Processing: Washed; Harvest: 2026) + barista-confirmed dose/yield 13g/215g + direct sensory observation | W73: =IF(OR(ISNUMBER(SEARCH("gesha",G73)),ISNUMBER(SEARCH("geisha",G73))),"⭐ GESHA","") | X73: 139 Selegie Rd, #01-01, Singapore 188309
A74: 46232 | B74: Singapore | C74: Alchemist (Funan) | D74: The Journey — Las Margaritas Geisha | E74: Las Margaritas | F74: Valle del Cauca, Colombia | G74: Geisha | H74: Honey | I74: Unknown | J74: V60 Pour-over (Stainless Steel, Conical) | K74: 15 | L74: 225 | M74: 1:15 | N74: 85 | O74: 50g bloom, 3-pour structure (bloom + 2), pour timings not recalled — barista-confirmed volumes; observed final pour ran to 252g against the 225g target | P74: Mahlkönig EK43S (98mm Flat Burr) | Q74: 10.5 | R74: Hibiscus, Strawberry, Manuka | S74: HOT: jasmine floral hit, sweetness already present unusually early. MID-COOL: more grounded and settled, light berry note emerging, honey moving to dominant position. COOL: honey fully takes over — sweet, moreish, thoroughly enjoyed and repeatedly highlighted as the standout character. Strong, well-liked cup; Geisha varietal identity held clearly under the honey layer. | T74: 85°C flat-temperature protocol (no descending pours) paired with a stainless steel V60's higher thermal conductivity and lower thermal mass likely compressed the usual floral-then-sugar sequencing, bringing mucilage sweetness forward into the HOT phase rather than reserving it for COOL. Honey-process sugars asserted progressively and became dominant by the cool phase — clean, well-managed process expression with no fermentation noise. Barista-stated 1:15 / 225g logged as authoritative per archive source hierarchy; observed final pour (252g ≈ 1:16.8) noted as minor on-the-day variance, not used to override. ARCHIVE FIRSTS: first stainless steel V60 (all prior V60 entries ceramic); first Las Margaritas farm; third Alchemist branch logged. | U74: Lunchtime visit, Wednesday 29 Jul 2026, 12:30 PM — Alchemist (Funan), 107 N Bridge Rd, #01-01, Singapore 179105. Ordered the limited 10th-anniversary Geisha, available one week only. Menu also offered Our Beginning (La Joyeria, Antioquia Washed, S$6.50) and Clarity in The Present (La Papaya Typica Anaerobic 120H, Loja Ecuador, S$8.50). Served in a plastic takeaway cup despite the S$10.50 price point — noted as a presentation gap typical of Alchemist's compact pop-up-format outlets. Second Valle del Cauca farm in archive after Inmaculada Estate (Homeground, 5 Jul) — same region, different farm and process. | V74: Live Field Audit — barista-confirmed brew parameters + menu screen photo + brewer material confirmed via direct photo | W74: =IF(OR(ISNUMBER(SEARCH("gesha",G74)),ISNUMBER(SEARCH("geisha",G74))),"⭐ GESHA","") -> ⭐ GESHA | X74: 107 N Bridge Rd, #01-01, Singapore 179105
A75: 46234 | B75: Singapore | C75: Lume Café | D75: El Origen | E75: Unknown | F75: Quindío, Colombia | G75: Pink Bourbon | H75: Washed | I75: Filter Roast | J75: V60 Pour-over (Conical) | K75: 15 | L75: 225 | M75: 1:15 | N75: 92 (flat, all pours) | O75: Unknown | P75: Mahlkönig EK43 | Q75: 10 | R75: Yellow Floral; Tangerines; Plum | S75: HOT: plum forward with light orange and a clear nectarine layer — nectarine not on the roaster card, detected independently. MID-COOL: floral lift present but hedged and uncertain; brightness rising; tangerine emerging distinctly as plum recedes; clarity increasing through the phase. COOL: best phase — orange and tangerine fully dominant, structure completely legible, no bitter tail. Washed transparency explicitly named as the driver of increasing clarity across the arc. Strong palate-DNA alignment on malic nectarine and integrated citric brightness; floral axis under-delivered relative to the roaster card despite a fresh 23-day bean and full-temperature extraction. | T75: Barista-confirmed protocol: 92°C FLAT across all pours (no descending-temperature stage), 1:15, Mahlkönig EK43. This inverts the extraction model carried over from Entry #019 at the same venue, where a 90°C→70°C descending pour was credited with truncating the late chlorogenic-acid-lactone tail. With no thermal brake in play here, the clean cool phase must be attributed elsewhere: the EK43's unimodal particle distribution limiting fines-driven late extraction, plus low bean density. Quindío Pink Bourbon at 1350 masl is a soft, high-solubility seed with a thin phenolic reserve — it surrenders solubles early and has less bitter material available to over-extract into, so low altitude protected the cup where temperature curve did at Lume in April. Pink Bourbon genotyping places the variety outside the true Bourbon lineage, closer to Ethiopian landrace material, explaining a floral-citric expression rather than Bourbon sugar-brown density. Thermal arc inversion (plum HOT → citrus COOL) is diagnostic washed behaviour: declining sucrose perception combined with rising acid perception unmasks citric acid as the cup drops. Hedged floral note is NOT staling — at 23 days off roast the linalool fraction should be intact. More likely sustained 92°C through full drawdown drove additional dissolved-solids weight that masked delicate monoterpenes retronasally, compounded by a modest intrinsic floral ceiling for Pink Bourbon at this altitude. ARCHIVE VALUE: forms a controlled two-point hardware comparison with Entry #019 — same venue, same grinder, same 1:15 ratio, same conical V60, only the thermal protocol differs (90+70 dual-temp vs 92 flat). First Pink Bourbon varietal in archive; first non-Gesha coffee logged at Lume. | U75: Solo lunch visit — Lume Café, 108 Robinson Rd, #01-01, Singapore 068900. Friday 31 Jul 2026, 13:30 SGT. First return to Lume since Entry #019 (1 Apr 2026, Corpachi Panama Geisha) — approx. four-month gap. Selected from a four-card board over Brazil Santa Ines Natural and PNG Arufa Natural (both espresso roast) and a Panama lot. ROAST DATE CORRECTION CHAIN: counter bean card read 31/5 (61 days); barista subsequently produced the actual bag in use, roast-stamped 8 Jul 2026 = 23 days off roast, an optimal window. Counter card did not correspond to the bag being brewed. OPEN DISCREPANCY (unresolved): whiteboard card listed Panama Agricola WASHED (blueberry / white tea / plum) while the physical bag on the counter was Panama El Pergamino NATURAL Bourbon, Bambito, producer Yaneth Lucich, 1900 masl, roast-stamped 24 APR 2026 — different farm and different process. Not reconciled; barista confirmation still pending. El Pergamino declined on roast-age grounds (98 days, natural process, elevated lipid oxidation exposure) and profile misalignment. ACTION ITEMS: (1) confirm whether Lume's counter cards are being kept current against hopper contents; (2) confirm Panama lot identity; (3) revisit El Origen to assess full floral ceiling. | V75: Live Field Audit — BARISTA-CONFIRMED (authoritative): roast date 8 Jul 2026 (bag physically shown), ratio 1:15, water temperature 92°C constant, grinder unchanged from prior visit. Bean card photo (El Origen, Pink Bourbon, Quindío, Washed, 1350 masl, Filter Roast) used for green data only. Direct three-phase sensory observation by Hari. DOSE/YIELD NOT BARISTA-STATED: 15g/225g applied per standing archive convention for a stated 1:15 — flagged as convention, not confirmation. Grinder logged as Mahlkönig EK43 per Entry #019 precedent at this venue; EK43 vs EK43S badge not visually confirmed on the day. Brewer material (ceramic/glass/plastic/steel) not confirmed — logged as conical geometry only. Bloom volume and time not stated. | W75: =IF(OR(ISNUMBER(SEARCH("gesha",G75)),ISNUMBER(SEARCH("geisha",G75))),"⭐ GESHA","") | X75: 108 Robinson Rd, #01-01, Singapore 068900
A76: 46235 | B76: Singapore | C76: Fluid Collective | D76: Finca Sophia — Natural Panama Geisha | E76: Willem Boot, Kelly Hartmann & David Pohl | F76: Panama | G76: Geisha | H76: Natural | I76: Filter Roast | J76: Hario Switch (Flat-Bottom Immersion Hybrid) | K76: 15 | L76: 155 (beverage; 210g water) | M76: 1:14 (water) → 155g beverage | N76: 93°C first 2 pours → 65°C last 2 pours (Split-Temp, barista-confirmed) | O76: Unknown | P76: Option-O Lagom P64 (64mm Flat Steel Burrs) | Q76: 32 | R76: Honeysuckle | Clementine | Nectarine | Apple Candy | S76: HOT: Bright, floral and fruity with excellent clarity from the first sip. Sweet lingering taste present right from the beginning. Clementine/mandarin hits after the opening. A sudden balanced 'punch' of slight orange-type taste and honeysuckle appears then quickly fades — aromatic notes flash and disappear; lingering finish short while hot. Nothing over-extracted. MID→COOL (best window): Nectarine and apple candy become much more prominent; fruitiness rises clearly; sweetness turns sugary-syrup and lingers longer and more pleasantly. Clarity gets higher as it cools while the fruity signature stays constant — the signature of this cup. The most enjoyable and generous stage; it felt great to drink. VERDICT: JOINT #1 IN ARCHIVE — ties with Finca Sophia Torcaza Grand Reserve Washed (Entry, 14 Jul 2026). If forced to choose one, the Washed edges it — but this Natural is extremely close. Every dollar of the SGD 32 was worth it. A great coffee to start August. | T76: SPECIAL TEMPERATURE PROTOCOL — barista-confirmed by Ong Shen Choy: first 2 pours at 93°C, last 2 pours at 65°C (4-pour split-temperature architecture). This INVERTS Fluid's standard 70→90→70°C oscillation: hot opening maximises volatile aromatic extraction (honeysuckle/clementine linalool-geraniol stack), dramatically cool 65°C close protects delicate natural-process sugars from phenolic bitterness — explains the clean apple-candy sweetness with zero over-extraction. Recipe: 15g : 210g water → 155g final beverage (~1:14 water ratio). Ong Shen noted this bean is complex to brew and requires real sophistication — the precise, clean result matched. Natural process at 2,000 masl Chiriquí: sugar concentration from whole-cherry drying delivers the apple candy + syrup body in the cool phase while Geisha florals stay clarity-forward. FARM A/B COMPLETE: same farm as archive #1 (Torcaza Grand Reserve Washed, TaoTao, 14 Jul, SGD 60) — process now the isolated variable across the two best cups in the archive. Also completes the Fluid Geisha Process Trilogy: Washed (El Obraje) → Honey (Hiu Los Lajones) → Natural (Finca Sophia). Grinder and filter unchanged from prior Fluid visits (Lagom P64, Hario Switch flat-bottom). | U76: Fifth visit to Fluid Collective, Saturday 1 August 2026, ~10:20am. Payment SGD 32 via PayNow confirmed. Ong Shen Choy was on his OFF DAY but came in specifically because they were brewing the Panama Geisha — he worked the bar to brew this Limited Release himself. A SGD 32 cup, Finca Sophia, brewed personally by the 2025 Singapore National Brewers Cup Champion on his day off — a special conversation and a special cup. Menu: Alo Peaberry Washed Ethiopia SGD 10 / Magma Natural Panama Pacamara SGD 10 / Finca Sophia Natural Panama Geisha SGD 32 (Limited Release, announced on Instagram the night before). Highest-priced cup at Fluid in archive history; second-highest overall after the SGD 60 Torcaza. | V76: Live Field Audit — Fifth Visit | Bean card + menu + payment receipt | W76: =IF(OR(ISNUMBER(SEARCH("gesha",G76)),ISNUMBER(SEARCH("geisha",G76))),"⭐ GESHA","") -> ⭐ GESHA | X76: 24 Opal Cres, Singapore 328418
A77: 46239 | B77: Singapore | C77: Nylon Coffee Roasters | D77: El Romerillo | E77: Luis Abarca | F77: Peru | G77: Caturra | H77: Washed | I77: Filter Roast | J77: OREA (Flat-Bottom) | K77: Unknown | L77: Unknown | M77: 1:17 | N77: 93°C (Constant — barista-confirmed house standard) | O77: Unknown | P77: Mahlkönig EK Omnia (98mm Flat Burr) | Q77: 7.5 | R77: Blood Orange | Red Plum | Currant | Pomegranate | S77: HOT: Bright and acidic with medium body and a quickly disappearing aftertaste. Tartaric acid hit identified — read as pomegranate. MID: Plum and orange emerge slowly as the volatile citrics burn off. MID-COOL: Acidity persists, mouth-filling, malic acid dominant, clarity notably improved. COOL: Mellowed further into soft red berries — pomegranate character but lighter, like a diluted pomegranate juice. OVERALL: Quite acidic and bright for a washed coffee. Clean three-phase evolution with zero bitter tail. Strong Palate DNA alignment. | T77: CONTROLLED PAIR vs the 08 Jul 2026 La Flor de la Palma at the same café: identical grinder (EK Omnia 98mm flat), identical ratio (1:17), identical temperature (93°C), same café, same flat-bottom geometry — opposite outcome. Washed process carries minimal cherry-skin polyphenol load into the brew, so there is little chlorogenic acid lactone in solution for a lean ratio to expose; the July bitterness is therefore attributable to PROCESS, not ratio. This is the empirical confirmation of Extraction Law 3 from the opposite direction. OREA flat-bottom (barista-confirmed and visually verified by Hari) delivers wide, near-unrestricted drainage — fast draw-down, even bed saturation, minimal fines contact time — which accounts for the clarity gain registered at mid-cool. 93°C is well matched to Caturra's lower-density bean (it was conservative on the denser Bourbon in July). Acidity persisting into the cool phase rather than collapsing indicates high organic acid concentration from slow high-altitude maturation. | U77: Solo visit — 05 Aug 2026, 13:30 SGT. Sixth Nylon audit. Filter menu rotation confirmed: Colombia Juan Martin and Peru La Flor de la Palma both rotated off; current filter line is Colombia El Pinal (Liliana Gembuel Paja, Castillo/Washed, S$7.00) and Peru El Romerillo (S$7.50). Espresso line: Colombia Juan Martin (Red Striped Bourbon/Washed) and Peru Los Cedros (Caturra/Washed). Ordered on Claude's recommendation over El Pinal on Palate DNA grounds (malic/citric acid stack, washed clarity, varietal novelty). First Caturra Washed Peru in the archive; first Luis Abarca lot. Barista confirmed 1:17 and 93°C as house standard, rarely modified. Roast date deliberately NOT logged — retail bag dates disregarded per Hari's instruction as the brewed batch may differ from shelf stock. | V77: Live Field Audit — Sixth Visit | Barista confirmation (ratio 1:17, temp 93°C, OREA dripper) + Hari direct visual verification of brewer + retail bag photo (name and tasting notes only; roast date excluded per instruction) + menu board photo | W77: =IF(OR(ISNUMBER(SEARCH("gesha",G77)),ISNUMBER(SEARCH("geisha",G77))),"⭐ GESHA","") | X77: 4 Everton Park, #01-40, Singapore 080004
A78: 46240 | B78: Singapore | C78: Double Shot Coffee (Shenton Way) | D78: Ruli | E78: Unknown | F78: Rwanda — Ruli | G78: Unknown | H78: Washed | I78: Unknown | J78: OREA (Flat-Bottom, Plastic) | K78: 13 | L78: 180 | M78: 1:13.8 | N78: 92°C (Constant — barista-confirmed 90–92°C band, logged at upper end) | O78: Unknown | P78: Mahlkönig EK43 S (98mm Flat Burr) | Q78: 8 | R78: Cranberry | Stewed Apple | Caramel | S78: HOT: Cranberry immediate and unmistakable — bright, acidic, clean entry. Red fruit reads as genuine cranberry rather than generic berry, which is unusual and immediately noticeable. Washed clarity fully present from the first sip, no muddiness. MID: Brightness holds. Cranberry does not fade or hand over to a different note the way most fruit-forward washed coffees do at mid-temperature — the signal simply persists. COOL: Cranberry still present and still clear. Full three-phase thermal consistency. OVERALL: Surprised by the level of berry expression and by how stable it was hot through cold. Damn clear cup. Not bad at all — honest, direct, clean, and at S$8 a strong value proposition. Bright and acidic throughout, which suits the Palate DNA well. | T78: Mahlkönig EK43 S (barista-confirmed) carries the same 98 mm flat cast-steel burr set as the full-size EK43 in a compact body — the largest burr diameter logged in the archive alongside the EK Omnia. A 98 mm burr presents roughly 2.3× the cutting surface area of a 64 mm burr, producing a narrow particle size distribution with very low fines yield; fines are the primary driver of micro-channelling and selective over-extraction of bitter chlorogenic acid lactones, so their suppression here is what preserved the cranberry signal as a clean single line rather than a muddied red-fruit blur. OREA flat-bottom (plastic body, barista-confirmed) contributes wide unrestricted drainage and even bed saturation across a shallow uniform bed. On the ratio: 1:13.8 sits well below the 1:15–1:17 Palate DNA band and is a concentrated format, yet the cup carried no bitter tail. The reason is process chemistry — Washed processing strips the cherry skin entirely before drying, so there is minimal procyanidin and tannin load available to enter solution. A concentrated ratio therefore amplifies malic and citric acid density (perceived as cranberry brightness) without an accompanying polyphenol penalty. The thermal stability across all three phases points to high organic acid concentration from slow high-altitude maturation in Rwanda's volcanic highlands, where cool nights extend the cherry ripening cycle and drive acid accumulation. | U78: Solo visit — 06 Aug 2026, 13:30 SGT, Thursday lunchtime. Double Shot Coffee Shenton Way branch — a separate venue from the Kampong Bahru outlet already in the archive; same chain, different location, logged as a distinct café per archive branch convention. Filter menu offered three pour overs: Rwanda Ruli Washed S$8 (ordered), Colombia La Quebraditas D.A. Washed S$14, and Ethiopia Alo Mosto 96 Hours S$15; iced brew also listed at S$6.50. Barista confirmed all brew parameters directly: Mahlkönig EK43 S grinder, OREA flat-bottom plastic dripper, 13 g dose to 180 g water, temperature held constant in the 90–92°C band (logged at the 92°C upper end per Hari). Barista also mentioned the café sells single-origin drip bags — noted as a potential home-brew purchase, which would allow this lot to be re-brewed at the preferred 1:15–1:17 band. Venue sits in Eon Shenton, the same building as Abseil (#01-14). Small unit, largely outdoor bench seating. Roast level not stated on menu or by barista. Varietal not stated on menu or by barista — logged Unknown rather than inferred. | V78: Live Field Audit — Menu board photo (origin, lot name, process, price, tasting notes) + barista confirmation (grinder EK43 S, OREA flat-bottom plastic dripper, 13 g dose, 180 g yield, 90–92°C) + Google Places address verification | W78: =IF(OR(ISNUMBER(SEARCH("gesha",G78)),ISNUMBER(SEARCH("geisha",G78))),"⭐ GESHA","") | X78: 70 Shenton Way, #01-05, Eon Shenton, Singapore 079118
A79: 46241 | B79: Singapore | C79: Kōhī Roastery + Coffee Bar | D79: Rwenzori Kisinga | E79: Unknown | F79: Uganda — Rwenzori Kisinga | G79: SL14, SL28 | H79: Natural | I79: Light-Medium (dual-purpose espresso/filter lot — barista-confirmed) | J79: Hario V60 Pour-over (Conical percolation) | K79: 15 | L79: 240 | M79: 1:16 | N79: 92°C (Constant — barista-confirmed) | O79: Unknown | P79: Mahlkönig EK43 S (98mm Flat Burr) | Q79: 8.5 | R79: Stone Fruit | Mixed Berries | Pink Pomelo | S79: Rated average to above-average — not bad, not excellent, and fair value at S$8.50. HOT: bright entry, stone fruit and berries reading clearly and cleanly; medium body as expected of a Natural. MID-COOL: berry dominates, strawberry specifically; a slight bitter aftertaste emerges — mild, non-escalating, and barista-confirmed as the INTENDED pink pomelo / bitter-orange character, a consequence of this lot being roasted light-to-mid so it can serve espresso as well as filter. All three roaster notes therefore confirmed on the palate. COOL: still fruity but less intense than before — the cup fades rather than evolves; no new sugar layer emerges. Clarity is compromised by fruit density: stone fruit and strawberry overlap rather than separate, making individual notes tricky to resolve — Hari's own summary was 'in one word, fruity'. Natural processing is unmistakable here and clearly differentiated from washed. FIRST UGANDA ORIGIN IN ARCHIVE (country #15) and first Natural-process SL28 in the archive. Worth logging for the origin; would not reorder. Barista friendly and knowledgeable (name not captured — archive gap). Monday morning Gesha pop-up flagged for return visit. | T79: Hario V60 conical percolation at 92°C and 1:16 (15g / 240g, barista-confirmed), ground on a Mahlkönig EK43 S 98mm flat burr set — the near-unimodal particle distribution starved the fines migration that has driven the over-extraction flag in prior conical entries (Agora Beloya, Kurasu Rwanda, PPP Suke Quto), so the bitter-citrus present here is ROAST INTENT, not extraction fault: it stayed mild and stable across all three thermal phases rather than sharpening. Fourth conical entry to show a bitter tail and the first to keep it slight — evidence that the conical over-extraction penalty scales with the grinder's fines population, not with geometry alone. 1:16 sat mid-band of the 1:15–1:17 Palate DNA window, correct for a high-solubles Natural. Separately, the Natural process layer overwrote the SL28 phosphoric acid spine entirely, delivering fruit density at the cost of the note separation the same genetics show washed (cf. Kenya Nyeri Hill, Kiamugumo AA). | U79: Solo visit — 07 Aug 2026, ~13:40 SGT, Friday lunchtime. First visit to Kōhī Roastery + Coffee Bar; venue #40 in the archive. Filter menu was four lots, ALL Natural process (Uganda Rwenzori Kisinga S$8.50 · Ethiopia Sidamo Guji Harsu G1 S$8.50 · Costa Rica Aquiares Estate Entre Rios S$8.50 · Peru Finca Los Santos Gesha S$12.00; iced option +S$1). Espresso bar running Honduras Guara Verde and Ethiopia Sidama G2. Uganda selected as a country-novelty audit. Hario Switch also available on bar but NOT used for this lot — barista selected standard V60 percolation. Barista noted as friendly and knowledgeable; name not recorded (archive gap). Kōhī runs a Monday morning Gesha pop-up with multiple Gesha varieties — flagged as high-priority return. OUTLET NOT CONFIRMED: Kōhī operates two Singapore coffee bars. | V79: Live Field Audit — First Visit | Bean card photo (origin, varietal SL14/SL28, process, tasting notes) + filter menu board photo (price S$8.50) + barista confirmation (ratio 1:16 = 15g dose / 240g yield, 92°C, Mahlkönig EK43 S, Hario V60 standard percolation, dual-purpose espresso/filter roast intent behind the bitter-citrus finish) | W79: =IF(OR(ISNUMBER(SEARCH("gesha",G79)),ISNUMBER(SEARCH("geisha",G79))),"⭐ GESHA","") | X79: Unknown — outlet not confirmed. Kōhī SG coffee bars: 5 Shenton Way, #01-01 UIC Building, S068808 · 432 Joo Chiat Rd, S427647
A80: 46243 | B80: Singapore | C80: Fluid Collective | D80: Berlina — Washed Panama Geisha | E80: Casa Ruiz | F80: Panama | G80: Geisha | H80: Washed | I80: Filter Roast | J80: Hario Switch (Flat-Bottom Immersion Hybrid) | K80: 15 | L80: 225 | M80: 1:15 | N80: 70 → 90 → 70°C (Thermal Oscillation Protocol — Fluid Standard) | O80: Unknown | P80: Option-O Lagom P64 (64mm Flat Steel Burrs) | Q80: 9 | R80: Nectarine | Orange | Jasmine Tea | S80: HOT: Bright and clean — orange and nectarine hit together, immediate and simultaneous. High clarity from the first sip; the washed character is unmistakable. MID-COOL: Body thins into a tea-like structure. Diluted orange juice character with hints of nectarine underneath. Clarity holds as body drops. COOL: Sweet and still fruity. Nectarine returns clearly and cleanly — 'like sweet nectarine, and I love to drink as much as possible when it's cool.' VERDICT: Overall a great one. Thoroughly enjoyed. Cool phase is the reward window. | T80: Casa Ruiz (Boquete, Chiriquí) washed Geisha at 13 days rest — brewed batch roasted 27 Jul 2026, barista-confirmed. NOTE: the retail bag on shelf showed 3 Aug — a different lot. Retail roast dates are never logged; only the barista-confirmed brewed batch. 13 days sits one day inside Fluid's stated 14-day optimal rest, so degassing complete and aromatics fully developed. Washed processing delivers orange and nectarine SIMULTANEOUSLY rather than sequentially — no fermentation layer to stagger arrival. Hari identified the washed character in-cup before confirming the process. Jasmine tea note expresses structurally as a thinning tea-like body in the mid-cool phase rather than as discrete flavour. Cool-phase nectarine return (malic re-emergence as volatiles dissipate) now confirmed across Gara Agena, Alo Peaberry and Berlina — three consecutive washed cups behaving identically. VALUE FINDING: at SGD 9 this is the cheapest Gesha/Geisha in the entire archive, undercutting Apartment Selegie (S$9.50) — and the cheapest Panama Geisha by a wide margin (vs S$60 Finca Sophia Torcaza Washed, S$32 Finca Sophia Natural, S$14 Hiu Los Lajones Honey). Hardware and 70→90→70°C protocol unchanged from prior Fluid visits. | U80: Fluid Collective visit, Sunday 9 August 2026, 16:00 — visited WITH AANYA (her second archive appearance after Finca La Siberia at Narrative, March 2026). First of two filters this session (S$18 total, S$9 each). Ong Shen Choy — 2025 Singapore National Brewers Cup Champion — on the bar. The barista mentioned she reads Hari's Google reviews of Fluid and likes them — the archive reaching the people it documents. Crispiliano Natural Panama Geisha (S$32) was on bar and deliberately declined: spend discipline after S$60 + S$32 on Geisha within the prior 26 days. Berlina 200g retail also purchased. | V80: Live Field Audit — with Aanya | Bean card + retail bag photo | W80: =IF(OR(ISNUMBER(SEARCH("gesha",G80)),ISNUMBER(SEARCH("geisha",G80))),"⭐ GESHA","") -> ⭐ GESHA | X80: 24 Opal Cres, Singapore 328418
A81: 46243 | B81: Singapore | C81: Fluid Collective | D81: Rosa Marina — Washed Nicaragua | E81: Finca La Lima | F81: Nicaragua | G81: Red Catuai | H81: Washed | I81: Filter Roast | J81: Hario Switch (Flat-Bottom Immersion Hybrid) | K81: 15 | L81: 225 | M81: 1:15 | N81: 70 → 90 → 70°C (Thermal Oscillation Protocol — Fluid Standard) | O81: Unknown | P81: Option-O Lagom P64 (64mm Flat Steel Burrs) | Q81: 9 | R81: Orange | Raisin | Hawthorn | S81: HOT: Clear and clean. Orange PEEL hit — rind and pith character, not just juice — arriving alongside a distinct grape note. Everything landing at once. MID-COOL: Clarity climbs further. Orange shifts from lead to backdrop and a light sweet aftertaste begins to appear. COOL: Nice and relaxed. Orange becomes more apparent again — the cup completes a full circle. Ends with a light sugar finish and a developing aftertaste. VERDICT: I love this coffee. Amazing. | T81: FIRST NICARAGUAN FILTER IN THE ARCHIVE — both prior Nicaragua entries (Finca La Virgen, Buena Vista) were espresso format; this closes a genuine origin gap. Red Catuai (Bourbon × Mundo Novo hybrid) under washed processing at Finca La Lima: compact high-yield varietal delivering clean citric structure with dried-fruit sweetness beneath. Orange peel read — limonene plus rind bitterness registering as structure, not defect — is a more precise capture than plain orange; Hari identified the pith character specifically. Grape in the hot phase is the raisin note in pre-concentration form; as the cup cools the sugars consolidate and the light sugar finish emerges. NOTABLE THERMAL BEHAVIOUR: orange RETURNS in the cool phase rather than being replaced — a circular arc, distinct from the washed Geishas where nectarine displaces the opening note. New pattern for the archive. Hawthorn (floral-herbal, subtle) not separately identified in cup. Last remaining box at Fluid — unlikely to recur. Hardware and protocol unchanged. | U81: Fluid Collective visit, Sunday 9 August 2026, 16:00 — visited WITH AANYA. Second of two filters this session (S$18 total, S$9 each). Ordered after the Berlina; barista flagged this as the LAST REMAINING BOX of Rosa Marina. Chosen deliberately over the Crispiliano Natural Panama Geisha (S$32) — scarcity of an unrepresented origin format ranked above a fourth Panama Geisha in under a month. Ong Shen Choy on the bar. Barista noted she reads and likes Hari's Google reviews of Fluid. | V81: Live Field Audit — with Aanya | Bean card photo | W81: =IF(OR(ISNUMBER(SEARCH("gesha",G81)),ISNUMBER(SEARCH("geisha",G81))),"⭐ GESHA","") | X81: 24 Opal Cres, Singapore 328418
A82: 46246 | B82: Singapore | C82: Grey Area Coffee Roasters | D82: La Papaya TM | E82: Hacienda La Papaya (Juan Peña) | F82: Loja, Ecuador | G82: Typica Mejorado | H82: Unknown — not stated on menu board or by barista; farm releases TM in Washed, Natural, Anaerobic Washed and Yeast-Inoculated Washed. Pending café confirmation. | I82: Unknown | J82: Solo Dripper by Mazelab (Flat-Bottom, 40° angle, Wave filter, PCTG plastic) + in-cup bypass | K82: 15 | L82: Unknown — dripper removed and bypass water added in-cup, volume not captured | M82: 1:13.3 through-bed (200g) + unquantified in-cup bypass — final ratio Unknown | N82: Unknown | O82: 58.7g first pour (1:3.9) — saturating pour, not a degassing bloom | P82: Mahlkönig EK43S (98mm Flat Burr) | Q82: 9.5 | R82: Apricot | Red Apple | S82: HOT: Bright and acidic — apple and apricot arrived together and competed for space, neither resolving. MID-COOL: Stewed apple became the dominant impression; apricot receded to a light, juice-like presence. COOL: Apricot took over the cup outright. Overall very good — reads like apple juice at points. No bitterness at any thermal phase despite the sub-band through-bed ratio. INVERSE THERMAL SEQUENCE vs Entry #034 (Ecuador La Papaya Geisha Washed, Pocket by Flip, 19 May 2026): that cup ran apricot-first then malic apple on cooling; this one ran apple-forward then apricot on cooling. Same farm, same descriptor pair, reversed thermal order. No thymol terpene coat and no floral top note — Typica Mejorado has no terpene pathway, so this is a pure malic/lactone architecture. | T82: SECOND HACIENDA LA PAPAYA ENTRY AND FIRST NON-GESHA LOT FROM THE FARM — enables a varietal delta (Typica Mejorado vs Geisha) against Entry #034 with producer, terroir and altitude band held constant. THIRD SOLO DRIPPER ENTRY IN THE ARCHIVE (after #062 and #067, both Pour.traits Roasters) AND THE FIRST OUTSIDE POUR.TRAITS — all three ran the same Mahlkönig EK43S 98mm flat burrs, so brewer and grinder are held constant and RATIO ARCHITECTURE is the isolated variable: #062 and #067 both ran a straight ~1:15, this one ran 1:13.3 through-bed plus in-cup bypass. SOLO GEOMETRY (Mazelab, designed by Jackie Tran, Czech Republic Brewers Cup Champion 2024): 40 degree wall angle, curved base, single large central hole, FLAT wave-filter bed, PCTG plastic. Barista-stated selection rationale — she wanted water to travel OUTWARDS across the bed rather than converge, and reserves the V60 for iced service. Flat bed gives uniform path length across the full diameter, structurally avoiding the conical fines-drain over-extraction signature (Law 1). PCTG is thermally near-neutral — no heat-sink behaviour vs stainless (Law 7). CONCENTRATE-PLUS-BYPASS ARCHITECTURE: 200g through the bed on a 15g dose (1:13.3), then dripper and filter removed and hot water added directly to the cup. This decouples extraction yield (set by through-bed water plus the Solo's fast drain) from final TDS (set by bypass volume) — and is why a sub-band 1:13.3 produced NO polyphenolic cool-phase bitterness, QUALIFYING LAW 2. Opening pour of 58.7g (1:3.9) is a saturating first pour, not a degassing bloom. | U82: Solo visit — Grey Area Coffee Roasters, 12 Aug 2026, ~13:00 SGT, Wednesday lunchtime. First visit; venue #41 in the archive. Busy lunch service — water temperature and final cup weight not captured, logged as honest nulls rather than estimated. Café founded by Xiang Sheng and Luke, both ex-Alchemist Coffee; Luke roasts in-house. Selected from a five-strong filter board (Nano Challa 8.5 / La Papaya TM 9.5 / La Papaya B7 10.0 / Emerson Filipe 8.0 / Los Rodriguez 10.5) on clarity grounds — TM chosen for the same-farm varietal delta against Entry #034. | V82: Live Field Audit — First Visit | Menu board photo (filter list + prices) + brew-in-progress photo (Solo Dripper with wave filter) + grinder photo (Mahlkönig) | Hari-stated hardware: EK43S grinder, Solo Dripper 40 degree, plastic | Barista-stated brewer selection rationale | Pour weights recorded live (58.7 / 140 / 200 cumulative) | PROCESS NOT STATED on board or by barista — pending café confirmation | W82: =IF(OR(ISNUMBER(SEARCH("gesha",G82)),ISNUMBER(SEARCH("geisha",G82))),"⭐ GESHA","") | X82: 13 Kampong Bahru Rd, Singapore 169345
A83: 46249 | B83: Singapore | C83: Suzuki Cafe & Roastery | D83: 117 Jairo Arcila Gesha Natural EF2 | E83: Finca Santa Mónica — Jairo Arcila & family (Cofinet) | F83: Quindío, Colombia | G83: Gesha | H83: Extended Dry Anaerobic Natural (EF2) — two-stage: 24h dry aerobic ferment, then ~50h sealed in GrainPro below 22°C, then slow raised-bed drying to 11% moisture | I83: Light | J83: Hario V60 Glass 02 (Conical, 60°, single central aperture, olive wood collar) — glass body | K83: 15 | L83: 225 | M83: 1:15 | N83: 92 | O83: Unknown | P83: Mahlkönig EK43S (98mm Flat Burr) | Q83: 13 | R83: Lychee | Raspberries | Honey | S83: HOT: High acidity, bright and fruity; floral character present; anaerobic ferment detectable but subordinate — nothing dominates the cup. Honey sweetness rises within the first few sips. HOT-MID: Syrupy texture develops, berry emerging, turning steadily. MID-COOL: Berries clarify and lead — sits on the fruity axis rather than floral, despite the barista calling it floral. Enjoyed it despite being a Natural; brew parameters worked. COOL: Mellows to a honey-sweet finish, nice medium body, light residual sourness. Strong sweet-sour aftertaste reading as sweet orange or sweet strawberry — lingered so long it persisted into the next cup. ZERO cool-phase bitterness: first Natural-family Gesha in the archive to avoid the polyphenol penalty. Lychee not detected. Upper-tier entry and the best Gesha value in the archive at S$13. | T83: FIRST V60 CONICAL ENTRY WITHOUT OVER-EXTRACTION — EK43S 98mm flat burrs produced a PSD tight enough that the conical fines-migration failure mode never activated (cf. Entry #031 Kurasu, Entry #044 PPP Funan). RATIO OUTRANKS GEOMETRY: 1:15 at 92°C suppressed Extended Dry Anaerobic polyphenols below palate threshold, where Entry #058 (Double Shot, Kotowa Natural Gesha) failed at 1:13.3 on superior flat-bottom geometry with tighter Ditting burrs — isolating brew ratio, not brewer geometry, as the controlling variable for Natural-process cool-phase bitterness. Light roast preserved malic acid; the EF2 two-stage cold-held ferment kept fermentation subordinate to varietal expression. Glass brewer body = fourth material datapoint on Extraction Law 7 (after plastic, ceramic, stainless). | U83: Solo visit — Suzuki Cafe & Roastery, 15 Aug 2026, Saturday late morning, first cup of a two-cup session. First visit; venue #42 in the archive. Boon Lay industrial estate, Kyoto-teahouse interior with indoor shishi-odoshi. Café packed at peak weekend rush; barista conversation limited by service volume. Barista confirmed 1:15 ratio, 92°C and Hario dripper; recommended this lot and described it as the more floral of the two (palate disagreed — see verdict). House flavour map plotted 117 in the Fruity quadrant, matching the palate reading over the barista testimony. | V83: Live Field Audit — First Visit | Barista-confirmed ratio, temperature and brewer | Bean card + wall card + retail bag photographed (varietal, altitude, process, EF2 designation, roast/intensity/acidity scores) | Dripper identified from direct photographs | Price from menu board | W83: =IF(OR(ISNUMBER(SEARCH("gesha",G83)),ISNUMBER(SEARCH("geisha",G83))),"⭐ GESHA","") -> ⭐ GESHA | X83: 8 Chin Bee Ave, Singapore 619932
A84: 46249 | B84: Singapore | C84: Suzuki Cafe & Roastery | D84: 119 Gargari Gutity | E84: Gargari Gutiti Washing Station — Banko kebele smallholders | F84: Gedeb, Gedeo Zone, Ethiopia | G84: Ethiopia Heirloom | H84: Supernatural (Extended Aerobic Natural) — thick-layer drying in a semi-permeable chamber with restricted sunlight and limited airflow; extended drying time increases fermentation of latent sugars; temperature, Brix and moisture monitored to ~12.5% | I84: Light | J84: Hario V60 Glass 02 (Conical, 60°, single central aperture, olive wood collar) — glass body | K84: 15 | L84: 225 | M84: 1:15 | N84: 92 | O84: Unknown | P84: Mahlkönig EK43S (98mm Flat Burr) | Q84: 8.5 | R84: Pineapple | Marmalade | Black Tea | S84: HOT: Very acidic and bright; tea-floral character leads; medium body; orange marmalade immediate and unmistakable — a clear citrus hit. HOT-MID: Unripe pineapple emerges — tropical ester family, not stone fruit. MID: Citrus and orange marmalade dominant; floral and fruit interleaved rather than one dominating; complex and layered — "a very complicated coffee with floral and fruit mixed together". COOL: Syrupy; sweet orange, pineapple and marmalade integrate; tea structure holds; decent and mellow, a slow-sipping tea-coffee that improves as it cools. All three official notes confirmed. Rated EQUAL to Entry #082 Gesha. No over-extraction — parameters judged built to perfection. Softened the stance on Natural process: syrupy and enjoyable, distinctly different from the washed cohort. | T84: ARCHIVE-DEFINING SESSION FINDING — AEROBIC vs ANAEROBIC ISOLATION: brewed on identical hardware, ratio, temperature and day as Entry #082, isolating fermentation architecture as the sole variable. The sealed anaerobic EF2 (#082) masked varietal and floral expression under berry esters; this open aerobic extended drying preserved florals, citrus and tea structure with fruit in support. Third same-session confirmation that 1:15 at 92°C suppresses extended-ferment polyphenols on V60 conical geometry when paired with 98mm flat burrs. ETHIOPIAN TERROIR CONSTANT CONFIRMED: orange/citrus now spans Guji, Sidamo and Gedeo zones across Washed, Natural and Supernatural processing — hypothesis promoted to established finding. WHITE PEACH ABSENT, supporting Guji-specificity rather than a pan-Ethiopian or JARC-lineage fingerprint. Station-level records indicate the Gargari Gutiti smallholder population is JARC 74110/7412/74165 — logged as Heirloom per bean card (source hierarchy). | U84: Solo visit — Suzuki Cafe & Roastery, 15 Aug 2026, Saturday, second cup of a two-cup session. Palate reset compromised: nut-and-raisin rye bread consumed between cups, plus a long-lingering sweet-orange aftertaste carried over from Entry #082 — hot-phase reading treated as provisional at the time. Reading subsequently accepted as CLEAN: orange marmalade appeared hot, persisted through mid and was still present at cool; a residue artifact would have faded rather than intensified. TWO-CUP CONSISTENCY FINDING: two different origins and two different processing architectures, brewed back to back during peak weekend rush, both landing clean — evidence of a systematic house recipe rather than a single lucky cup. | V84: Live Field Audit — First Visit | Barista-confirmed ratio, temperature and brewer | Bean card photographed (varietal, altitude 1,983 m.a.s.l., Supernatural process, Light roast, intensity 2.5/5, acidity 4.5/5 — highest on the house board) | Process mechanism from station documentation | Price from menu board | W84: =IF(OR(ISNUMBER(SEARCH("gesha",G84)),ISNUMBER(SEARCH("geisha",G84))),"⭐ GESHA","") | X84: 8 Chin Bee Ave, Singapore 619932
A85: 46256 | B85: Johor Bahru | C85: Sweet Blossom Coffee Roasters | D85: AB Mwirua Getuya #006 | E85: Unknown — AB is a screen-size grade, not an estate; washing station not stated on bean card or by barista | F85: Kenya | G85: SL28 & SL34, Batian, Ruiru 11 | H85: Washed | I85: Unknown — not stated on bean card or by barista | J85: Hario — ceramic conical wall with spiral ribs and a FLAT RECESSED FOUR-HOLE BASE PLATE (multi-aperture restricted base, not a single central aperture); model Unknown | K85: 15 | L85: 240 | M85: 1:16 | N85: 93 | O85: Unknown — four-pour structure barista-confirmed; individual pour weights not captured | P85: Mahlkönig EK43 (98mm Flat Burr) | Q85: 6.98 | R85: Currants | Rosehip | Brown Sugar | Strawberry Tea | S85: HOT: Bright and properly acidic; currants immediate and running the full length of the cup. MID: Berries opening out while clarity holds — no loss of definition as the profile moves from acid-led to fruit-led; brightness undiminished. COOL: Brown sugar arrives exactly on cue and resolves cleanly, with a quiet berry aftertaste persisting underneath and brightness still intact. No cool-phase bitterness at any point. The house card's three-phase prediction verified in all three bands. Preferred cup of the two-cup session. | T85: HOUSE CARD THERMAL PREDICTION VERIFIED — FIRST ARCHIVE INSTANCE. Sweet Blossom's bean card commits to a falsifiable three-phase arc (currants/rosehip hot, aromatic brown sugar as it cools, strawberry-tea aftertaste) and the cup matched it in all three phases. Elevates the printed bean card above generic menu descriptors in the source hierarchy for this venue. VARIETAL COMPOSITION: AB denotes screen size, not varietal. This lot blends SL28 & SL34 with Batian and Ruiru 11 — the modern disease-resistant Kenyan cultivars — which typically round the sharp linear phosphoric-malic attack of pure SL selections. The currant-led rather than piercing-blackcurrant profile is consistent with that dilution and is the likely explanation for the unusually smooth acid delivery. HARDWARE: EK43 98mm flats at 1:16 / 93°C across four pours. The brewer is the notable variable — a ceramic conical-wall cone terminating in a flat recessed base plate with FOUR discrete holes rather than the single wide aperture of a V60. Four separated exits cap maximum flow rate independent of grind size, so the documented V60 apex-choke failure mode (Entries #031, #044 — fines migrating to a single outlet and over-extracting) is structurally unavailable on this geometry. First archive entry on a multi-aperture restricted-base cone; behaviourally closer to Kalita Wave contact-time dominance than to V60 percolation despite the conical wall. | U85: Day trip to Johor Bahru with Anusha, 22 Aug 2026. Second stop of six; arrived 13:37 by Grab from Komtar JBCC, departed 14:38 — 61 minutes at the bar. First cup of a deliberate two-cup controlled comparison (Washed vs Anaerobic Washed) on identical grinder, ratio, temperature, brewer and barista. Coffee-only venue — no food, no pastries, no distraction. Baristas: Grace, plus a second barista whose name was not captured (the visit's one data regret) who brewed both cups and argued the case for the Indonesian lot on its merits. Green sack wall observed and photographed: Nordic Approach (Sítio Cachoeira #4, Rodrigo Pereira, NORDIC29, Red Catuaí, Brazil), Café Tuxpal El Salvador El Condor Bourbon FW, Pirineos washed, plus Colombia and Brazil lots. Untried on the filter list: Colectivo Cedrobamba Peru natural RM20, Santa Rosa P50 El Salvador Pacamara honey RM23, Maguta Kenya nitrogen-flushed natural Lot L2 RM30 (resting). | V85: Live Field Audit — First Visit | Barista-confirmed grinder, dose, yield, ratio, temperature and pour count | Bean card photographed (varietal, process, three-phase house notes) | Filter menu photographed (RM22) | Brewer and grinder photographed — four-hole base plate clearly visible; model not identified and logged Unknown per no-inference rule | Payment RM43 for both cups, NETS debit S$13.93 @ 0.323869 | Archive price converted at the standing 1 SGD = 3.15 MYR reference rate | W85: =IF(OR(ISNUMBER(SEARCH("gesha",G85)),ISNUMBER(SEARCH("geisha",G85))),"⭐ GESHA","") | X85: 28 Jalan Maju, Taman Pelangi, 80400 Johor Bahru, Johor, Malaysia
A86: 46256 | B86: Johor Bahru | C86: Sweet Blossom Coffee Roasters | D86: Cibeureum Lot 41 | E86: Unknown — lot 41, Cibeureum; producer and washing station not stated on menu or by barista | F86: Indonesia — sub-region not stated | G86: Mixed varietals — not specified on menu or by barista | H86: Anaerobic Washed | I86: Unknown — not stated on menu or by barista | J86: Hario — ceramic conical wall with spiral ribs and a FLAT RECESSED FOUR-HOLE BASE PLATE (multi-aperture restricted base, not a single central aperture); model Unknown | K86: 15 | L86: 240 | M86: 1:16 | N86: 93 | O86: Unknown — four-pour structure barista-confirmed; individual pour weights not captured | P86: Mahlkönig EK43 (98mm Flat Burr) | Q86: 6.67 | R86: Red Grapes | Hibiscus | Water Chestnut | S86: HOT: Bright, with the washed base clearly legible beneath the ferment — process character reads first, fermentation second. MID: A little funky as the anaerobic layer asserts itself, but contained and never muddy; a clear mandarin orange note comes through the middle. COOL: Brightness holds; ferment expresses as lift and texture rather than as jam or wine. No cool-phase bitterness. Good cup, but the Kenya was the better of the two. | T86: CONTROLLED FERMENTATION ISOLATION — SECOND OF TWO CUPS, SINGLE VARIABLE MOVED. Identical grinder (EK43 98mm flat), ratio (1:16), temperature (93°C), pour count (4), brewer geometry and barista as Entry #084; only the process differs — Washed vs Anaerobic Washed. RESULT: the washed base remained legible underneath the ferment, and the fermentation expressed as controlled funk and aromatic lift rather than as ester masking. This is a materially different outcome from the sealed-anaerobic-on-natural EF2 result at Suzuki (Entry #082), where the ferment buried varietal and floral expression under berry esters. WORKING CONCLUSION: anaerobic fermentation applied over a WASHED base is substantially less occlusive than the same fermentation applied over a NATURAL base — mucilage removed prior to sealing appears to cap the ester load available to the ferment. This refines Law 9 (fermentation architecture governs varietal expression) by identifying the pre-ferment substrate, not merely the vessel, as a controlling term. DIVERGENCE FROM HOUSE CARD: the card claimed red grapes, hibiscus and water chestnut; the cup delivered mandarin orange as the dominant fruit descriptor. Unlike Entry #084 the card did not predict this cup — card reliability at this venue is therefore process-dependent, strong on washed and weaker on fermented lots. RATIO: 1:16 sits mid-band of the 1:15–1:17 Palate DNA window and well clear of the ≤1:14 concentration threshold at which fermented lots have historically failed in this archive. | U86: Day trip to Johor Bahru with Anusha, 22 Aug 2026. Second cup of a two-cup session at Sweet Blossom, same date, venue, hardware and barista as Entry #084. Ordered second by design so that ferment esters could not contaminate the washed reference cup; approximately 15 minutes and a water reset between cups. Brewed by the second barista (name not captured), who had recommended this lot unprompted and made a substantive case for Indonesian coffee generally. | V86: Live Field Audit — First Visit | Barista-confirmed grinder, dose, yield, ratio, temperature and pour count | Filter menu photographed (lot name, origin, process, house notes, RM21) | Brewer and grinder photographed; model not identified and logged Unknown per no-inference rule | Payment RM43 for both cups, NETS debit S$13.93 @ 0.323869 | Archive price converted at the standing 1 SGD = 3.15 MYR reference rate | W86: =IF(OR(ISNUMBER(SEARCH("gesha",G86)),ISNUMBER(SEARCH("geisha",G86))),"⭐ GESHA","") | X86: 28 Jalan Maju, Taman Pelangi, 80400 Johor Bahru, Johor, Malaysia
A87: 46256 | B87: Johor Bahru | C87: August Drip Coffee | D87: La Mariposa — Panama Boquete | E87: Unknown — "La Mariposa" is a blended Boquete lot; producing farm not stated on bean card or by barista | F87: Boquete, Panama | G87: Gesha (70%) & Typica (30%) — BLEND, not a single-varietal lot | H87: Anaerobic Natural | I87: Unknown — no roast badge on the bean card photographed; venue roasts predominantly light but not confirmed for this lot | J87: Switch dripper — full immersion with valve-controlled release; non-Hario (Chinese-made unit; house Hario switches failed repeatedly), model Unknown | K87: Unknown — not stated by barista | L87: Unknown — served in glass carafe; brew-water charge 210–215 g confirmed, final beverage yield not measured | M87: Unknown — dose not stated; water charge 210–215 g confirmed | N87: 95 | O87: N/A — no bloom phase in this protocol; single 20-second charge poured with the valve CLOSED, then undisturbed full immersion to 2:50 | P87: Mahlkönig EK43S (98mm Flat Burr) — setting #7 | Q87: 11.75 | R87: Floral Fragrance | Citrus | Apple | Plum | S87: HOT: Floral on the nose and immediately into orange and lime; bright, high clarity, unmistakably tea-like in body. MID: Apple emerging as temperature drops, fruit sweetness broadening without any loss of definition. COOL: Citrus and fruit holding to the final sip — no decay, no thinning, no cool-phase bitterness; intensity essentially flat across the thermal range rather than declining. NOT DETECTED: berry, jam, wine or solvent character. For a sealed anaerobic natural on a Gesha-dominant lot the ferment left almost no fingerprint. Among the strongest cups in the archive. | T87: ARCHIVE-DEFINING METHOD ENTRY — FIRST FULL-IMMERSION SWITCH PROTOCOL LOGGED. House method confirmed directly by co-owner and barista Pei: 95°C water, EK43S setting #7 (fine), valve CLOSED, the entire 210–215 ml charge delivered in a SINGLE POUR OF 20 SECONDS with no pulsing, circling or agitation, undisturbed full immersion until 2:50, then valve opened for a single drawdown. Pour time was originally field-recorded as "30 seconds or less" and subsequently corrected to 20 s by Pei on 23 Aug 2026 — barista confirmation overrides field recall. CANDIDATE EXTRACTION LAW 10 — IMMERSION DECOUPLES GRIND SIZE FROM FLOW RATE: in percolation, grind governs surface area and drawdown rate simultaneously, so extraction yield cannot be pursued without paying in flow; with the valve shut there is no flow to choke, and fineness can be pushed to a level that would trigger apex choke in a conical cone. EK43S #7 would be reckless in a V60 and is unremarkable here. Two supporting mechanisms: (i) a static column cannot compact, so channelling and fines migration are structurally unavailable rather than merely avoided; (ii) colloids and lipids remain in suspension for the full steep instead of being progressively stripped and filtered by continuous flow — the origin of the body Pei explicitly optimises for. SYSTEM DESIGN NOTE: removing pour rate, pour pattern, agitation and pulse timing leaves only grind, temperature, water mass and a clock — variables that can be handed to a barista on a first shift. Applied team-wide with per-lot tuning only; a protocol engineered for cross-barista consistency rather than individual virtuosity. FERMENTATION FINDING — consistent with Entry #085 and contrary to Entry #082: anaerobic ferment failed to mask varietal expression, with orange and lime leading and no berry or wine register at any temperature. VARIETAL CAVEAT: this is a 70/30 Gesha-Typica blend, so varietal attribution is partial and the Typica fraction may account for some of the body and the mid-phase apple. Gesha_Alert fires on Gesha-dominant composition; the blend is flagged explicitly here to prevent downstream analysis reading it as a single-varietal Gesha lot. ORANGE/CITRUS CROSS-TERROIR NOTE: orange appears again here, now outside Ethiopia — open question whether this is a Gesha genetic marker rather than an Ethiopian terroir constant. | U87: Day trip to Johor Bahru with Anusha, 22 Aug 2026. Sixth and final stop of the day; arrived 19:27 by Grab from Bangkok Spa, departed 20:48 — 81 minutes on site. Venue deliberately scheduled last because it trades until 22:00. Asked whether the bar carried any Gesha and was shown MORE THAN TEN distinct Gesha lots, predominantly anaerobic — the deepest single-venue Gesha bench encountered in the archive to date. Approximately 45 minutes in conversation with co-owner and barista Pei, who shared the full house brewing protocol unprompted, reviewed the Hari Coffee Archive spreadsheet, and exchanged contact details; common ground on whisky, and she knows Homeground. Added to the barista leaderboard alongside Jason (Prodigal), Ong Shen Choy (Fluid Collective) and Elysia Tan (Homeground). Also consumed: Bite Me Brownie (78% dark chocolate, mousse layer) RM17.90 and banana chocolate pound cake RM12.90, both rated highly — patisserie quality matches the coffee programme. Seven retail drip bags purchased on departure for RM52.20 (invoice T01-013385). Venue named default Johor Bahru destination going forward; return planned for a morning visit to allow multiple cups. | V87: Live Field Audit — First Visit | Full brewing protocol barista-confirmed direct from co-owner Pei (temperature, grinder setting, water charge, pour duration, steep time, valve sequence), with pour time corrected by her from 30 s to 20 s in follow-up 23 Aug 2026 | Bean card photographed (grade SHB, variety, altitude 1600–1700 m, process, 70/30 blend composition, house notes) | Itemised invoice T01-013384, JIA Coffee House Sdn Bhd (Reg 1221078W), 211 Jalan Dato Sulaiman, RM81.80 total with the cup at RM37 | Brewer confirmed by Pei as a non-Hario switch-type immersion dripper; model not identified and logged Unknown per no-inference rule | Archive price converted at the standing 1 SGD = 3.15 MYR reference rate | W87: =IF(OR(ISNUMBER(SEARCH("gesha",G87)),ISNUMBER(SEARCH("geisha",G87))),"⭐ GESHA","") -> ⭐ GESHA | X87: 211 Jalan Dato Sulaiman, Taman Abad, 80250 Johor Bahru, Johor, Malaysia
A88: 46259 | B88: Singapore | C88: Pocket by Flip (Flip Coffee Roasters) | D88: Wilder Garcia — Peru Geisha | E88: Wilder Garcia | F88: Jaen, Cajamarca, Peru | G88: Geisha | H88: Washed | I88: Unknown — not stated on bean card or by barista | J88: Hario V60 — ceramic conical (matte black) over glass server; cone PREHEATED and paper filter rinsed (barista-confirmed); bloom + 3 subsequent pours (4 pours total); model number Unknown | K88: 15 | L88: 225 | M88: 1:15 | N88: 71 → 92 (ascending two-stage: 71°C bloom, 92°C subsequent pours — barista-confirmed; profile is barista-discretionary, not house-fixed) | O88: Yes — pour 1 is the bloom (barista-confirmed); individual pour weights not captured | P88: Mahlkönig EK43 (98mm Flat Burr) — full-size EK43, explicitly not the EK43S (barista-confirmed) | Q88: 12 | R88: Yuzu | Yellow Floral | Tarragon | S88: PRIMARY SENSORY RECORD (in-cup, blind of the correct bean card): honeysuckle identified on the finish — a direct independent hit on the card's YELLOW FLORAL, named before the correct card was ever seen. Acid read as soft stewed apple, described in the moment as 'like drinking a light apple juice'; no citrus lift, no tarragon, light body, low aromatic intensity throughout. Peach and red currant impressions sat faintly in the background. HOT phase NOT captured — cup delivered already descended; MID to COOL only. RETROSPECTIVE REVISION (post-label, flagged, does not overwrite): on seeing the correct Geisha card, Hari revised the apple read toward yuzu. Methodological note: the original read was made while Hari ALREADY believed the cup was Geisha, making it the less label-influenced of the two accounts; both are retained side by side. ⚠️ CARD DISCREPANCY (Rule 5, resolved): a BOURBON card from the same producer (Stewed Red Apple / Yellow Peach / Red Currant / Demerara) was mis-supplied to the table by the barista. Barista's verbal GEISHA call was correct and subsequently card-confirmed when the correct Geisha card was located. All Bourbon-card data struck from this entry. | T88: TEMPERATURE ISOLATED AS THE SOLE FAILURE VARIABLE — every other controllable was sound. Cone preheated and filter rinsed (barista-confirmed), ratio 1:15 inside the Palate DNA band, EK43 98mm flat burr = benchmark hardware. The ascending two-stage profile OPENS AT 71°C, far below the threshold at which volatile monoterpenes mobilise. Limonene, linalool and gamma-terpinene carry yuzu's identity and require thermal energy both to extract from the bed and to achieve retronasal release; estragole/anethole carry tarragon and behave identically. The first pour — with full access to a fresh bed and the steepest concentration gradient — stripped the fast, low-volatility citric/malic acid fraction while leaving the aromatic fraction behind. What reached the cup was yuzu's ACID SKELETON with its aromatic signature removed, which reads as soft apple. Linalool, least volatile of the group, survived and surfaced as honeysuckle — the surviving aromatic is diagnostic of the deficit's depth. Preheat confirmation EXCLUDES Law 7 thermal mass as a contributing cause, isolating bloom temperature. VENUE PROTOCOL NOTE: barista confirmed the profile is HER OWN, not a fixed house recipe — temperature varies by who is on bar, so the same lot at this venue on a different shift constitutes a valid single-variable comparison. NEW V60 FAILURE MODE FOR THE ARCHIVE: thermal-deficit de-aromatisation — mechanically OPPOSITE to the standing Law 1 conical fines-migration over-extraction pattern. | U88: Solo visit, Pocket by Flip Coffee Roasters, 25 Aug 2026. Second archive visit to this venue (first was Entry #034, 19 May 2026, Ecuador La Papaya Geisha at S$18). Five filter lots on the display wall; pre-visit shortlist ran the Wilder Garcia Geisha first on Palate DNA fit (Washed + Gesha + citrus/floral/stone-fruit), with Kirinyaga Kii Lot 6211 as the paired-comparison candidate and Inmaculada (Natural Anaerobic) and Los Rodriguez (Coco Natural) both declined on ferment load and roast development. Single cup taken; no second cup ordered. RELATIONSHIP EVENT: Marshella, owner of Boon Cafe Dutamas (Duta Mas, West Jakarta, Indonesia), was seated alongside — in Singapore as a visitor, at Pocket seeking Panama coffee, which was unavailable. She identified the mis-supplied bean card and retrieved the correct Geisha card. Extended conversation on the Indonesian coffee context; contacts exchanged by WhatsApp and Hari's 95-venue Singapore café list shared. Standing invitation to visit Boon Cafe — approximately one hour from central Jakarta. FIRST INDONESIAN INDUSTRY CONTACT IN THE ARCHIVE and the first with a café owner rather than a barista. Barista name NOT captured — reserved during the brew, then approached Hari unprompted to ask how the cup was; quoted every parameter precisely and held the correct varietal against a mislabelled card. Capture her name on return. | V88: Live Field Audit — Second Visit | Barista-confirmed: dose, yield, ratio, two-stage temperature profile, pour count, bloom placement, grinder model (full-size EK43, explicitly NOT the EK43S), cone preheat and filter rinse, and that the temperature profile is her own rather than house-fixed | Correct Geisha bean card photographed (region, varietal, elevation, process, roaster notes) | Incorrect Bourbon card also photographed and struck | Brewer geometry directly observed (Hario ceramic conical, black, glass server) | Roast level and roast date NOT captured — logged Unknown per no-inference rule | Venue signage photographed (Pocket by Flip Coffee Roasters) | W88: =IF(OR(ISNUMBER(SEARCH("gesha",G88)),ISNUMBER(SEARCH("geisha",G88))),"⭐ GESHA","") -> ⭐ GESHA | X88: 30 Stevens Rd, #01-08, Singapore 257840
A89: 46260 | B89: Singapore | C89: Pour.traits Roasters | D89: Om Koi, Chiang Mai — Washed Bio Control | E89: Om Koi, Chiang Mai | F89: Om Koi, Chiang Mai, Thailand · 1300 masl | G89: Catuai, Catimor | H89: Washed (Bio Control) | I89: Filter Roast | J89: Unknown (barista busy at lunch service — not confirmed) | K89: Unknown | L89: Unknown | M89: Unknown | N89: Unknown | O89: Unknown | P89: Unknown (barista busy at lunch service — not confirmed) | Q89: 10 | R89: Red Apple, Nectarine, Berries | S89: HOT: Red apple and berries arrive together — apple reads as the white flesh, not the skin (malic acid without tannic/phenolic edge, a clean crisp note). Berries add light anthocyanin brightness. Nectarine not yet present. MID-COOL: Malic-to-citric transition — orange emerges with a slight sourness like a normal orange, with lime hints starting; nectarine and orange blur together (chemically adjacent malic/citric expressions at this band). COOL: Clarity increases — apple and berries recede to the background while brighter aromatic esters move forward; fruity lime-mandarin-orange comes to the foreground, described as 'diluted lime juice' — clean, bright, thin, a clear malic acid hit Harry connects with easily. A fine nectarine note lands at cool phase. Best enjoyed cool. Verdict: very good for the price — an enjoyable, easy cup and the best of the mid-tier entries. Not a top-tier flagship, but a genuinely likeable washed cup that rewards patience as it cools. Archive first: first washed Thailand coffee (previous Thai entries were Natural/Anaerobic — Sirinya Geisha Amarone and Toki); first Catuai/Catimor varietal from Thailand; first Om Koi (Chiang Mai) origin. | T89: Pour.traits in-house roast (Om Koi, Chiang Mai, 1300 masl, Catuai/Catimor, Washed Bio Control). 'Bio Control' processing detail not confirmed with barista (lunch service) — term typically refers to controlled/managed fermentation using selected microbial cultures or biological pest/quality management at the washing station; logged as observed on bean card without over-interpretation. Brew parameters (brewer, grinder, dose, yield, ratio, temperature) all Unknown — barista too busy at lunch to confirm, and per archive integrity rules NOT assumed from prior visits. Sensory arc consistent with a cleanly processed washed coffee: apple/berry structural notes dominant hot, brighter citric/malic esters (lime, mandarin, orange) emerging and moving to foreground as the cup cools — classic washed-process clarity progression. The cool-phase 'diluted lime juice' malic expression is squarely within Harry's documented palate preference. | U89: Lunchtime solo visit — Pour.traits Roasters, Outram Park, Singapore. Tuesday 26 August 2026, ~12:30–13:30 SGT. Repeat visit to Pour.traits (previous entries include: 11 Jul Thailand Sirinya Geisha Amarone; 14 Jul TaoTao WBRC crown entry; 21 Jul Toki). Ordered from the updated in-house filter menu. MENU DISCREPANCY LOGGED: Ethiopia Nensenbo Mewa Washed was printed on the menu but confirmed unavailable by barista Elaine — Om Koi ordered as the top available alternative. Barista Elaine busy during lunch service — brew parameters not confirmed this visit, logged as Unknown per archive integrity rules rather than assumed. | V89: Live Field Audit — bean card photo (Pour.traits Om Koi card, authoritative: Catuai/Catimor, 1300 masl, Washed Bio Control) + Harry's sensory notes. Brew hardware not confirmed (barista busy) — logged Unknown. | W89: =IF(OR(ISNUMBER(SEARCH("gesha",G89)),ISNUMBER(SEARCH("geisha",G89))),"⭐ GESHA","") | X89: 2 Havelock Rd, #01-14, Singapore 059763
A90: 46263 | B90: Singapore | C90: Nylon Coffee Roasters | D90: La Lucuma | E90: Unknown | F90: Peru | G90: Geisha | H90: Washed | I90: Filter Roast | J90: OREA (Flat-Bottom) | K90: Approx 12.5 (barista-stated; exact figure uncertain) | L90: Approx 210–220 (barista-stated; exact figure uncertain) | M90: Slightly less than 1:17 (barista-confirmed — deviation from house standard on the day) | N90: 93°C (Constant — house standard) | O90: Unknown | P90: Mahlkönig EK Omnia (98mm Flat Burr) | Q90: 10 | R90: Kaffir Lime | Yellow Peach | Jasmine | Earl Grey | S90: HOT: Bright and acidic on the tongue. Lime hits immediately. Slight bitter tinge in the aftertaste. Possible trace of peach. Light body, disappears quickly. MID: Brightness and acidity hold without reduction — lime clearly dominant. COOL: Bitter aftertaste develops further even with lime still encapsulated — described as an unripe lime character. POST-CUP: Bitter lime still perceptible in the mouth five minutes after leaving the café — confirmed at 150% certainty. OVERALL: Not bad, but a riper lime would have been more interesting — preference is for sweet-sour over bitter. Rated AVERAGE at S$10. | T90: Bitterness attributed primarily to the green, with ratio as a contributing variable. Barista confirmed the brew ran slightly leaner than the 1:17 house standard on the day (approx 12.5g dose, 210–220g yield — exact figures uncertain), so this is NOT a clean single-variable comparison against the 05 Aug El Romerillo, which used house-standard 1:17 on identical hardware and finished with zero bitter tail. Two factors still point away from extraction as the primary cause: the bitterness was present from the HOT phase rather than emerging on cooling (concentration-driven bitterness typically builds as sweetness contrast fades), and it persisted in the mouth five minutes after the cup — a duration inconsistent with a marginal ratio shift and consistent with compounds structurally bound to the bean. The 'unripe lime' descriptor is diagnostic: bitterness fused to the citrus as pith/rind character, distinct from the flat, dry CGA lactone signature logged on the 08 Jul Natural Bourbon. Most consistent with underripe cherry in the lot — elevated chlorogenic acids and low sugar development, which washed processing conceals nothing of. Extraction physics otherwise near-ideal: Geisha's low bean density gives up volatiles readily at 93°C, and the OREA's wide unrestricted drain keeps contact time short, protecting monoterpenes. GESHA HYPOTHESIS: lime present in HOT and dominant by MID from Peruvian terroir, washed, no Ethiopian lineage — supports citrus as a genetic varietal marker rather than an Ethiopian terroir signature. Yellow peach appeared only as a trace in HOT, consistent with white peach being Guji-specific rather than a universal varietal fingerprint. | U90: Solo visit — 29 Aug 2026. Seventh Nylon audit. Filter menu rotated again since 05 Aug: El Romerillo retained at S$7.50; three new additions — Peru La Lucuma (Geisha/Washed, S$10.00), Ethiopia Banko Gotiti (Dega, Wolisho, Kurume/Washed, S$8.50 — returning lot, previously audited 07 May 2026), Nicaragua Finca Libre (Yellow Catuai/Natural Anaerobic, S$8.50). Colombia El Pinal rotated off. Espresso line: Peru Los Cedros (Caturra/Washed) and Brazil Nossa Senhora Aparecida (Yellow Bourbon/Natural). Seasonal special: Summer Cola espresso tonic, S$8.50. Ordered as a direct test of the open Gesha citrus hypothesis. First Peruvian Geisha in the archive. BARISTA EXCHANGE: Hari raised the bitter aftertaste on the way out; barista appeared surprised, then suggested it could be a bitter lime character that some people perceive — read as accommodation rather than confirmation of a known lot issue. Producer name not obtained. Roast date not logged. | V90: Live Field Audit — Seventh Visit | Barista confirmation (ratio slightly under 1:17 on the day; approximate dose and yield) + menu board photo + house-standard temperature and brewer (barista-confirmed 05 Aug 2026) | W90: =IF(OR(ISNUMBER(SEARCH("gesha",G90)),ISNUMBER(SEARCH("geisha",G90))),"⭐ GESHA","") -> ⭐ GESHA | X90: 4 Everton Park, #01-40, Singapore 080004
A91: 46264 | B91: Singapore | C91: Asylum Coffeehouse | D91: Peru Cajamarca Gesha — Elegant Series (Wilder Garcia) | E91: Wilder Garcia — Farm Cajamarca | F91: Jaen, Cajamarca, Peru | G91: Gesha | H91: Washed | I91: Unknown | J91: Unknown | K91: Unknown | L91: Unknown | M91: Unknown | N91: Unknown | O91: Unknown | P91: Unknown | Q91: 10 | R91: Jasmine | Caramel | Lime | Cacao Nibs | S91: HOT: Stone fruit clarity present; tea-floral hit registers immediately, but individual flavours not yet differentiable — integrated rather than resolved aromatic field. MID: Lime emerges and sugars begin surfacing as acid and sweetness separate. COOL: Caramel and chocolate hints forward, with lime persisting on the aftertaste. Lemon-citrus thread continuous across all three thermal phases. Overall above average and good value for the price paid. Barista recognised Harry from prior visits. Notes written from recall in the evening, not in-cup. | T91: Fifth Wilder Garcia encounter in the archive and the cheapest to date (SGD 10 vs 11 / 12.5 / 12 in Entries #017, #021, #087). Complete card-to-palate alignment — all four official descriptors landed (jasmine to tea-floral, caramel and cacao nibs at cool, lime at mid and aftertaste). Continuous citrus across all three thermal phases on a clean washed Peruvian Gesha with no fermentation confound gives the strongest support yet for the Gesha-citrus-as-genetic-marker hypothesis. Divergence from the nectarine/honey-dominant readings of Entries #071 and #087 (same producer) indicates citrus prominence is preparation- and batch-dependent rather than absent. Brew parameters not captured on the day; logged Unknown per post-#031 rule that sensory record is primary. | U91: Solo visit — Asylum Coffeehouse, Jln Besar. Fifth Asylum audit. Ordered from Elegant Series. Menu also carried Yellow Gesha Natural (La Esmeralda, S$14), Pink Bourbon Honey+Rose Tea (S$14), Castillo Honey+Cherry (S$12), Castillo Honey+Green Apple (S$14), Papayo Washed (S$8), Caturra Natural (S$8), Decaf Fruit Maceration (S$9.50). Barista known from prior visits and recognised Harry. Notes recorded from recall in the evening. DATE CORRECTED to Sunday 30 August 2026. MORNING leg of a two-cup day: Asylum (morning) -> lunch at Super Deluxe -> beer at RedDot -> Oaks Coffee Co. (evening, ~16:30) -> Railway Corridor walk. Companions on the day: Prateek and Alex. | V91: Live Field Audit — Fifth Asylum Visit | Bean card photo (Elegant Series Gesha Washed, Wilder Garcia / Cajamarca / Peru-Jaen, roasted by Asylum Coffee) + menu board photo. Sensory notes from evening recall. Brew parameters not obtained. | W91: =IF(OR(ISNUMBER(SEARCH("gesha",G91)),ISNUMBER(SEARCH("geisha",G91))),"⭐ GESHA","") -> ⭐ GESHA | X91: 311 Jln Besar, Singapore 208970
A92: 46264 | B92: Singapore | C92: Oaks Coffee Co. | D92: Alo Bombe Tadesse | E92: Tamiru Tadesse | F92: Ethiopia | G92: 74158 | H92: Natural | I92: Filter Roast | J92: Origami Dripper (Flat-Bottom) | K92: 15 | L92: 240 | M92: 1:16 | N92: 90 | O92: 4 pours | P92: Option-O Lagom P80 (80mm Flat Burr) | Q92: 9 | R92: Black Grapes; White Peach | S92: Full bodied and bright simultaneously — an unusual pairing driven by extreme-altitude bean density. Complex and fruity with mild fermentative funk that stayed within tolerance. HOT: white peach leads. MID-COOL to COOL: black grape builds and gradually dominates. Peach and grape overlap heavily and resist clean separation, but both clearly present in the cool phase. Best drunk cool. Strong value at SGD 9. | T92: At 2400–2550 MASL this is the highest-altitude lot in the archive; extended cherry maturation raises cell density and sugar/acid concentration, producing simultaneous body and brightness. P80 80mm flat burrs deliver the unimodal particle distribution required to extract evenly from a dense high-altitude bean. Water temperature raised to 90°C (vs 88°C on the Bolivia lactic honey, Entry #051) — a deliberate per-lot adjustment: a dry-process 74158 carries a thermally robust aromatic load that tolerates more extraction force. Four-pour pulsed agitation keeps the dense bed turning over and recovers the deep sugar layer that drives cool-phase improvement. Thermal arc runs INVERTED versus the typical natural: volatile lactone peach hot, anthocyanin grape late. | U92: Third Oaks visit. Sunday 30 August 2026, ~16:30, with Prateek and Alex. Day sequence: coffee at Asylum Coffeehouse (logged as the morning entry, same date) -> lunch at Super Deluxe -> beer at RedDot Brewhouse/Distillery -> Oaks -> Railway Corridor walk. Barista friendly and explained the lot. Menu had fully rotated since 10 Jul: all three Geishas (Janson Lot 930, Santa Barbara Honduras, Finca El Diviso) rolled off; new filter line-up Alo Bombe Tadesse / Mount Totumas Panama Caturra / Floripondio, all SGD 9. ARCHIVE FIRSTS: highest altitude ever logged (2400–2550 MASL); first Tamiru Tadesse producer. WHITE PEACH HYPOTHESIS TEST: peach confirmed present in a 74158 lot. If growing zone confirms as Bensa/Sidama rather than Guji, this weakens the Guji-specific reading and supports white peach as a 74158 varietal marker. DIRECTIONAL ONLY — ester/anthocyanin overlap prevented clean isolation; a washed 74158 would give the single-variable test. | V92: Live field audit — bean card photo + menu photo + barista-confirmed brew parameters | W92: =IF(OR(ISNUMBER(SEARCH("gesha",G92)),ISNUMBER(SEARCH("geisha",G92))),"⭐ GESHA","") | X92: 619H Bukit Timah Road, Singapore 269728
A93: 46266 | B93: Singapore | C93: ECHO | D93: Panama Lerida Estate Geisha Washed — aery x ECHO Bar Takeover (Lim Junghwan) | E93: Lerida Estate (Hacienda La Lerida) | F93: Boquete, Panama | G93: Geisha | H93: Washed | I93: Unknown | J93: UFO Dripper (80° Hybrid Conical — Kenzie Chay & Jay Kim, Korea) | K93: 15 | L93: 240 | M93: 1:16 | N93: 96 | O93: Unknown — 4 pours total; bloom not separated out by barista | P93: Mahlkönig EK43S (98mm Flat Burr) | Q93: 18 | R93: Jasmine; Floral; White Peach | S93: All three official descriptors confirmed. ASCENDING-FLORAL thermal curve — HOT: stone fruit dominant, very light body. MID-COOL: jasmine and floral character climbing. COOL: maximum clarity, peach and jasmine locked together. ZERO CITRUS at any phase. No cool-phase bitterness. Body very light throughout. Unlike anything previously in the archive; S$18 judged worth paying for the encounter and the conversation rather than the liquor alone. | T93: UFO Dripper's 80° interior cone angle (vs V60's 60°) widens and flattens the bed, cutting bed-depth variability and structurally suppressing the fines-migration over-extraction mode of Entries #031/#044; combined with EK43S 98mm flat burrs this delivers flat-bottom-equivalent extraction architecture through a conical-derived vessel. 96°C sits far clear of the ~80°C thermal-deficit threshold, guaranteeing monoterpene mobilisation, and the wide shallow bed absorbs the aggressive 4-pour agitation without CGA-lactone penalty. 15g/240g = high-EY, LOW-TDS liquor: the very light body is an architecture outcome, not a lot deficiency — and matches aery's own stated clarity-led house target. Florals were present in the cup throughout but perception-gated by heat, resolving only below ~55°C; mechanically OPPOSITE to thermal-deficit de-aromatisation, where monoterpenes never leave the grounds at all. | U93: 'aery' x ECHO bar takeover, 11:30-16:30. Arrived ~13:30 straight from afternoon gym; stayed 30-45 min. Served by LIM JUNGHWAN — 2024 Korea National Barista Champion, WBC Finalist, and FOUNDER/CEO of aery (verified: aery company registration lists Lim Junghwan). His English partial; female colleague fluent and translated, and supplied the brew parameters (her '80 degrees so water flow slowly' = the UFO's interior cone angle, not temperature — resolved, not a discrepancy). Extended technical discussion on extraction physics, ratios, the full bean lineup and Gesha. KEY INTEL: aery is based in BUSAN (Jung-gu, Jungang-daero 47), not Seoul; barista reports Busan specialty scene expanding with local government support. Independently corroborated: Busan now framed as Korea's coffee capital, with >90% of Korea's imported coffee clearing customs through Busan Port. Venue already known — Harry was a regular at Kyuukei Coffee next door at 5 Kadayanallur St #01-04. ARCHIVE FIRSTS: first Korean guest barista; first Lerida Estate lot; first UFO Dripper. HYPOTHESIS-CRITICAL: zero citrus in a clean Washed Boquete Geisha at 1,600 masl with every confound controlled (process, ratio, temp, burr, bed geometry) — the strongest counter-evidence yet against Gesha-citrus-as-genetic-marker, and points toward terroir/altitude modulation. Also: white peach confirmed in a Panamanian Geisha, so white peach cannot be treated as an Ethiopian regional marker. Day plan: leave 15:15 for Fluid Collective x Bayu Prawiro takeover, 24 Opal Crescent, 16:00-19:00. OPEN: roast level not stated; bloom not separated from the 4-pour count; S$18 is menu-listed, not receipt-confirmed. | V93: Live field audit — bean card photo + menu photo + barista-confirmed brew parameters (via translating colleague) | W93: =IF(OR(ISNUMBER(SEARCH("gesha",G93)),ISNUMBER(SEARCH("geisha",G93))),"⭐ GESHA","") -> ⭐ GESHA | X93: 5 Kadayanallur Street, #01-08, Singapore 069183
A94: 46266 | B94: Singapore | C94: Fluid Collective | D94: Sumedang Excelsa — Thermal Shock Natural · Bayu Prawiro Bar Takeover | E94: Java Sumedang (West Java) | F94: Indonesia | G94: Excelsa (Coffea Excelsa) | H94: Thermal Shock Natural | I94: Filter Roast | J94: Flat-Bottom Dripper | K94: Unknown | L94: Unknown | M94: Unknown | N94: 75°C → 94°C ASCENDING across 4 pours (barista-confirmed, Bayu Prawiro) | O94: Unknown | P94: Option-O LAGOM 01 (102mm Mizen Blind Burrs — largest flat burr in archive) | Q94: 18 | R94: Funk → Tropical Fruit → Pineapple (no printed note card; Bayu pop-up lot) | S94: AROMA: Opened funky and fermented on the nose, then slowly resolved — tropical fruits emerged as the cup settled. The funk announced itself first and then stepped aside. HOT: Bright with a little funk still present, but tropical fruit already pushing through. MID: Tropical fruit takes over completely; the ferment character recedes. MID-COOL (BEST WINDOW): Pineapple emerges clearly and dominates — really fruity, generous, resolved. This was the peak of the cup and the most enjoyable phase. VERDICT: I liked this, and he did it very well. Amazing experience overall — great discussions with both Ong Shen Choy and Bayu Prawiro. Very satisfied and worth the visit. | T94: ARCHIVE FIRST — SECOND NON-ARABICA SPECIES. Coffea Excelsa (Coffea liberica var. dewevrei lineage) is a distinct species, under 1% of world production and rarely roasted for specialty. Only the second non-Arabica in the archive after the Corner Corner Liberica (Entry #039). ASCENDING TEMPERATURE PROTOCOL — barista-confirmed by Bayu Prawiro: 4 pours, starting LOW at 75°C and climbing to 94°C. This is the exact INVERSE of Fluid's house architecture (70→90→70°C oscillating, or 93°C→65°C descending on the Finca Sophia). The chemistry maps precisely onto the cup experienced: the 75°C opening under-extracts the aggressive fermentation volatiles produced by thermal shock — which is why the funk was present on the nose and first sip but faded rather than built; the 94°C finish then pulls the heavier sugars out of a denser, non-Arabica bean structure, which is why tropical fruit and finally pineapple dominated the mid-cool phase. Funk down, fruit up, by design. LAW 6 AMENDED. Thermal Shock processing previously exceeded this palate's fermentation ceiling at Entry #059 (Finca El Diviso, Aji Bourbon, Oaks) under a DESCENDING protocol. Under an ASCENDING protocol it did not. The controlling variable is brew architecture, not the process itself. GRINDER — ARCHIVE FIRST: Option-O LAGOM 01 with 102mm Mizen blind burrs. Verified per Rule 6 (search-before-logging): official qualified filter grinder of the World Brewers Cup 2026–2029; blind burr format removes screw holes for ~18% more effective grinding surface vs the 98mm standard; independent testing records 0.5g retention and 0.04g standard deviation. Now the LARGEST FLAT BURR in the archive, ahead of the EK43/EK Omnia at 98mm and the Lagom P100 at 100mm. COMPETITION PROVENANCE: this exact coffee — Sumedang Excelsa — formed the final 10% of Bayu Prawiro's blend when he took 1st Runner-Up at the 2025 World Brewers Cup in Jakarta (70% Finca Sophia washed Geisha, 20% Janson Estate Panama anaerobic, 10% Sumedang Excelsa). Both other components appeared on today's pop-up menu, and the Finca Sophia backbone is already a joint #1 cup in this archive (1 Aug 2026, Fluid). | U94: Fluid Collective — BAYU PRAWIRO BAR TAKEOVER, Tuesday 1 September 2026, 4–7pm. Arrived ~17:08, left office early to attend. SECOND EVENT OF THE DAY — followed the aery x ECHO takeover with Lim Junghwan. BOTH CHAMPIONS ON ONE BAR: Bayu Prawiro (2025 World Brewers Cup 1st Runner-Up, Common Grounds Indonesia) brewing alongside Ong Shen Choy (2025 Singapore National Brewers Cup Champion). Extended technical conversations with both — Bayu shared his full 4-pour ascending protocol and grinder choice unprompted. POP-UP MENU: Janson X Geisha Lot 989 Washed (Panama) S$36 · Daterra Aramosa, Coffea Arabica × Coffea Racemosa, 24h Aerobic + 48h Anaerobic Natural (Brazil) S$20 · Aceh Avatara Thermal Anaerobic Natural S$18 · Aceh Avatara Washed S$15 · Sumedang Excelsa Thermal Shock Natural S$18 (ORDERED) · West Java Finca De Berman Pichia Anaerobic Natural S$15. Excelsa chosen over the S$36 Janson Geisha deliberately: species novelty and competition provenance ranked above a fourth premium Panama Geisha in five weeks. BAR PHOTOS CAPTURED: Bayu and Ong Shen working the pass together; Lagom 01 visually confirmed beside Fluid's EK43; retail bags legible — Catur Coffee 'De Berman Pichia' (Pangalengan, West Java, Anaerobic Natural, 2026 crop, 300g) and Java Sumedang 'Excelsa'; Aceh Avatara card notes producer Hendra Mudlim, 1,600 masl, ~30-day slow dry. Three Acaia scales and mint flat-bottom drippers on the brew line. | V94: Live Field Audit — Bayu Prawiro Bar Takeover | Menu + bar + retail bag photos | W94: =IF(OR(ISNUMBER(SEARCH("gesha",G94)),ISNUMBER(SEARCH("geisha",G94))),"⭐ GESHA","") | X94: 24 Opal Cres, Singapore 328418
A95: 46267 | B95: Johor Bahru | C95: Sweet Blossom Coffee Roasters | D95: Guatemala El Injerto "Los Pinos" Geisha Washed — Nas Jaafar Guest Bar Takeover | E95: Finca El Injerto (Aguirre family) | F95: Huehuetenango, Guatemala | G95: Geisha | H95: Washed | I95: Unknown — Nas stated his roasting philosophy (deliberately "slightly indented" vs a typical light roast) but did not name a level for this specific lot | J95: UFO V3 Dripper + UFO type-F paper — HYBRID percolation/immersion achieved by pour timing, NOT by a mechanical valve (no Hario Switch base on the day; barista-confirmed) | K95: 15 | L95: 165 | M95: 1:11 (in-cup, 15g:165g target yield) — 200g water charge = 1:13.3 brew ratio | N95: 92 | O95: No discrete bloom. Two-stage structure: 100g PERCOLATION over 60s, then 100g IMMERSION held 25s, ~10s drawdown. (Brussels routine ran the immersion at 60s on high-flux paper; compressed to 25s today because UFO type-F flows slower.) | P95: Unknown make/model — ground fresh to order by Sweet Blossom baristas off-table and carried to the brew station. Nas worked from a demonstration trestle table with no room for a commercial grinder; he specified, the house executed. Not inferred, not stated by the barista. | Q95: 16 | R95: Jasmine; Peach; Apricot; Pineapple; Brown Sugar | S95: CITRUS FOUND UNPROMPTED IN A LOT THAT CLAIMS NONE. HOT: fruity, everything arriving at once — total intensity rather than resolution, nothing separates. MID: apricot pulls clear of the mass and becomes properly legible. COOL: ORANGE emerges and BUILDS rather than fading, sweet and bright and improving as the cup drops in temperature, with lime underneath it. Overall bright, acidic, FULL BODY, clean lingering aftertaste, ZERO BITTERNESS at any phase. El Injerto's own card lists jasmine / peach / apricot / pineapple / brown sugar and NO citrus of any kind — so the orange and lime were uncontaminated by suggestion. Cleanest configuration the Gesha-citrus hypothesis has ever been tested in. | T95: ARCHIVE FIRSTS — first GUATEMALAN GESHA, first Finca El Injerto lot, first UFO V3 dripper, and the first VALVE-FREE HYBRID IMMERSION in the archive. HARDWARE CLASS: Law 10 covers valve-gated immersion (Entry #086, August Drip, Hario Switch). This is mechanically distinct — the immersion phase is created by POUR TIMING and PAPER PERMEABILITY rather than a mechanical gate, so the bed floods and holds without any valve in the system. CAUSAL CHAIN (barista verbatim, and the most valuable thing said all session): indented roast -> coarser grind required -> coarse grind flows too fast under pure percolation -> ratio drops to 1:13-1:14 to compensate -> immersion stage added to recover the sweetness the fast flow would otherwise lose. Every downstream variable is a compensation for a decision made in the roastery; the tight ratio is a consequence, not a style. RATIO: barista-confirmed 92°C, 200g water charge, 165g target yield at TDS 1.20-1.25 — a true 1:11 IN THE CUP, four full points below the 1:15-1:17 Palate DNA band and deep inside the concentration zone that Law 2 flags for polyphenolic cool-phase bitterness. Zero bitterness delivered. THERMAL INVERSION: citrus emerged COOL rather than hot, the opposite of normal volatile-terpene behaviour — attributable to perceptual masking at very high dissolved-solid concentration clearing as temperature falls, NOT to any property of the lot (repeated in Entry #095 on a different process, which confirms it as a ratio effect). GRIND CHAIN SPLIT: grind is the hinge of Nas's own causal chain, yet he did not operate the grinder — logged as Unknown per Law 4 rather than inferred. | U95: NAS JAAFAR GUEST BAR TAKEOVER — Sweet Blossom Taman Pelangi roastery, Wed 2 Sep 2026. Nas Jaafar: 2026 WORLD BREWERS CUP CHAMPION (Brussels, 27 Jun 2026), first Malaysian to win the title, returning to his home town. Reservation-only, three one-hour slots; Hari booked Slot B (11:45-12:45) deliberately — NOT because Slot A was full, but because a 10:30 start leaves no buffer for the Causeway crossing from Singapore. Spotted via Instagram after following @sweetblossomcoffee on the 22 Aug visit; booked and deposit paid 11 days ahead (S$16.00 by FAST transfer — the roastery accepts SGD, deducted from the order). Café closed to walk-ins for the event. ZERO COFFEE FROM WAKING until 11:45 — deliberate palate protocol; Hiritsu was walked past at 09:26 and deferred to the evening for this reason. Arrived 11:15; Slot A overran. SLOT A DRANK THE ENTIRE HACIENDA LA ESMERALDA BLOCK (Leon 3ANB RM70, Mario Arriba 5FB RM70, Gigante 2ANC RM150) — gone before Slot B was seated. ~22 attendees; nobody asked a question until Hari opened, then asked 3-4 more (ratios, why no blend at competition, life as champion, access to micro lots). Nas answered fully and without condescension. HIS STORY: father a taxi driver, mother at a small charity organisation, money tight growing up; closed his own roastery during COVID and went to work for another roaster; competed pre-COVID and lost before he won. Competition theme RESISTANCE. On competing: he will not encourage anyone to enter if the only reason is to win — you need another reason, go with passion, and the winning takes care of itself. Says he still cannot believe he won; wants time with his two daughters after months of competition travel. Shirt: NAS x FALCON COFFEES (green sourcing partner — explains an 11-lot bar of this calibre in Taman Pelangi). Barista CHEE ran the floor through an overrunning Slot A and a full changeover without it showing. Day sequence: Punggol 07:45 -> JB 09:00 -> Antipodean Gold breakfast -> Lawa Lawa foot spa (time-killer) -> NAS -> Crystal Leaf 90min -> 7 Spice crab chettinad -> Hiritsu -> home 20:20. | V95: Live field audit — printed menu photo + brew-bar photos + barista-confirmed parameters transcribed from Hari's own video recording of Nas Jaafar explaining the recipe | W95: =IF(OR(ISNUMBER(SEARCH("gesha",G95)),ISNUMBER(SEARCH("geisha",G95))),"⭐ GESHA","") -> ⭐ GESHA | X95: 28 Jalan Maju, Taman Pelangi, 80400 Johor Bahru, Malaysia
